Workbook
Name QiddiyaRates: 'Rate Card'!$AA$4:$AA$103
Name GoogleRates: 'Rate Card'!$U$4:$U$103
Name ActualMargin: 'Internal Budget'!$G$250
Name COGSForecast: 'Internal Budget'!$G$240
Name LondonRatesGBP: 'Rate Card'!$AC$3:$AC$103
Name DellRates: 'Rate Card'!$W$4:$W$103
Name IntelRates: 'Rate Card'!$AE$4:$AE$103
Name AmazonRates: 'Rate Card'!$Z$4:$Z$81
Name EmeaRatesEuro: 'Rate Card'!$AB$4:$AB$103
Name MASCosts: 'Internal Budget'!$G$222
Name NorthwellRates: 'Rate Card'!$X$4:$X$103
Name COGSActual: 'Internal Budget'!$G$247
Name OtherClientRates: 'Rate Card'!$V$4:$V$103
Name LinkedInRates: 'Rate Card'!$Y$4:$Y$103
Name LondonDAYRatesGBP: 'Rate Card'!$AD$4:$AD$103
Name ForecastMargin: 'Internal Budget'!$G$239

Sheet Assumptions
B1: ASSUMPTIONS | E1: TEMPLATE VERSION: v5.1324
B3: 1. Fill out each yellow section before moving to the Internal Budget Tab. (The template requires fields are filled out in order to function properly.) 2. Review the budget with the appropriate stakeholders and get final approval from Melissa. The Assumptions tab should be initialed and dated before presenting the budget to the client.
B5: CLICK ALLOW ACCESS -> If yellow, you still need to allow access, if white, you are all set! | C5: =IFERROR(__xludf.DUMMYFUNCTION("(importrange(""https://docs.google.com/spreadsheets/d/1tPdrumQu7yTHPPe3CUfS8G2vUSXAfmvGb7cm2rQihRY/edit#gid=1195252998"",""Importrange Cell!A1""))"),"#REF!") -> #REF!
E7: Budget Approval
B8: Job Code | E8: Melanie Primeaux
B9: Program Name | E9: Approved (Initials)
B10: Client Name | E10: Date
B11: Client Rate Card | E11: Gross Margin Goal
B12: Budget Bracket | E12: Gross Margin Tier
B13: Start Work Date | E13: Gross Margin Goal %
B14: Date of Last Deliverable/Event Date | E14: Gross Margin at Approval
B15: Finance Close (6 weeks post) | C15: =C14+45 -> 45 | E15: Approved (Initials)
B16: Activation State (For Tax Estimate) | E16: Budget Model
B17: Activation Address (For Official Tax Check). List all activation addresses if there are multiple. Example: Evening Event Pier 57, 57 Hudson River Greenway, New York, NY 10011 | E17: Budget Model
E18: Approved (Initials)
E21: Finance Section Only
E22: Pull Actuals or Forecasted | F22: Forecasted
E23: Target Client Budget | F23: ='Internal Budget'!I2
B24: Tell us about the experience: | E24: Client Subtotal | F24: ='Internal Budget'!G227 -> #N/A
B25: Event Details | E25: MAS Internal
B26: Select an event category: | E26: Revenue | F26: ='Internal Budget'!G238 -> #N/A
B27: Select how we won this project: | E27: =iferror(ifs(F27=COGSForecast, "COGS Forecast",F27=COGSActual,"COGS Actual"),"COGS") -> COGS Forecast | F27: =(ifs(F22="Forecasted",COGSForecast, F22="Actual",COGSActual)) -> 0
B28: What type of event is this? (Ex: Conference, Upfront, Dinner, Incentive, Pop-Up, etc.) | E28: =iferror(ifs(E27="COGS Forecast","Gross Margin $$ Forecasted",E27="COGS Actual","Gross Margin $$ Actual"),"Gross Margin $$") -> Gross Margin $$ Forecasted | F28: =F26-F27 -> #N/A
E29: =iferror(ifs(E27="COGS Forecast","Gross Margin %% Forecasted",E27="COGS Actual","Gross Margin %% Actual"),"Gross Margin %%") -> Gross Margin %% Forecasted | F29: =(F26-F27)/F26 -> #N/A
B30: Is this a B2B or B2C event? | E30: Passthrough Total | F30: ='Internal Budget'!G14 -> 0
E31: Made By MAS
B32: How many attendees? | E32: Revenue | F32: =sumif('Internal Budget'!E17:E214,true,'Internal Budget'!G17:G210) -> 0
E33: =iferror(ifs(F33=COGSForecastMadeBy, "COGS Forecast",F33=COGSActualMadeBy,"COGS Actual"),"COGS") -> COGS | F33: =(ifs(F22="Forecasted",'Internal Budget'!G241, F22="Actual",'Internal Budget'!G248)) -> 0
B34: Describe broad-level run of show (ex: keynote, breakouts, reception, etc.) | E34: =iferror(ifs(E33="COGS Forecast","Gross Margin $$ Forecasted",E33="COGS Actual","Gross Margin $$ Actual"),"Gross Margin $$") -> Gross Margin $$ | F34: =F32-F33 -> 0
E35: =iferror(ifs(E33="COGS Forecast","Gross Margin %% Forecasted",E33="COGS Actual","Gross Margin %% Actual"),"Gross Margin %%") -> Gross Margin %% | F35: =(F32-F33)/F32 -> #DIV/0!
B36: Is this a revenue generating program for the client? (I.e. is the client selling tickets?) | E36: Staffing
E37: Freelancer Total Budgeted | F37: ='Internal Budget'!G242 -> #N/A
B38: Project Scope | E38: Freelancer % of Staffing | F38: ='Internal Budget'!G244 -> #N/A
B39: Is a venue already selected or is a venue search in our scope? | E39: Hours
E40: Actual Hours | F40: ='Hours Report'!G1 -> 0
B41: Are we responsible for the registration platform and/or guest travel? | E41: Budgeted Hours | F41: ='Hours Report'!G2 -> 0
E42: % Complete | F42: ='Hours Report'!G3 -> 0
B43: Is there any upfront strategy required? (Ex: Brand ID, event toolkit, etc.) | E43: Insurance and Admininstration
E44: ='Internal Budget'!B207 -> Insurance and Admininstration | F44: ='Internal Budget'!G207 -> 0
B45: Are we responsible for content?
B47: Are we partnering with any other agency? If yes, include agency name.
B49: Staffing
B50: Do we need multiple teams on this event? Explain.
B52: Any special staffing you want to flag?
B54: Any other assumptions you'd like to flag before reviewing the budget?

Sheet Internal Budget
A1: INTERNAL BUDGET | B1: =Assumptions!C9 | C1: Working GM: | F1: Total Revenue: | G1: Client Subtotal: | H1: Client Grand Total: | I1: Target Budget: | J1: Client Budget Link: | K1: Actual GM: | M1: Yellow = Formula was removed
C2: =(G238-G240)/G238 -> #DIV/0! | F2: =G238 -> 0 | G2: =G227 -> 0 | H2: =G229 -> 0 | K2: =G250 -> 0 | M2: Teal = estimated cost, Blue = connected to Expense Tracker
A3: Project Status: | C3: GM Target: | D3: =Assumptions!F13 | I3: FX Rate (FX to USD): | K3: Date of Conversion: | M3: Red = Expense Tracker bucket not set up
A4: Tax Category | B4: Description | C4: OVH | D4: Tax | E4: Made By | F4: Vendor | G4: Client Estimate [DATE] | H4: MAS Internal Budget | I4: Forecast Costs | J4: -/+ Internal - Forcecast | K4: Actual Costs | L4: -/+ Forecast - Actual | M4: Internal Notes | N4: Client Notes [Dates] | O4: Mark Up % | Q4: Guide [Delete column when budget build is complete]
H5: =iferror(if(C5=true,vlookup(B5,'Internal Staffing Calculator'!$B$9:$AK$95,'Internal Staffing Calculator'!L$1,false)*P5,vlookup(B5,'Internal Staffing Calculator'!$B$9:$AK$95,'Internal Staffing Calculator'!L$1,false)*(P5/1.5*1.2285)),"")
A6: PASSTHROUGH COSTS
A7: Line items here are contracted by Client, paid for by MAS.
H8: =iferror(if(C8=true,vlookup(B8,'Internal Staffing Calculator'!$B$9:$AK$95,'Internal Staffing Calculator'!L$1,false)*P8,vlookup(B8,'Internal Staffing Calculator'!$B$9:$AK$95,'Internal Staffing Calculator'!L$1,false)*(P8/1.5*1.2285)),"")
D9: {=iferror(INDEX('Tax Codes'!$I$4:BQ320,MATCH($A9,'Tax Codes'!$B$4:B320,0),MATCH(Assumptions!$C$16,'Tax Codes'!$I$3:$BQ$3,0)),"")} | G9: =(H9*O9) -> 0 | I9: =if(C9=true,0, if(F9="Expense Tracker",sumif('Expense Tracker'!E:E,B9,'Expense Tracker'!D:D),H9)) | J9: =H9-I9 -> 0 | K9: =sumif('Job Report'!I:I,B9,'Job Report'!H:H) -> 0 | L9: =I9-K9 -> 0 | O9: 1
D10: {=iferror(INDEX('Tax Codes'!$I$4:BQ320,MATCH($A10,'Tax Codes'!$B$4:B320,0),MATCH(Assumptions!$C$16,'Tax Codes'!$I$3:$BQ$3,0)),"")} | G10: =(H10*O10) -> 0 | I10: =if(C10=true,0, if(F10="Expense Tracker",sumif('Expense Tracker'!E:E,B10,'Expense Tracker'!D:D),H10)) | J10: =H10-I10 -> 0 | K10: =sumif('Job Report'!I:I,B10,'Job Report'!H:H) -> 0 | L10: =I10-K10 -> 0 | O10: 1
D11: {=iferror(INDEX('Tax Codes'!$I$4:BQ320,MATCH($A11,'Tax Codes'!$B$4:B320,0),MATCH(Assumptions!$C$16,'Tax Codes'!$I$3:$BQ$3,0)),"")} | G11: =(H11*O11) -> 0 | I11: =if(C11=true,0, if(F11="Expense Tracker",sumif('Expense Tracker'!E:E,B11,'Expense Tracker'!D:D),H11)) | J11: =H11-I11 -> 0 | K11: =sumif('Job Report'!I:I,B11,'Job Report'!H:H) -> 0 | L11: =I11-K11 -> 0 | O11: 1
D12: {=iferror(INDEX('Tax Codes'!$I$4:BQ320,MATCH($A12,'Tax Codes'!$B$4:B320,0),MATCH(Assumptions!$C$16,'Tax Codes'!$I$3:$BQ$3,0)),"")} | G12: =(H12*O12) -> 0 | I12: =if(C12=true,0, if(F12="Expense Tracker",sumif('Expense Tracker'!E:E,B12,'Expense Tracker'!D:D),H12)) | J12: =H12-I12 -> 0 | K12: =sumif('Job Report'!I:I,B12,'Job Report'!H:H) -> 0 | L12: =I12-K12 -> 0 | O12: 1
H13: =iferror(if(C13=true,vlookup(B13,'Internal Staffing Calculator'!$B$9:$AK$95,'Internal Staffing Calculator'!L$1,false)*P13,vlookup(B13,'Internal Staffing Calculator'!$B$9:$AK$95,'Internal Staffing Calculator'!L$1,false)*(P13/1.5*1.2285)),"")
F14: Passthrough Costs: | G14: =SUM(G6:G13) -> 0 | H14: =SUM(H6:H13) -> 0 | I14: =SUM(I6:I13) -> 0 | J14: =SUM(J6:J13) -> 0 | K14: =SUM(K6:K13) -> 0 | L14: =SUM(L6:L13) -> 0
A15: MAS COSTS | O15: 1
H16: =iferror(if(C16=true,vlookup(B16,'Internal Staffing Calculator'!$B$9:$AK$95,'Internal Staffing Calculator'!L$1,false)*P16,vlookup(B16,'Internal Staffing Calculator'!$B$9:$AK$95,'Internal Staffing Calculator'!L$1,false)*(P16/1.5*1.2285)),"")
A17: Event Costs
B18: * VENUE SEARCH AND SITE SURVEY | F18: Expense Tracker | H18: - | I18: - | O18: =iferror(vlookup(F18,'Tax Codes'!$B$2:$D$110,3,false)*O$15,"")
A19: Admin | B19: Research and Sourcing | C19: FALSE | D19: {=iferror(INDEX('Tax Codes'!$I$4:BQ320,MATCH($A19,'Tax Codes'!$B$4:B320,0),MATCH(Assumptions!$C$16,'Tax Codes'!$I$3:$BQ$3,0)),"")} | E19: FALSE | G19: =(H19*O19) -> 0 | I19: =if(C19=true,0, if(F19="Expense Tracker",sumif('Expense Tracker'!E:E,B19,'Expense Tracker'!D:D),H19)) | J19: =H19-I19 -> 0 | K19: =sumif('Job Report'!I:I,B19,'Job Report'!H:H) -> 0 | L19: =I19-K19 -> 0 | O19: =iferror(vlookup(A19,'Tax Codes'!$B$2:$D$110,3,false)*O$15,"") -> 1.25 | Q19: 150/HR - TBD depending on number of locations
A20: Travel | B20: Selection Survey | C20: FALSE | D20: {=iferror(INDEX('Tax Codes'!$I$4:BQ320,MATCH($A20,'Tax Codes'!$B$4:B320,0),MATCH(Assumptions!$C$16,'Tax Codes'!$I$3:$BQ$3,0)),"")} | E20: FALSE | G20: =(H20*O20) -> 0 | I20: =if(C20=true,0, if(F20="Expense Tracker",sumif('Expense Tracker'!E:E,B20,'Expense Tracker'!D:D),H20)) | J20: =H20-I20 -> 0 | K20: =sumif('Job Report'!I:I,B20,'Job Report'!H:H) -> 0 | L20: =I20-K20 -> 0 | O20: =iferror(vlookup(A20,'Tax Codes'!$B$2:$D$110,3,false)*O$15,"") -> 1.25 | Q20: Travel $
A21: Travel | B21: Vendor Survey | C21: FALSE | D21: {=iferror(INDEX('Tax Codes'!$I$4:BQ320,MATCH($A21,'Tax Codes'!$B$4:B320,0),MATCH(Assumptions!$C$16,'Tax Codes'!$I$3:$BQ$3,0)),"")} | E21: FALSE | G21: =(H21*O21) -> 0 | I21: =if(C21=true,0, if(F21="Expense Tracker",sumif('Expense Tracker'!E:E,B21,'Expense Tracker'!D:D),H21)) | J21: =H21-I21 -> 0 | K21: =sumif('Job Report'!I:I,B21,'Job Report'!H:H) -> 0 | L21: =I21-K21 -> 0 | O21: =iferror(vlookup(A21,'Tax Codes'!$B$2:$D$110,3,false)*O$15,"") -> 1.25 | Q21: Travel $
B22: * VENUE MANAGEMENT + GUEST SERVICES | H22: - | I22: - | O22: =iferror(vlookup(F22,'Tax Codes'!$B$2:$D$110,3,false)*O$15,"")
A23: Admin | B23: Admin Fees or Required Venue Staff | C23: FALSE | D23: {=iferror(INDEX('Tax Codes'!$I$4:BQ320,MATCH($A23,'Tax Codes'!$B$4:B320,0),MATCH(Assumptions!$C$16,'Tax Codes'!$I$3:$BQ$3,0)),"")} | E23: FALSE | G23: =(H23*O23) -> 0 | I23: =if(C23=true,0, if(F23="Expense Tracker",sumif('Expense Tracker'!E:E,B23,'Expense Tracker'!D:D),H23)) | J23: =H23-I23 -> 0 | K23: =sumif('Job Report'!I:I,B23,'Job Report'!H:H) -> 0 | L23: =I23-K23 -> 0 | O23: =iferror(vlookup(A23,'Tax Codes'!$B$2:$D$110,3,false)*O$15,"") -> 1.25 | Q23: Venue related
A24: Venue Fees | B24: Venue Cost | C24: FALSE | D24: {=iferror(INDEX('Tax Codes'!$I$4:BQ320,MATCH($A24,'Tax Codes'!$B$4:B320,0),MATCH(Assumptions!$C$16,'Tax Codes'!$I$3:$BQ$3,0)),"")} | E24: FALSE | G24: =(H24*O24) -> 0 | I24: =if(C24=true,0, if(F24="Expense Tracker",sumif('Expense Tracker'!E:E,B24,'Expense Tracker'!D:D),H24)) | J24: =H24-I24 -> 0 | K24: =sumif('Job Report'!I:I,B24,'Job Report'!H:H) -> 0 | L24: =I24-K24 -> 0 | O24: =iferror(vlookup(A24,'Tax Codes'!$B$2:$D$110,3,false)*O$15,"") -> 1.25 | Q24: Mark up if client hasn't seen, Include security deposit as part of venue fee, Ensure fee covers more than 10 hour days
A25: Graphics | B25: Barricade Covers | C25: FALSE | D25: {=iferror(INDEX('Tax Codes'!$I$4:BQ320,MATCH($A25,'Tax Codes'!$B$4:B320,0),MATCH(Assumptions!$C$16,'Tax Codes'!$I$3:$BQ$3,0)),"")} | E25: FALSE | G25: =(H25*O25) -> 0 | I25: =if(C25=true,0, if(F25="Expense Tracker",sumif('Expense Tracker'!E:E,B25,'Expense Tracker'!D:D),H25)) | J25: =H25-I25 -> 0 | K25: =sumif('Job Report'!I:I,B25,'Job Report'!H:H) -> 0 | L25: =I25-K25 -> 0 | O25: =iferror(vlookup(A25,'Tax Codes'!$B$2:$D$110,3,false)*O$15,"") -> 1.25
A26: Rentals | B26: Barricades | C26: FALSE | D26: {=iferror(INDEX('Tax Codes'!$I$4:BQ320,MATCH($A26,'Tax Codes'!$B$4:B320,0),MATCH(Assumptions!$C$16,'Tax Codes'!$I$3:$BQ$3,0)),"")} | E26: FALSE | G26: =(H26*O26) -> 0 | I26: =if(C26=true,0, if(F26="Expense Tracker",sumif('Expense Tracker'!E:E,B26,'Expense Tracker'!D:D),H26)) | J26: =H26-I26 -> 0 | K26: =sumif('Job Report'!I:I,B26,'Job Report'!H:H) -> 0 | L26: =I26-K26 -> 0 | O26: =iferror(vlookup(A26,'Tax Codes'!$B$2:$D$110,3,false)*O$15,"") -> 1.25
A27: Rentals | B27: Stanchions | C27: FALSE | D27: {=iferror(INDEX('Tax Codes'!$I$4:BQ320,MATCH($A27,'Tax Codes'!$B$4:B320,0),MATCH(Assumptions!$C$16,'Tax Codes'!$I$3:$BQ$3,0)),"")} | E27: FALSE | G27: =(H27*O27) -> 0 | I27: =if(C27=true,0, if(F27="Expense Tracker",sumif('Expense Tracker'!E:E,B27,'Expense Tracker'!D:D),H27)) | J27: =H27-I27 -> 0 | K27: =sumif('Job Report'!I:I,B27,'Job Report'!H:H) -> 0 | L27: =I27-K27 -> 0 | O27: =iferror(vlookup(A27,'Tax Codes'!$B$2:$D$110,3,false)*O$15,"") -> 1.25
A28: Rentals | B28: Pipe and Drape | C28: FALSE | D28: {=iferror(INDEX('Tax Codes'!$I$4:BQ320,MATCH($A28,'Tax Codes'!$B$4:B320,0),MATCH(Assumptions!$C$16,'Tax Codes'!$I$3:$BQ$3,0)),"")} | E28: FALSE | G28: =(H28*O28) -> 0 | I28: =if(C28=true,0, if(F28="Expense Tracker",sumif('Expense Tracker'!E:E,B28,'Expense Tracker'!D:D),H28)) | J28: =H28-I28 -> 0 | K28: =sumif('Job Report'!I:I,B28,'Job Report'!H:H) -> 0 | L28: =I28-K28 -> 0 | O28: =iferror(vlookup(A28,'Tax Codes'!$B$2:$D$110,3,false)*O$15,"") -> 1.25
A29: Rentals | B29: BOH Set Up | C29: FALSE | D29: {=iferror(INDEX('Tax Codes'!$I$4:BQ320,MATCH($A29,'Tax Codes'!$B$4:B320,0),MATCH(Assumptions!$C$16,'Tax Codes'!$I$3:$BQ$3,0)),"")} | E29: FALSE | G29: =(H29*O29) -> 0 | I29: =if(C29=true,0, if(F29="Expense Tracker",sumif('Expense Tracker'!E:E,B29,'Expense Tracker'!D:D),H29)) | J29: =H29-I29 -> 0 | K29: =sumif('Job Report'!I:I,B29,'Job Report'!H:H) -> 0 | L29: =I29-K29 -> 0 | O29: =iferror(vlookup(A29,'Tax Codes'!$B$2:$D$110,3,false)*O$15,"") -> 1.25
A30: Cleaners | B30: Cleaning | C30: FALSE | D30: {=iferror(INDEX('Tax Codes'!$I$4:BQ320,MATCH($A30,'Tax Codes'!$B$4:B320,0),MATCH(Assumptions!$C$16,'Tax Codes'!$I$3:$BQ$3,0)),"")} | E30: FALSE | G30: =(H30*O30) -> 0 | I30: =if(C30=true,0, if(F30="Expense Tracker",sumif('Expense Tracker'!E:E,B30,'Expense Tracker'!D:D),H30)) | J30: =H30-I30 -> 0 | K30: =sumif('Job Report'!I:I,B30,'Job Report'!H:H) -> 0 | L30: =I30-K30 -> 0 | O30: =iferror(vlookup(A30,'Tax Codes'!$B$2:$D$110,3,false)*O$15,"") -> 1.25
A31: Rentals | B31: Coat Check Set Up | C31: FALSE | D31: {=iferror(INDEX('Tax Codes'!$I$4:BQ320,MATCH($A31,'Tax Codes'!$B$4:B320,0),MATCH(Assumptions!$C$16,'Tax Codes'!$I$3:$BQ$3,0)),"")} | E31: FALSE | G31: =(H31*O31) -> 0 | I31: =if(C31=true,0, if(F31="Expense Tracker",sumif('Expense Tracker'!E:E,B31,'Expense Tracker'!D:D),H31)) | J31: =H31-I31 -> 0 | K31: =sumif('Job Report'!I:I,B31,'Job Report'!H:H) -> 0 | L31: =I31-K31 -> 0 | O31: =iferror(vlookup(A31,'Tax Codes'!$B$2:$D$110,3,false)*O$15,"") -> 1.25 | Q31: Do you need furniture for this? Add in Decor. Otherwise get from Catering or Venue estimate
A32: Unlicensed Labor | B32: Coat Check Staff | C32: FALSE | D32: {=iferror(INDEX('Tax Codes'!$I$4:BQ320,MATCH($A32,'Tax Codes'!$B$4:B320,0),MATCH(Assumptions!$C$16,'Tax Codes'!$I$3:$BQ$3,0)),"")} | E32: FALSE | G32: =(H32*O32) -> 0 | I32: =if(C32=true,0, if(F32="Expense Tracker",sumif('Expense Tracker'!E:E,B32,'Expense Tracker'!D:D),H32)) | J32: =H32-I32 -> 0 | K32: =sumif('Job Report'!I:I,B32,'Job Report'!H:H) -> 0 | L32: =I32-K32 -> 0 | O32: =iferror(vlookup(A32,'Tax Codes'!$B$2:$D$110,3,false)*O$15,"") -> 1.26
A33: Permitting | B33: DOB Permit | C33: FALSE | D33: {=iferror(INDEX('Tax Codes'!$I$4:BQ320,MATCH($A33,'Tax Codes'!$B$4:B320,0),MATCH(Assumptions!$C$16,'Tax Codes'!$I$3:$BQ$3,0)),"")} | E33: FALSE | G33: =(H33*O33) -> 0 | I33: =if(C33=true,0, if(F33="Expense Tracker",sumif('Expense Tracker'!E:E,B33,'Expense Tracker'!D:D),H33)) | J33: =H33-I33 -> 0 | K33: =sumif('Job Report'!I:I,B33,'Job Report'!H:H) -> 0 | L33: =I33-K33 -> 0 | O33: =iferror(vlookup(A33,'Tax Codes'!$B$2:$D$110,3,false)*O$15,"") -> 1.25 | Q33: Get real estimate if needed.
A34: Permitting | B34: Engineer Stamps | C34: FALSE | D34: {=iferror(INDEX('Tax Codes'!$I$4:BQ320,MATCH($A34,'Tax Codes'!$B$4:B320,0),MATCH(Assumptions!$C$16,'Tax Codes'!$I$3:$BQ$3,0)),"")} | E34: FALSE | G34: =(H34*O34) -> 0 | I34: =if(C34=true,0, if(F34="Expense Tracker",sumif('Expense Tracker'!E:E,B34,'Expense Tracker'!D:D),H34)) | J34: =H34-I34 -> 0 | K34: =sumif('Job Report'!I:I,B34,'Job Report'!H:H) -> 0 | L34: =I34-K34 -> 0 | O34: =iferror(vlookup(A34,'Tax Codes'!$B$2:$D$110,3,false)*O$15,"") -> 1.25 | Q34: Engineer Stamps are required for scenery over 10' or for all public-facing events
A35: Permitting | B35: TPA | C35: FALSE | D35: {=iferror(INDEX('Tax Codes'!$I$4:BQ320,MATCH($A35,'Tax Codes'!$B$4:B320,0),MATCH(Assumptions!$C$16,'Tax Codes'!$I$3:$BQ$3,0)),"")} | E35: FALSE | G35: =(H35*O35) -> 0 | I35: =if(C35=true,0, if(F35="Expense Tracker",sumif('Expense Tracker'!E:E,B35,'Expense Tracker'!D:D),H35)) | J35: =H35-I35 -> 0 | K35: =sumif('Job Report'!I:I,B35,'Job Report'!H:H) -> 0 | L35: =I35-K35 -> 0 | O35: =iferror(vlookup(A35,'Tax Codes'!$B$2:$D$110,3,false)*O$15,"") -> 1.25 | Q35: Confirm with venue if TPA needed
A36: Permitting | B36: City and Street Permits | C36: FALSE | D36: {=iferror(INDEX('Tax Codes'!$I$4:BQ320,MATCH($A36,'Tax Codes'!$B$4:B320,0),MATCH(Assumptions!$C$16,'Tax Codes'!$I$3:$BQ$3,0)),"")} | E36: FALSE | G36: =(H36*O36) -> 0 | I36: =if(C36=true,0, if(F36="Expense Tracker",sumif('Expense Tracker'!E:E,B36,'Expense Tracker'!D:D),H36)) | J36: =H36-I36 -> 0 | K36: =sumif('Job Report'!I:I,B36,'Job Report'!H:H) -> 0 | L36: =I36-K36 -> 0 | O36: =iferror(vlookup(A36,'Tax Codes'!$B$2:$D$110,3,false)*O$15,"") -> 1.25 | Q36: Get real estimate
A37: Licensed Labor | B37: Drayage | C37: FALSE | D37: {=iferror(INDEX('Tax Codes'!$I$4:BQ320,MATCH($A37,'Tax Codes'!$B$4:B320,0),MATCH(Assumptions!$C$16,'Tax Codes'!$I$3:$BQ$3,0)),"")} | E37: FALSE | G37: =(H37*O37) -> 0 | I37: =if(C37=true,0, if(F37="Expense Tracker",sumif('Expense Tracker'!E:E,B37,'Expense Tracker'!D:D),H37)) | J37: =H37-I37 -> 0 | K37: =sumif('Job Report'!I:I,B37,'Job Report'!H:H) -> 0 | L37: =I37-K37 -> 0 | O37: =iferror(vlookup(A37,'Tax Codes'!$B$2:$D$110,3,false)*O$15,"") -> 1.26
A38: Rentals | B38: Exec Trailers | C38: FALSE | D38: {=iferror(INDEX('Tax Codes'!$I$4:BQ320,MATCH($A38,'Tax Codes'!$B$4:B320,0),MATCH(Assumptions!$C$16,'Tax Codes'!$I$3:$BQ$3,0)),"")} | E38: FALSE | G38: =(H38*O38) -> 0 | I38: =if(C38=true,0, if(F38="Expense Tracker",sumif('Expense Tracker'!E:E,B38,'Expense Tracker'!D:D),H38)) | J38: =H38-I38 -> 0 | K38: =sumif('Job Report'!I:I,B38,'Job Report'!H:H) -> 0 | L38: =I38-K38 -> 0 | O38: =iferror(vlookup(A38,'Tax Codes'!$B$2:$D$110,3,false)*O$15,"") -> 1.25 | Q38: $2000/day x trailer
A39: Rentals | B39: Portable Restrooms | C39: FALSE | D39: {=iferror(INDEX('Tax Codes'!$I$4:BQ320,MATCH($A39,'Tax Codes'!$B$4:B320,0),MATCH(Assumptions!$C$16,'Tax Codes'!$I$3:$BQ$3,0)),"")} | E39: FALSE | G39: =(H39*O39) -> 0 | I39: =if(C39=true,0, if(F39="Expense Tracker",sumif('Expense Tracker'!E:E,B39,'Expense Tracker'!D:D),H39)) | J39: =H39-I39 -> 0 | K39: =sumif('Job Report'!I:I,B39,'Job Report'!H:H) -> 0 | L39: =I39-K39 -> 0 | O39: =iferror(vlookup(A39,'Tax Codes'!$B$2:$D$110,3,false)*O$15,"") -> 1.25 | Q39: Porta John $300/per; Trailer $2500/day
A40: Heavy Equipment | B40: Heavy Equipment | C40: FALSE | D40: {=iferror(INDEX('Tax Codes'!$I$4:BQ320,MATCH($A40,'Tax Codes'!$B$4:B320,0),MATCH(Assumptions!$C$16,'Tax Codes'!$I$3:$BQ$3,0)),"")} | E40: FALSE | G40: =(H40*O40) -> 0 | I40: =if(C40=true,0, if(F40="Expense Tracker",sumif('Expense Tracker'!E:E,B40,'Expense Tracker'!D:D),H40)) | J40: =H40-I40 -> 0 | K40: =sumif('Job Report'!I:I,B40,'Job Report'!H:H) -> 0 | L40: =I40-K40 -> 0 | O40: =iferror(vlookup(A40,'Tax Codes'!$B$2:$D$110,3,false)*O$15,"") -> 1.3 | Q40: Ask Aaron
A41: Heavy Equipment | B41: Power Distro | C41: FALSE | D41: {=iferror(INDEX('Tax Codes'!$I$4:BQ320,MATCH($A41,'Tax Codes'!$B$4:B320,0),MATCH(Assumptions!$C$16,'Tax Codes'!$I$3:$BQ$3,0)),"")} | E41: FALSE | G41: =(H41*O41) -> 0 | I41: =if(C41=true,0, if(F41="Expense Tracker",sumif('Expense Tracker'!E:E,B41,'Expense Tracker'!D:D),H41)) | J41: =H41-I41 -> 0 | K41: =sumif('Job Report'!I:I,B41,'Job Report'!H:H) -> 0 | L41: =I41-K41 -> 0 | O41: =iferror(vlookup(A41,'Tax Codes'!$B$2:$D$110,3,false)*O$15,"") -> 1.3 | Q41: Ask Aaron
A42: Heavy Equipment | B42: Generator | C42: FALSE | D42: {=iferror(INDEX('Tax Codes'!$I$4:BQ320,MATCH($A42,'Tax Codes'!$B$4:B320,0),MATCH(Assumptions!$C$16,'Tax Codes'!$I$3:$BQ$3,0)),"")} | E42: FALSE | G42: =(H42*O42) -> 0 | I42: =if(C42=true,0, if(F42="Expense Tracker",sumif('Expense Tracker'!E:E,B42,'Expense Tracker'!D:D),H42)) | J42: =H42-I42 -> 0 | K42: =sumif('Job Report'!I:I,B42,'Job Report'!H:H) -> 0 | L42: =I42-K42 -> 0 | O42: =iferror(vlookup(A42,'Tax Codes'!$B$2:$D$110,3,false)*O$15,"") -> 1.3 | Q42: Ask Aaron
A43: Heavy Equipment | B43: Temporary HVAC | C43: FALSE | D43: {=iferror(INDEX('Tax Codes'!$I$4:BQ320,MATCH($A43,'Tax Codes'!$B$4:B320,0),MATCH(Assumptions!$C$16,'Tax Codes'!$I$3:$BQ$3,0)),"")} | E43: FALSE | G43: =(H43*O43) -> 0 | I43: =if(C43=true,0, if(F43="Expense Tracker",sumif('Expense Tracker'!E:E,B43,'Expense Tracker'!D:D),H43)) | J43: =H43-I43 -> 0 | K43: =sumif('Job Report'!I:I,B43,'Job Report'!H:H) -> 0 | L43: =I43-K43 -> 0 | O43: =iferror(vlookup(A43,'Tax Codes'!$B$2:$D$110,3,false)*O$15,"") -> 1.3 | Q43: Ask Aaron
A44: Cleaners | B44: Trash Removal | C44: FALSE | D44: {=iferror(INDEX('Tax Codes'!$I$4:BQ320,MATCH($A44,'Tax Codes'!$B$4:B320,0),MATCH(Assumptions!$C$16,'Tax Codes'!$I$3:$BQ$3,0)),"")} | E44: FALSE | G44: =(H44*O44) -> 0 | I44: =if(C44=true,0, if(F44="Expense Tracker",sumif('Expense Tracker'!E:E,B44,'Expense Tracker'!D:D),H44)) | J44: =H44-I44 -> 0 | K44: =sumif('Job Report'!I:I,B44,'Job Report'!H:H) -> 0 | L44: =I44-K44 -> 0 | O44: =iferror(vlookup(A44,'Tax Codes'!$B$2:$D$110,3,false)*O$15,"") -> 1.25 | Q44: Venue provided or outsourced? You may need multiple pick ups depending on length of event
A45: Security | B45: Security | C45: FALSE | D45: {=iferror(INDEX('Tax Codes'!$I$4:BQ320,MATCH($A45,'Tax Codes'!$B$4:B320,0),MATCH(Assumptions!$C$16,'Tax Codes'!$I$3:$BQ$3,0)),"")} | E45: FALSE | G45: =(H45*O45) -> 0 | I45: =if(C45=true,0, if(F45="Expense Tracker",sumif('Expense Tracker'!E:E,B45,'Expense Tracker'!D:D),H45)) | J45: =H45-I45 -> 0 | K45: =sumif('Job Report'!I:I,B45,'Job Report'!H:H) -> 0 | L45: =I45-K45 -> 0 | O45: =iferror(vlookup(A45,'Tax Codes'!$B$2:$D$110,3,false)*O$15,"") -> 1.25 | Q45: If Google budget 3-12% of budget. Otherwise $50/hr
A46: Internet | B46: Internet | C46: FALSE | D46: {=iferror(INDEX('Tax Codes'!$I$4:BQ320,MATCH($A46,'Tax Codes'!$B$4:B320,0),MATCH(Assumptions!$C$16,'Tax Codes'!$I$3:$BQ$3,0)),"")} | E46: FALSE | G46: =(H46*O46) -> 0 | I46: =if(C46=true,0, if(F46="Expense Tracker",sumif('Expense Tracker'!E:E,B46,'Expense Tracker'!D:D),H46)) | J46: =H46-I46 -> 0 | K46: =sumif('Job Report'!I:I,B46,'Job Report'!H:H) -> 0 | L46: =I46-K46 -> 0 | O46: =iferror(vlookup(A46,'Tax Codes'!$B$2:$D$110,3,false)*O$15,"") -> 1.25 | Q46: Get estimate from TD, Interactive Team, Venue. Google Projects likley need an ETT approved vendor $$
B47: * ONSITE STAFFING | H47: - | I47: - | O47: =iferror(vlookup(F47,'Tax Codes'!$B$2:$D$110,3,false)*O$15,"")
A48: Unlicensed Labor | B48: Scenic Labor | C48: FALSE | D48: {=iferror(INDEX('Tax Codes'!$I$4:BQ320,MATCH($A48,'Tax Codes'!$B$4:B320,0),MATCH(Assumptions!$C$16,'Tax Codes'!$I$3:$BQ$3,0)),"")} | E48: FALSE | G48: =(H48*O48) -> 0 | I48: =if(C48=true,0, if(F48="Expense Tracker",sumif('Expense Tracker'!E:E,B48,'Expense Tracker'!D:D),H48)) | J48: =H48-I48 -> 0 | K48: =sumif('Job Report'!I:I,B48,'Job Report'!H:H) -> 0 | L48: =I48-K48 -> 0 | O48: =iferror(vlookup(A48,'Tax Codes'!$B$2:$D$110,3,false)*O$15,"") -> 1.26 | Q48: TBD
A49: Licensed Labor | B49: AV Labor | C49: FALSE | D49: {=iferror(INDEX('Tax Codes'!$I$4:BQ320,MATCH($A49,'Tax Codes'!$B$4:B320,0),MATCH(Assumptions!$C$16,'Tax Codes'!$I$3:$BQ$3,0)),"")} | E49: FALSE | G49: =(H49*O49) -> 0 | I49: =if(C49=true,0, if(F49="Expense Tracker",sumif('Expense Tracker'!E:E,B49,'Expense Tracker'!D:D),H49)) | J49: =H49-I49 -> 0 | K49: =sumif('Job Report'!I:I,B49,'Job Report'!H:H) -> 0 | L49: =I49-K49 -> 0 | O49: =iferror(vlookup(A49,'Tax Codes'!$B$2:$D$110,3,false)*O$15,"") -> 1.26 | Q49: TBD
A50: Unlicensed Labor | B50: Graphics Install | C50: FALSE | D50: {=iferror(INDEX('Tax Codes'!$I$4:BQ320,MATCH($A50,'Tax Codes'!$B$4:B320,0),MATCH(Assumptions!$C$16,'Tax Codes'!$I$3:$BQ$3,0)),"")} | E50: FALSE | G50: =(H50*O50) -> 0 | I50: =if(C50=true,0, if(F50="Expense Tracker",sumif('Expense Tracker'!E:E,B50,'Expense Tracker'!D:D),H50)) | J50: =H50-I50 -> 0 | K50: =sumif('Job Report'!I:I,B50,'Job Report'!H:H) -> 0 | L50: =I50-K50 -> 0 | O50: =iferror(vlookup(A50,'Tax Codes'!$B$2:$D$110,3,false)*O$15,"") -> 1.26 | Q50: TBD
A51: Unlicensed Labor | B51: Decor Crew/PA's | C51: FALSE | D51: {=iferror(INDEX('Tax Codes'!$I$4:BQ320,MATCH($A51,'Tax Codes'!$B$4:B320,0),MATCH(Assumptions!$C$16,'Tax Codes'!$I$3:$BQ$3,0)),"")} | E51: FALSE | G51: =(H51*O51) -> 0 | I51: =if(C51=true,0, if(F51="Expense Tracker",sumif('Expense Tracker'!E:E,B51,'Expense Tracker'!D:D),H51)) | J51: =H51-I51 -> 0 | K51: =sumif('Job Report'!I:I,B51,'Job Report'!H:H) -> 0 | L51: =I51-K51 -> 0 | O51: =iferror(vlookup(A51,'Tax Codes'!$B$2:$D$110,3,false)*O$15,"") -> 1.26 | Q51: 74x hr x ppl
A52: Unlicensed Labor | B52: Brand Ambassadors | C52: FALSE | D52: {=iferror(INDEX('Tax Codes'!$I$4:BQ320,MATCH($A52,'Tax Codes'!$B$4:B320,0),MATCH(Assumptions!$C$16,'Tax Codes'!$I$3:$BQ$3,0)),"")} | E52: FALSE | G52: =(H52*O52) -> 0 | I52: =if(C52=true,0, if(F52="Expense Tracker",sumif('Expense Tracker'!E:E,B52,'Expense Tracker'!D:D),H52)) | J52: =H52-I52 -> 0 | K52: =sumif('Job Report'!I:I,B52,'Job Report'!H:H) -> 0 | L52: =I52-K52 -> 0 | O52: =iferror(vlookup(A52,'Tax Codes'!$B$2:$D$110,3,false)*O$15,"") -> 1.26 | Q52: 74x hr x ppl
A53: Unlicensed Labor | B53: Product Expert Brand Ambassador | C53: FALSE | D53: {=iferror(INDEX('Tax Codes'!$I$4:BQ320,MATCH($A53,'Tax Codes'!$B$4:B320,0),MATCH(Assumptions!$C$16,'Tax Codes'!$I$3:$BQ$3,0)),"")} | E53: FALSE | G53: =(H53*O53) -> 0 | I53: =if(C53=true,0, if(F53="Expense Tracker",sumif('Expense Tracker'!E:E,B53,'Expense Tracker'!D:D),H53)) | J53: =H53-I53 -> 0 | K53: =sumif('Job Report'!I:I,B53,'Job Report'!H:H) -> 0 | L53: =I53-K53 -> 0 | O53: =iferror(vlookup(A53,'Tax Codes'!$B$2:$D$110,3,false)*O$15,"") -> 1.26 | Q53: 100x hr
A54: Unlicensed Labor | B54: Street Teams | C54: FALSE | D54: {=iferror(INDEX('Tax Codes'!$I$4:BQ320,MATCH($A54,'Tax Codes'!$B$4:B320,0),MATCH(Assumptions!$C$16,'Tax Codes'!$I$3:$BQ$3,0)),"")} | E54: FALSE | G54: =(H54*O54) -> 0 | I54: =if(C54=true,0, if(F54="Expense Tracker",sumif('Expense Tracker'!E:E,B54,'Expense Tracker'!D:D),H54)) | J54: =H54-I54 -> 0 | K54: =sumif('Job Report'!I:I,B54,'Job Report'!H:H) -> 0 | L54: =I54-K54 -> 0 | O54: =iferror(vlookup(A54,'Tax Codes'!$B$2:$D$110,3,false)*O$15,"") -> 1.26 | Q54: 74x hr x ppl
A55: Unlicensed Labor | B55: Photographer | C55: FALSE | D55: {=iferror(INDEX('Tax Codes'!$I$4:BQ320,MATCH($A55,'Tax Codes'!$B$4:B320,0),MATCH(Assumptions!$C$16,'Tax Codes'!$I$3:$BQ$3,0)),"")} | E55: FALSE | G55: =(H55*O55) -> 0 | I55: =if(C55=true,0, if(F55="Expense Tracker",sumif('Expense Tracker'!E:E,B55,'Expense Tracker'!D:D),H55)) | J55: =H55-I55 -> 0 | K55: =sumif('Job Report'!I:I,B55,'Job Report'!H:H) -> 0 | L55: =I55-K55 -> 0 | O55: =iferror(vlookup(A55,'Tax Codes'!$B$2:$D$110,3,false)*O$15,"") -> 1.26 | Q55: 2500/DAY
A56: Unlicensed Labor | B56: Assistant TD | C56: FALSE | D56: {=iferror(INDEX('Tax Codes'!$I$4:BQ320,MATCH($A56,'Tax Codes'!$B$4:B320,0),MATCH(Assumptions!$C$16,'Tax Codes'!$I$3:$BQ$3,0)),"")} | E56: FALSE | G56: =(H56*O56) -> 0 | I56: =if(C56=true,0, if(F56="Expense Tracker",sumif('Expense Tracker'!E:E,B56,'Expense Tracker'!D:D),H56)) | J56: =H56-I56 -> 0 | K56: =sumif('Job Report'!I:I,B56,'Job Report'!H:H) -> 0 | L56: =I56-K56 -> 0 | O56: =iferror(vlookup(A56,'Tax Codes'!$B$2:$D$110,3,false)*O$15,"") -> 1.26 | Q56: 1500/DAY Breakout or overnight manager
A57: Licensed Labor | B57: Lighting Designer | C57: FALSE | D57: {=iferror(INDEX('Tax Codes'!$I$4:BQ320,MATCH($A57,'Tax Codes'!$B$4:B320,0),MATCH(Assumptions!$C$16,'Tax Codes'!$I$3:$BQ$3,0)),"")} | E57: FALSE | G57: =(H57*O57) -> 0 | I57: =if(C57=true,0, if(F57="Expense Tracker",sumif('Expense Tracker'!E:E,B57,'Expense Tracker'!D:D),H57)) | J57: =H57-I57 -> 0 | K57: =sumif('Job Report'!I:I,B57,'Job Report'!H:H) -> 0 | L57: =I57-K57 -> 0 | O57: =iferror(vlookup(A57,'Tax Codes'!$B$2:$D$110,3,false)*O$15,"") -> 1.26 | Q57: $20k+ placeholder
A58: Unlicensed Labor | B58: Show Caller | C58: FALSE | D58: {=iferror(INDEX('Tax Codes'!$I$4:BQ320,MATCH($A58,'Tax Codes'!$B$4:B320,0),MATCH(Assumptions!$C$16,'Tax Codes'!$I$3:$BQ$3,0)),"")} | E58: FALSE | G58: =(H58*O58) -> 0 | I58: =if(C58=true,0, if(F58="Expense Tracker",sumif('Expense Tracker'!E:E,B58,'Expense Tracker'!D:D),H58)) | J58: =H58-I58 -> 0 | K58: =sumif('Job Report'!I:I,B58,'Job Report'!H:H) -> 0 | L58: =I58-K58 -> 0 | O58: =iferror(vlookup(A58,'Tax Codes'!$B$2:$D$110,3,false)*O$15,"") -> 1.26 | Q58: 2000/DAY
A59: Unlicensed Labor | B59: Stage Manager | C59: FALSE | D59: {=iferror(INDEX('Tax Codes'!$I$4:BQ320,MATCH($A59,'Tax Codes'!$B$4:B320,0),MATCH(Assumptions!$C$16,'Tax Codes'!$I$3:$BQ$3,0)),"")} | E59: FALSE | G59: =(H59*O59) -> 0 | I59: =if(C59=true,0, if(F59="Expense Tracker",sumif('Expense Tracker'!E:E,B59,'Expense Tracker'!D:D),H59)) | J59: =H59-I59 -> 0 | K59: =sumif('Job Report'!I:I,B59,'Job Report'!H:H) -> 0 | L59: =I59-K59 -> 0 | O59: =iferror(vlookup(A59,'Tax Codes'!$B$2:$D$110,3,false)*O$15,"") -> 1.26 | Q59: 1500/DAY
A60: Unlicensed Labor | B60: Stagehands | C60: FALSE | D60: {=iferror(INDEX('Tax Codes'!$I$4:BQ320,MATCH($A60,'Tax Codes'!$B$4:B320,0),MATCH(Assumptions!$C$16,'Tax Codes'!$I$3:$BQ$3,0)),"")} | E60: FALSE | G60: =(H60*O60) -> 0 | I60: =if(C60=true,0, if(F60="Expense Tracker",sumif('Expense Tracker'!E:E,B60,'Expense Tracker'!D:D),H60)) | J60: =H60-I60 -> 0 | K60: =sumif('Job Report'!I:I,B60,'Job Report'!H:H) -> 0 | L60: =I60-K60 -> 0 | O60: =iferror(vlookup(A60,'Tax Codes'!$B$2:$D$110,3,false)*O$15,"") -> 1.26 | Q60: 750/DAY (non-union) unless Radar
A61: Unlicensed Labor | B61: Talent Wrangler | C61: FALSE | D61: {=iferror(INDEX('Tax Codes'!$I$4:BQ320,MATCH($A61,'Tax Codes'!$B$4:B320,0),MATCH(Assumptions!$C$16,'Tax Codes'!$I$3:$BQ$3,0)),"")} | E61: FALSE | G61: =(H61*O61) -> 0 | I61: =if(C61=true,0, if(F61="Expense Tracker",sumif('Expense Tracker'!E:E,B61,'Expense Tracker'!D:D),H61)) | J61: =H61-I61 -> 0 | K61: =sumif('Job Report'!I:I,B61,'Job Report'!H:H) -> 0 | L61: =I61-K61 -> 0 | O61: =iferror(vlookup(A61,'Tax Codes'!$B$2:$D$110,3,false)*O$15,"") -> 1.26 | Q61: 1000/DAY unless Radar
A62: Unlicensed Labor | B62: Stylist | C62: FALSE | D62: {=iferror(INDEX('Tax Codes'!$I$4:BQ320,MATCH($A62,'Tax Codes'!$B$4:B320,0),MATCH(Assumptions!$C$16,'Tax Codes'!$I$3:$BQ$3,0)),"")} | E62: FALSE | G62: =(H62*O62) -> 0 | I62: =if(C62=true,0, if(F62="Expense Tracker",sumif('Expense Tracker'!E:E,B62,'Expense Tracker'!D:D),H62)) | J62: =H62-I62 -> 0 | K62: =sumif('Job Report'!I:I,B62,'Job Report'!H:H) -> 0 | L62: =I62-K62 -> 0 | O62: =iferror(vlookup(A62,'Tax Codes'!$B$2:$D$110,3,false)*O$15,"") -> 1.26 | Q62: 1500/DAY
A63: Unlicensed Labor | B63: Hair & Makeup | C63: FALSE | D63: {=iferror(INDEX('Tax Codes'!$I$4:BQ320,MATCH($A63,'Tax Codes'!$B$4:B320,0),MATCH(Assumptions!$C$16,'Tax Codes'!$I$3:$BQ$3,0)),"")} | E63: FALSE | G63: =(H63*O63) -> 0 | I63: =if(C63=true,0, if(F63="Expense Tracker",sumif('Expense Tracker'!E:E,B63,'Expense Tracker'!D:D),H63)) | J63: =H63-I63 -> 0 | K63: =sumif('Job Report'!I:I,B63,'Job Report'!H:H) -> 0 | L63: =I63-K63 -> 0 | O63: =iferror(vlookup(A63,'Tax Codes'!$B$2:$D$110,3,false)*O$15,"") -> 1.26
A64: Software Development | B64: UI/UX Designer | C64: FALSE | D64: {=iferror(INDEX('Tax Codes'!$I$4:BQ320,MATCH($A64,'Tax Codes'!$B$4:B320,0),MATCH(Assumptions!$C$16,'Tax Codes'!$I$3:$BQ$3,0)),"")} | E64: FALSE | G64: =(H64*O64) -> 0 | I64: =if(C64=true,0, if(F64="Expense Tracker",sumif('Expense Tracker'!E:E,B64,'Expense Tracker'!D:D),H64)) | J64: =H64-I64 -> 0 | K64: =sumif('Job Report'!I:I,B64,'Job Report'!H:H) -> 0 | L64: =I64-K64 -> 0 | O64: =iferror(vlookup(A64,'Tax Codes'!$B$2:$D$110,3,false)*O$15,"") -> 1.3
A65: Unlicensed Labor | B65: Director | C65: FALSE | D65: {=iferror(INDEX('Tax Codes'!$I$4:BQ320,MATCH($A65,'Tax Codes'!$B$4:B320,0),MATCH(Assumptions!$C$16,'Tax Codes'!$I$3:$BQ$3,0)),"")} | E65: FALSE | G65: =(H65*O65) -> 0 | I65: =if(C65=true,0, if(F65="Expense Tracker",sumif('Expense Tracker'!E:E,B65,'Expense Tracker'!D:D),H65)) | J65: =H65-I65 -> 0 | K65: =sumif('Job Report'!I:I,B65,'Job Report'!H:H) -> 0 | L65: =I65-K65 -> 0 | O65: =iferror(vlookup(A65,'Tax Codes'!$B$2:$D$110,3,false)*O$15,"") -> 1.26
A66: Unlicensed Labor | B66: Content Manager | C66: FALSE | D66: {=iferror(INDEX('Tax Codes'!$I$4:BQ320,MATCH($A66,'Tax Codes'!$B$4:B320,0),MATCH(Assumptions!$C$16,'Tax Codes'!$I$3:$BQ$3,0)),"")} | E66: FALSE | G66: =(H66*O66) -> 0 | I66: =if(C66=true,0, if(F66="Expense Tracker",sumif('Expense Tracker'!E:E,B66,'Expense Tracker'!D:D),H66)) | J66: =H66-I66 -> 0 | K66: =sumif('Job Report'!I:I,B66,'Job Report'!H:H) -> 0 | L66: =I66-K66 -> 0 | O66: =iferror(vlookup(A66,'Tax Codes'!$B$2:$D$110,3,false)*O$15,"") -> 1.26
A67: Unlicensed Labor | B67: VOG Artist | C67: FALSE | D67: {=iferror(INDEX('Tax Codes'!$I$4:BQ320,MATCH($A67,'Tax Codes'!$B$4:B320,0),MATCH(Assumptions!$C$16,'Tax Codes'!$I$3:$BQ$3,0)),"")} | E67: FALSE | G67: =(H67*O67) -> 0 | I67: =if(C67=true,0, if(F67="Expense Tracker",sumif('Expense Tracker'!E:E,B67,'Expense Tracker'!D:D),H67)) | J67: =H67-I67 -> 0 | K67: =sumif('Job Report'!I:I,B67,'Job Report'!H:H) -> 0 | L67: =I67-K67 -> 0 | O67: =iferror(vlookup(A67,'Tax Codes'!$B$2:$D$110,3,false)*O$15,"") -> 1.26 | Q67: $250-$500
A68: Unlicensed Labor | B68: Copywriter/Script Supervisor | C68: FALSE | D68: {=iferror(INDEX('Tax Codes'!$I$4:BQ320,MATCH($A68,'Tax Codes'!$B$4:B320,0),MATCH(Assumptions!$C$16,'Tax Codes'!$I$3:$BQ$3,0)),"")} | E68: FALSE | G68: =(H68*O68) -> 0 | I68: =if(C68=true,0, if(F68="Expense Tracker",sumif('Expense Tracker'!E:E,B68,'Expense Tracker'!D:D),H68)) | J68: =H68-I68 -> 0 | K68: =sumif('Job Report'!I:I,B68,'Job Report'!H:H) -> 0 | L68: =I68-K68 -> 0 | O68: =iferror(vlookup(A68,'Tax Codes'!$B$2:$D$110,3,false)*O$15,"") -> 1.26
A69: Unlicensed Labor | B69: Site Surveyor | C69: FALSE | D69: {=iferror(INDEX('Tax Codes'!$I$4:BQ320,MATCH($A69,'Tax Codes'!$B$4:B320,0),MATCH(Assumptions!$C$16,'Tax Codes'!$I$3:$BQ$3,0)),"")} | E69: FALSE | G69: =(H69*O69) -> 0 | I69: =if(C69=true,0, if(F69="Expense Tracker",sumif('Expense Tracker'!E:E,B69,'Expense Tracker'!D:D),H69)) | J69: =H69-I69 -> 0 | K69: =sumif('Job Report'!I:I,B69,'Job Report'!H:H) -> 0 | L69: =I69-K69 -> 0 | O69: =iferror(vlookup(A69,'Tax Codes'!$B$2:$D$110,3,false)*O$15,"") -> 1.26
B70: Onsite Supervisor Labor
A71: Unlicensed Labor | B71: Onsite Supervisor Labor - FTE Creative | C71: TRUE | D71: {=iferror(INDEX('Tax Codes'!$I$4:BQ320,MATCH($A71,'Tax Codes'!$B$4:B320,0),MATCH(Assumptions!$C$16,'Tax Codes'!$I$3:$BQ$3,0)),"")} | E71: FALSE | G71: ='Internal Staffing Calculator'!C118 -> #N/A | O71: 1
A72: Unlicensed Labor | B72: Onsite Supervisor Labor - Freelance Creative | C72: FALSE | D72: {=iferror(INDEX('Tax Codes'!$I$4:BQ320,MATCH($A72,'Tax Codes'!$B$4:B320,0),MATCH(Assumptions!$C$16,'Tax Codes'!$I$3:$BQ$3,0)),"")} | E72: FALSE | G72: ='Internal Staffing Calculator'!C119 -> 0 | O72: 1
A73: Unlicensed Labor | B73: Onsite Supervisor Labor - FTE Production | C73: TRUE | D73: {=iferror(INDEX('Tax Codes'!$I$4:BQ320,MATCH($A73,'Tax Codes'!$B$4:B320,0),MATCH(Assumptions!$C$16,'Tax Codes'!$I$3:$BQ$3,0)),"")} | E73: FALSE | G73: ='Internal Staffing Calculator'!C120 -> #N/A | O73: 1
A74: Unlicensed Labor | B74: Onsite Supervisor Labor - Freelance Production | C74: FALSE | D74: {=iferror(INDEX('Tax Codes'!$I$4:BQ320,MATCH($A74,'Tax Codes'!$B$4:B320,0),MATCH(Assumptions!$C$16,'Tax Codes'!$I$3:$BQ$3,0)),"")} | E74: FALSE | G74: ='Internal Staffing Calculator'!C121 -> #N/A | O74: 1
B75: * DESIGN & FABRICATION | H75: - | I75: - | O75: =iferror(vlookup(F75,'Tax Codes'!$B$2:$D$110,3,false)*O$15,"")
A76: Floor Plans | B76: Render and Floorplans - Design & Fab | C76: FALSE | D76: {=iferror(INDEX('Tax Codes'!$I$4:BQ320,MATCH($A76,'Tax Codes'!$B$4:B320,0),MATCH(Assumptions!$C$16,'Tax Codes'!$I$3:$BQ$3,0)),"")} | E76: FALSE | G76: =(H76*O76) -> 0 | I76: =if(C76=true,0, if(F76="Expense Tracker",sumif('Expense Tracker'!E:E,B76,'Expense Tracker'!D:D),H76)) | J76: =H76-I76 -> 0 | K76: =sumif('Job Report'!I:I,B76,'Job Report'!H:H) -> 0 | L76: =I76-K76 -> 0 | O76: =iferror(vlookup(A76,'Tax Codes'!$B$2:$D$110,3,false)*O$15,"") -> 1.25
A77: Licensed Labor | B77: CAD Draughtsman - Fab | C77: FALSE | D77: {=iferror(INDEX('Tax Codes'!$I$4:BQ320,MATCH($A77,'Tax Codes'!$B$4:B320,0),MATCH(Assumptions!$C$16,'Tax Codes'!$I$3:$BQ$3,0)),"")} | E77: FALSE | G77: =(H77*O77) -> 0 | I77: =if(C77=true,0, if(F77="Expense Tracker",sumif('Expense Tracker'!E:E,B77,'Expense Tracker'!D:D),H77)) | J77: =H77-I77 -> 0 | K77: =sumif('Job Report'!I:I,B77,'Job Report'!H:H) -> 0 | L77: =I77-K77 -> 0 | O77: =iferror(vlookup(A77,'Tax Codes'!$B$2:$D$110,3,false)*O$15,"") -> 1.26
A78: Graphics | B78: Exterior Branding | C78: FALSE | D78: {=iferror(INDEX('Tax Codes'!$I$4:BQ320,MATCH($A78,'Tax Codes'!$B$4:B320,0),MATCH(Assumptions!$C$16,'Tax Codes'!$I$3:$BQ$3,0)),"")} | E78: FALSE | G78: =(H78*O78) -> 0 | I78: =if(C78=true,0, if(F78="Expense Tracker",sumif('Expense Tracker'!E:E,B78,'Expense Tracker'!D:D),H78)) | J78: =H78-I78 -> 0 | K78: =sumif('Job Report'!I:I,B78,'Job Report'!H:H) -> 0 | L78: =I78-K78 -> 0 | O78: =iferror(vlookup(A78,'Tax Codes'!$B$2:$D$110,3,false)*O$15,"") -> 1.25
A79: Fabrication | B79: Fabrication | C79: FALSE | D79: {=iferror(INDEX('Tax Codes'!$I$4:BQ320,MATCH($A79,'Tax Codes'!$B$4:B320,0),MATCH(Assumptions!$C$16,'Tax Codes'!$I$3:$BQ$3,0)),"")} | E79: FALSE | G79: =(H79*O79) -> 0 | I79: =if(C79=true,0, if(F79="Expense Tracker",sumif('Expense Tracker'!E:E,B79,'Expense Tracker'!D:D),H79)) | J79: =H79-I79 -> 0 | K79: =sumif('Job Report'!I:I,B79,'Job Report'!H:H) -> 0 | L79: =I79-K79 -> 0 | O79: =iferror(vlookup(A79,'Tax Codes'!$B$2:$D$110,3,false)*O$15,"") -> 1.25
A80: Fabrication | B80: Set Build | C80: FALSE | D80: {=iferror(INDEX('Tax Codes'!$I$4:BQ320,MATCH($A80,'Tax Codes'!$B$4:B320,0),MATCH(Assumptions!$C$16,'Tax Codes'!$I$3:$BQ$3,0)),"")} | E80: FALSE | G80: =(H80*O80) -> 0 | I80: =if(C80=true,0, if(F80="Expense Tracker",sumif('Expense Tracker'!E:E,B80,'Expense Tracker'!D:D),H80)) | J80: =H80-I80 -> 0 | K80: =sumif('Job Report'!I:I,B80,'Job Report'!H:H) -> 0 | L80: =I80-K80 -> 0 | O80: =iferror(vlookup(A80,'Tax Codes'!$B$2:$D$110,3,false)*O$15,"") -> 1.25
A81: Fabrication | B81: Clad for Camera Platforms/Press Riser | C81: FALSE | D81: {=iferror(INDEX('Tax Codes'!$I$4:BQ320,MATCH($A81,'Tax Codes'!$B$4:B320,0),MATCH(Assumptions!$C$16,'Tax Codes'!$I$3:$BQ$3,0)),"")} | E81: FALSE | G81: =(H81*O81) -> 0 | I81: =if(C81=true,0, if(F81="Expense Tracker",sumif('Expense Tracker'!E:E,B81,'Expense Tracker'!D:D),H81)) | J81: =H81-I81 -> 0 | K81: =sumif('Job Report'!I:I,B81,'Job Report'!H:H) -> 0 | L81: =I81-K81 -> 0 | O81: =iferror(vlookup(A81,'Tax Codes'!$B$2:$D$110,3,false)*O$15,"") -> 1.25
A82: Fabrication | B82: FOH and DSM Surrond | C82: FALSE | D82: {=iferror(INDEX('Tax Codes'!$I$4:BQ320,MATCH($A82,'Tax Codes'!$B$4:B320,0),MATCH(Assumptions!$C$16,'Tax Codes'!$I$3:$BQ$3,0)),"")} | E82: FALSE | G82: =(H82*O82) -> 0 | I82: =if(C82=true,0, if(F82="Expense Tracker",sumif('Expense Tracker'!E:E,B82,'Expense Tracker'!D:D),H82)) | J82: =H82-I82 -> 0 | K82: =sumif('Job Report'!I:I,B82,'Job Report'!H:H) -> 0 | L82: =I82-K82 -> 0 | O82: =iferror(vlookup(A82,'Tax Codes'!$B$2:$D$110,3,false)*O$15,"") -> 1.25
A83: Furniture | B83: Registration Furniture | C83: FALSE | D83: {=iferror(INDEX('Tax Codes'!$I$4:BQ320,MATCH($A83,'Tax Codes'!$B$4:B320,0),MATCH(Assumptions!$C$16,'Tax Codes'!$I$3:$BQ$3,0)),"")} | E83: FALSE | G83: =(H83*O83) -> 0 | I83: =if(C83=true,0, if(F83="Expense Tracker",sumif('Expense Tracker'!E:E,B83,'Expense Tracker'!D:D),H83)) | J83: =H83-I83 -> 0 | K83: =sumif('Job Report'!I:I,B83,'Job Report'!H:H) -> 0 | L83: =I83-K83 -> 0 | O83: =iferror(vlookup(A83,'Tax Codes'!$B$2:$D$110,3,false)*O$15,"") -> 1.25
A84: Furniture | B84: Green Room | C84: FALSE | D84: {=iferror(INDEX('Tax Codes'!$I$4:BQ320,MATCH($A84,'Tax Codes'!$B$4:B320,0),MATCH(Assumptions!$C$16,'Tax Codes'!$I$3:$BQ$3,0)),"")} | E84: FALSE | G84: =(H84*O84) -> 0 | I84: =if(C84=true,0, if(F84="Expense Tracker",sumif('Expense Tracker'!E:E,B84,'Expense Tracker'!D:D),H84)) | J84: =H84-I84 -> 0 | K84: =sumif('Job Report'!I:I,B84,'Job Report'!H:H) -> 0 | L84: =I84-K84 -> 0 | O84: =iferror(vlookup(A84,'Tax Codes'!$B$2:$D$110,3,false)*O$15,"") -> 1.25
A85: Furniture | B85: F&B Furniture | C85: FALSE | D85: {=iferror(INDEX('Tax Codes'!$I$4:BQ320,MATCH($A85,'Tax Codes'!$B$4:B320,0),MATCH(Assumptions!$C$16,'Tax Codes'!$I$3:$BQ$3,0)),"")} | E85: FALSE | G85: =(H85*O85) -> 0 | I85: =if(C85=true,0, if(F85="Expense Tracker",sumif('Expense Tracker'!E:E,B85,'Expense Tracker'!D:D),H85)) | J85: =H85-I85 -> 0 | K85: =sumif('Job Report'!I:I,B85,'Job Report'!H:H) -> 0 | L85: =I85-K85 -> 0 | O85: =iferror(vlookup(A85,'Tax Codes'!$B$2:$D$110,3,false)*O$15,"") -> 1.25
A86: Furniture | B86: Seating | C86: FALSE | D86: {=iferror(INDEX('Tax Codes'!$I$4:BQ320,MATCH($A86,'Tax Codes'!$B$4:B320,0),MATCH(Assumptions!$C$16,'Tax Codes'!$I$3:$BQ$3,0)),"")} | E86: FALSE | G86: =(H86*O86) -> 0 | I86: =if(C86=true,0, if(F86="Expense Tracker",sumif('Expense Tracker'!E:E,B86,'Expense Tracker'!D:D),H86)) | J86: =H86-I86 -> 0 | K86: =sumif('Job Report'!I:I,B86,'Job Report'!H:H) -> 0 | L86: =I86-K86 -> 0 | O86: =iferror(vlookup(A86,'Tax Codes'!$B$2:$D$110,3,false)*O$15,"") -> 1.25
A87: Furniture | B87: Charging Solutions | C87: FALSE | D87: {=iferror(INDEX('Tax Codes'!$I$4:BQ320,MATCH($A87,'Tax Codes'!$B$4:B320,0),MATCH(Assumptions!$C$16,'Tax Codes'!$I$3:$BQ$3,0)),"")} | E87: FALSE | G87: =(H87*O87) -> 0 | I87: =if(C87=true,0, if(F87="Expense Tracker",sumif('Expense Tracker'!E:E,B87,'Expense Tracker'!D:D),H87)) | J87: =H87-I87 -> 0 | K87: =sumif('Job Report'!I:I,B87,'Job Report'!H:H) -> 0 | L87: =I87-K87 -> 0 | O87: =iferror(vlookup(A87,'Tax Codes'!$B$2:$D$110,3,false)*O$15,"") -> 1.25
A88: Furniture | B88: Lactation Room/Multi-Faith Room | C88: FALSE | D88: {=iferror(INDEX('Tax Codes'!$I$4:BQ320,MATCH($A88,'Tax Codes'!$B$4:B320,0),MATCH(Assumptions!$C$16,'Tax Codes'!$I$3:$BQ$3,0)),"")} | E88: FALSE | G88: =(H88*O88) -> 0 | I88: =if(C88=true,0, if(F88="Expense Tracker",sumif('Expense Tracker'!E:E,B88,'Expense Tracker'!D:D),H88)) | J88: =H88-I88 -> 0 | K88: =sumif('Job Report'!I:I,B88,'Job Report'!H:H) -> 0 | L88: =I88-K88 -> 0 | O88: =iferror(vlookup(A88,'Tax Codes'!$B$2:$D$110,3,false)*O$15,"") -> 1.25
A89: Furniture | B89: Press Room | C89: FALSE | D89: {=iferror(INDEX('Tax Codes'!$I$4:BQ320,MATCH($A89,'Tax Codes'!$B$4:B320,0),MATCH(Assumptions!$C$16,'Tax Codes'!$I$3:$BQ$3,0)),"")} | E89: FALSE | G89: =(H89*O89) -> 0 | I89: =if(C89=true,0, if(F89="Expense Tracker",sumif('Expense Tracker'!E:E,B89,'Expense Tracker'!D:D),H89)) | J89: =H89-I89 -> 0 | K89: =sumif('Job Report'!I:I,B89,'Job Report'!H:H) -> 0 | L89: =I89-K89 -> 0 | O89: =iferror(vlookup(A89,'Tax Codes'!$B$2:$D$110,3,false)*O$15,"") -> 1.25
A90: Furniture | B90: Greenery/Florals | C90: FALSE | D90: {=iferror(INDEX('Tax Codes'!$I$4:BQ320,MATCH($A90,'Tax Codes'!$B$4:B320,0),MATCH(Assumptions!$C$16,'Tax Codes'!$I$3:$BQ$3,0)),"")} | E90: FALSE | G90: =(H90*O90) -> 0 | I90: =if(C90=true,0, if(F90="Expense Tracker",sumif('Expense Tracker'!E:E,B90,'Expense Tracker'!D:D),H90)) | J90: =H90-I90 -> 0 | K90: =sumif('Job Report'!I:I,B90,'Job Report'!H:H) -> 0 | L90: =I90-K90 -> 0 | O90: =iferror(vlookup(A90,'Tax Codes'!$B$2:$D$110,3,false)*O$15,"") -> 1.25
A91: Furniture | B91: Table Decor/Centerpieces | C91: FALSE | D91: {=iferror(INDEX('Tax Codes'!$I$4:BQ320,MATCH($A91,'Tax Codes'!$B$4:B320,0),MATCH(Assumptions!$C$16,'Tax Codes'!$I$3:$BQ$3,0)),"")} | E91: FALSE | G91: =(H91*O91) -> 0 | I91: =if(C91=true,0, if(F91="Expense Tracker",sumif('Expense Tracker'!E:E,B91,'Expense Tracker'!D:D),H91)) | J91: =H91-I91 -> 0 | K91: =sumif('Job Report'!I:I,B91,'Job Report'!H:H) -> 0 | L91: =I91-K91 -> 0 | O91: =iferror(vlookup(A91,'Tax Codes'!$B$2:$D$110,3,false)*O$15,"") -> 1.25
A92: Furniture | B92: Props | C92: FALSE | D92: {=iferror(INDEX('Tax Codes'!$I$4:BQ320,MATCH($A92,'Tax Codes'!$B$4:B320,0),MATCH(Assumptions!$C$16,'Tax Codes'!$I$3:$BQ$3,0)),"")} | E92: FALSE | G92: =(H92*O92) -> 0 | I92: =if(C92=true,0, if(F92="Expense Tracker",sumif('Expense Tracker'!E:E,B92,'Expense Tracker'!D:D),H92)) | J92: =H92-I92 -> 0 | K92: =sumif('Job Report'!I:I,B92,'Job Report'!H:H) -> 0 | L92: =I92-K92 -> 0 | O92: =iferror(vlookup(A92,'Tax Codes'!$B$2:$D$110,3,false)*O$15,"") -> 1.25
A93: Furniture | B93: Trash Cans | C93: FALSE | D93: {=iferror(INDEX('Tax Codes'!$I$4:BQ320,MATCH($A93,'Tax Codes'!$B$4:B320,0),MATCH(Assumptions!$C$16,'Tax Codes'!$I$3:$BQ$3,0)),"")} | E93: FALSE | G93: =(H93*O93) -> 0 | I93: =if(C93=true,0, if(F93="Expense Tracker",sumif('Expense Tracker'!E:E,B93,'Expense Tracker'!D:D),H93)) | J93: =H93-I93 -> 0 | K93: =sumif('Job Report'!I:I,B93,'Job Report'!H:H) -> 0 | L93: =I93-K93 -> 0 | O93: =iferror(vlookup(A93,'Tax Codes'!$B$2:$D$110,3,false)*O$15,"") -> 1.25
A94: Furniture | B94: Rush Fees Due to Timeline - Fabrication | C94: FALSE | D94: {=iferror(INDEX('Tax Codes'!$I$4:BQ320,MATCH($A94,'Tax Codes'!$B$4:B320,0),MATCH(Assumptions!$C$16,'Tax Codes'!$I$3:$BQ$3,0)),"")} | E94: FALSE | G94: =(H94*O94) -> 0 | I94: =if(C94=true,0, if(F94="Expense Tracker",sumif('Expense Tracker'!E:E,B94,'Expense Tracker'!D:D),H94)) | J94: =H94-I94 -> 0 | K94: =sumif('Job Report'!I:I,B94,'Job Report'!H:H) -> 0 | L94: =I94-K94 -> 0 | O94: =iferror(vlookup(A94,'Tax Codes'!$B$2:$D$110,3,false)*O$15,"") -> 1.25
B95: * CATERING | H95: - | I95: - | O95: =iferror(vlookup(F95,'Tax Codes'!$B$2:$D$110,3,false)*O$15,"")
A96: Catering | B96: Breakfast | C96: FALSE | D96: {=iferror(INDEX('Tax Codes'!$I$4:BQ320,MATCH($A96,'Tax Codes'!$B$4:B320,0),MATCH(Assumptions!$C$16,'Tax Codes'!$I$3:$BQ$3,0)),"")} | E96: FALSE | G96: =(H96*O96) -> 0 | I96: =if(C96=true,0, if(F96="Expense Tracker",sumif('Expense Tracker'!E:E,B96,'Expense Tracker'!D:D),H96)) | J96: =H96-I96 -> 0 | K96: =sumif('Job Report'!I:I,B96,'Job Report'!H:H) -> 0 | L96: =I96-K96 -> 0 | O96: =iferror(vlookup(A96,'Tax Codes'!$B$2:$D$110,3,false)*O$15,"") -> 1.25
A97: Catering | B97: Lunch | C97: FALSE | D97: {=iferror(INDEX('Tax Codes'!$I$4:BQ320,MATCH($A97,'Tax Codes'!$B$4:B320,0),MATCH(Assumptions!$C$16,'Tax Codes'!$I$3:$BQ$3,0)),"")} | E97: FALSE | G97: =(H97*O97) -> 0 | I97: =if(C97=true,0, if(F97="Expense Tracker",sumif('Expense Tracker'!E:E,B97,'Expense Tracker'!D:D),H97)) | J97: =H97-I97 -> 0 | K97: =sumif('Job Report'!I:I,B97,'Job Report'!H:H) -> 0 | L97: =I97-K97 -> 0 | O97: =iferror(vlookup(A97,'Tax Codes'!$B$2:$D$110,3,false)*O$15,"") -> 1.25
A98: Catering | B98: Dinner | C98: FALSE | D98: {=iferror(INDEX('Tax Codes'!$I$4:BQ320,MATCH($A98,'Tax Codes'!$B$4:B320,0),MATCH(Assumptions!$C$16,'Tax Codes'!$I$3:$BQ$3,0)),"")} | E98: FALSE | G98: =(H98*O98) -> 0 | I98: =if(C98=true,0, if(F98="Expense Tracker",sumif('Expense Tracker'!E:E,B98,'Expense Tracker'!D:D),H98)) | J98: =H98-I98 -> 0 | K98: =sumif('Job Report'!I:I,B98,'Job Report'!H:H) -> 0 | L98: =I98-K98 -> 0 | O98: =iferror(vlookup(A98,'Tax Codes'!$B$2:$D$110,3,false)*O$15,"") -> 1.25
A99: Catering | B99: Snacks | C99: FALSE | D99: {=iferror(INDEX('Tax Codes'!$I$4:BQ320,MATCH($A99,'Tax Codes'!$B$4:B320,0),MATCH(Assumptions!$C$16,'Tax Codes'!$I$3:$BQ$3,0)),"")} | E99: FALSE | G99: =(H99*O99) -> 0 | I99: =if(C99=true,0, if(F99="Expense Tracker",sumif('Expense Tracker'!E:E,B99,'Expense Tracker'!D:D),H99)) | J99: =H99-I99 -> 0 | K99: =sumif('Job Report'!I:I,B99,'Job Report'!H:H) -> 0 | L99: =I99-K99 -> 0 | O99: =iferror(vlookup(A99,'Tax Codes'!$B$2:$D$110,3,false)*O$15,"") -> 1.25
A100: Rentals | B100: Catering Rentals | C100: FALSE | D100: {=iferror(INDEX('Tax Codes'!$I$4:BQ320,MATCH($A100,'Tax Codes'!$B$4:B320,0),MATCH(Assumptions!$C$16,'Tax Codes'!$I$3:$BQ$3,0)),"")} | E100: FALSE | G100: =(H100*O100) -> 0 | I100: =if(C100=true,0, if(F100="Expense Tracker",sumif('Expense Tracker'!E:E,B100,'Expense Tracker'!D:D),H100)) | J100: =H100-I100 -> 0 | K100: =sumif('Job Report'!I:I,B100,'Job Report'!H:H) -> 0 | L100: =I100-K100 -> 0 | O100: =iferror(vlookup(A100,'Tax Codes'!$B$2:$D$110,3,false)*O$15,"") -> 1.25
...

Sheet Expense Tracker
A1: EXPENSE TRACKER | B1: Color Key | C1: Estimate Cost | D1: Pulling Totals to Budget | E1: Pulling Budget # to Budget | I1: Link to CC folder:
A3: Description | B3: Vendor | C3: Quantity | D3: Total Cost | E3: Purchaser Name | F3: Order # | G3: Ship to Location | H3: Reconciliation Status | I3: Notes | J3: Budget Line
A4: =if(E14="",E13,E14) | B4: -
J5: =E13
J6: =J5
J7: =J6
J8: =J7
J9: =J8
J10: =J9
J11: =J10
J12: =if(E13<>"",E13,"")
C13: TOTAL | D13: =SUM(D5:D12) -> 0
C14: BUDGET | D14: =if(E14="",sumif('Internal Budget'!B:B,E13,'Internal Budget'!H:H),sumif('Internal Budget'!B:B,E14,'Internal Budget'!H:H)) -> 0
C15: +/- | D15: =D14-D13 -> 0
A16: =if(E26="",E25,E26) | B16: -
J17: =E25
J18: =J17
J19: =J18
J20: =J19
J21: =J20
J22: =J21
J23: =J22
J24: =if(E25<>"",E25,"")
C25: TOTAL | D25: =SUM(D17:D24) -> 0
C26: BUDGET | D26: =if(E26="",sumif('Internal Budget'!B:B,E25,'Internal Budget'!H:H),sumif('Internal Budget'!B:B,E26,'Internal Budget'!H:H)) -> 0
C27: +/- | D27: =D26-D25 -> 0
A28: =if(E38="",E37,E38) | B28: -
J29: =E37
J30: =J29
J31: =J30
J32: =J31
J33: =J32
J34: =J33
J35: =J34
J36: =if(E37<>"",E37,"")
C37: TOTAL | D37: =SUM(D29:D36) -> 0
C38: BUDGET | D38: =if(E38="",sumif('Internal Budget'!B:B,E37,'Internal Budget'!H:H),sumif('Internal Budget'!B:B,E38,'Internal Budget'!H:H)) -> 0
C39: +/- | D39: =D38-D37 -> 0
A40: =if(E50="",E49,E50) | B40: -
J41: =E49
J42: =J41
J43: =J42
J44: =J43
J45: =J44
J46: =J45
J47: =J46
J48: =if(E49<>"",E49,"")
C49: TOTAL | D49: =SUM(D41:D48) -> 0
C50: BUDGET | D50: =if(E50="",sumif('Internal Budget'!B:B,E49,'Internal Budget'!H:H),sumif('Internal Budget'!B:B,E50,'Internal Budget'!H:H)) -> 0
C51: +/- | D51: =D50-D49 -> 0
A52: =if(E62="",E61,E62) | B52: -
J53: =E61
J54: =J53
J55: =J54
J56: =J55
J57: =J56
J58: =J57
J59: =J58
J60: =if(E61<>"",E61,"")
C61: TOTAL | D61: =SUM(D53:D60) -> 0
C62: BUDGET | D62: =if(E62="",sumif('Internal Budget'!B:B,E61,'Internal Budget'!H:H),sumif('Internal Budget'!B:B,E62,'Internal Budget'!H:H)) -> 0
C63: +/- | D63: =D62-D61 -> 0
A64: =if(E74="",E73,E74) | B64: -
J65: =E73
J66: =J65
J67: =J66
J68: =J67
J69: =J68
J70: =J69
J71: =J70
J72: =if(E73<>"",E73,"")
C73: TOTAL | D73: =SUM(D65:D72) -> 0
C74: BUDGET | D74: =if(E74="",sumif('Internal Budget'!B:B,E73,'Internal Budget'!H:H),sumif('Internal Budget'!B:B,E74,'Internal Budget'!H:H)) -> 0
C75: +/- | D75: =D74-D73 -> 0
A76: =if(E86="",E85,E86) | B76: -
J77: =E85
J78: =J77
J79: =J78
J80: =J79
J81: =J80
J82: =J81
J83: =J82
J84: =if(E85<>"",E85,"")
C85: TOTAL | D85: =SUM(D77:D84) -> 0
C86: BUDGET | D86: =if(E86="",sumif('Internal Budget'!B:B,E85,'Internal Budget'!H:H),sumif('Internal Budget'!B:B,E86,'Internal Budget'!H:H)) -> 0
C87: +/- | D87: =D86-D85 -> 0
A88: =if(E98="",E97,E98) | B88: -
J89: =E97
J90: =J89
J91: =J90
J92: =J91
J93: =J92
J94: =J93
J95: =J94
J96: =if(E97<>"",E97,"")
C97: TOTAL | D97: =SUM(D89:D96) -> 0
C98: BUDGET | D98: =if(E98="",sumif('Internal Budget'!B:B,E97,'Internal Budget'!H:H),sumif('Internal Budget'!B:B,E98,'Internal Budget'!H:H)) -> 0
C99: +/- | D99: =D98-D97 -> 0
A100: =if(E110="",E109,E110) | B100: -
J101: =E109
...

Sheet Job Report
C1: JOB REPORT | F1: Forecast Total | G1: ='Internal Budget'!G240 -> 0 | H1: Forecast total (or "budget total") = the expenses you've been tracking in your budget or expense tracker Actuals total = when your job report is reconciled, your Actuals Column should equal Column F (make sure each line item in your budget is unique, no duplicates or it will count the $ twice) Job report = sum of the "Charges" (column E). Do not edit the amounts in this column! Charges Broken Out = should equal the job report (make sure you've delete the original charges in Column F after breaking them out) Once you have selected a budget line for each charge your actuals total = column F = job report total (forecast total shouldn't be far off)
C2: RECLASSED | F2: Actuals Total | G2: ='Internal Budget'!G249 -> 0
C3: ORIGINAL CHARGE | F3: Job Report Total | G3: =SUM(G6:G960) -> 0
C4: BROKEN OUT CHARGES | F4: Charges Broken Out | G4: =SUM(H6:H960) -> 0
A5: Account No | B5: Item ID | C5: Date | D5: Invoice # | E5: Description | F5: Purchaser | G5: Charges | H5: Charges Broken Out | I5: Budget Line Item | J5: Status | K5: Notes
E6: <- Do not edit columns in red ->
H7: =G7
H8: =G8
H9: =G9
H10: =G10
H11: =G11
H12: =G12
H13: =G13
H14: =G14
H15: =G15
H16: =G16
H17: =G17
H18: =G18
... H1063: =G1063

Sheet Internal Staffing Calculator
R1: 3 | S1: =R1+1 -> 4 | T1: =S1+1 -> 5 | U1: =T1+1 -> 6 | V1: =U1+1 -> 7 | W1: =V1+1 -> 8 | X1: =W1+1 -> 9 | Y1: =X1+1 -> 10 | Z1: =Y1+1 -> 11 | ... BL1: =BK1+1 -> 49
A2: STAFFING CALCULATOR | F2: ='Internal Budget'!G221 -> #N/A | H2: Gross Margin: | I2: Total Revenue: | M2: G | S2: * If your project runs longer than 40 weeks please contact Lindsay and Anna B | AQ2: Start Date | AT2: Event Date | AW2: Pre-Pro Weeks | AZ2: Staffing Tolerance: | BC2: Current Staffing %:
A3: =Assumptions!C11 | B3: Staffing Type: | H3: =('Internal Budget'!G238-'Internal Budget'!G240)/'Internal Budget'!G238 -> #DIV/0! | I3: ='Internal Budget'!G238 -> 0 | AQ3: =Assumptions!C13 | AT3: =Assumptions!C14 | AW3: =((AQ3-AT3)/7)-1 -> -1 | AZ3: =iferror(Controls!E9,"") | BC3: ='Internal Budget'!G245 -> 0
B4: All Staffing in Staffing Section
A5: =Assumptions!C12 | E5: TOTALS | F5: =sum(F8:F114) -> #N/A | G5: =sum(G8:G114) -> 0 | H5: =sum(H8:H114) -> 0 | I5: =sum(I8:I114) -> 0 | J5: =sum(J8:J114) -> 0 | K5: =sum(K8:K114) -> 0 | L5: =sum(L8:L114) -> 0 | M5: =sum(M8:M114) -> 0 | N5: =sum(N8:N114) -> 0 | O5: =sum(O8:O96) -> #N/A | P5: =sum(P8:P114) -> 0 | R5: =iferror(S5-WEEKDAY(S5,3)-7,"") -> -12 | S5: =iferror(T5-WEEKDAY(T5,3)-7,"") | T5: =iferror(U5-WEEKDAY(U5,3)-7,"") -> -12 | U5: =iferror(V5-WEEKDAY(V5,3)-7,"") | V5: =iferror(W5-WEEKDAY(W5,3)-7,"") -> -12 | W5: =iferror(X5-WEEKDAY(X5,3)-7,"") | X5: =iferror(Y5-WEEKDAY(Y5,3)-7,"") -> -12 | Y5: =iferror(Z5-WEEKDAY(Z5,3)-7,"") | ... BE5: =iferror(BF5-WEEKDAY(BF5,3)-7,"") | BF5: =iferror(AT3-WEEKDAY(AT3,3),"") -> -5 | BG5: =BF5+7 -> 2 | BH5: =BG5+7 -> 9 | BI5: =BH5+7 -> 16 | BJ5: =BI5+7 -> 23 | BK5: =BJ5+7 -> 30 | BL5: =BK5+7 -> 37
A7: Department | B7: Role | C7: FTE | D7: X | E7: Name | F7: Client | G7: Internal | H7: Forecast | I7: +/- | J7: Actuals | K7: +/- | L7: Total Hours Pre-pro + Onsite | M7: Verve (Below) | N7: Onsite Hours Onsite Only | O7: Onsite Client | P7: Reduced Hours Total - Onsite | R7: -40 | S7: -39 | T7: -38 | U7: -37 | V7: -36 | W7: -35 | X7: -34 | Y7: -33 | Z7: -32 | AA7: -31 | AB7: -30 | AC7: -29 | AD7: -28 | AE7: -27 | AF7: -26 | AG7: -25 | AH7: -24 | AI7: -23 | AJ7: -22 | AK7: -21 | AL7: -20 | AM7: -19 | AN7: -18 | AO7: -17 | AP7: -16 | AQ7: -15 | AR7: -14 | AS7: -13 | AT7: -12 | AU7: -11 | AV7: -10 | AW7: -9 | AX7: -8 | AY7: -7 | AZ7: -6 | BA7: -5 | BB7: -4 | BC7: -3 | BD7: -2 | BE7: -1 | BF7: 0 | BG7: 1 | BH7: 2 | BI7: 3 | BJ7: 4 | BK7: 5 | BL7: 6 | BM7: Client Role | BN7: =Assumptions!C11
A8: LEADERSHIP
A9: Other | B9: President | C9: TRUE | E9: =if(D9="x","Needs Staffing","") | F9: =(L9-N9)*BN9 -> #N/A | G9: =iferror(if(C9=true,0,(L9*(BN9/1.55*1.2285))),"") -> 0 | H9: =G9 -> 0 | I9: =G9-H9 -> 0 | J9: =sumif('Job Report'!I:I,B9,'Job Report'!H:H) -> 0 | K9: =if(C9=false,H9-J9,0) -> 0 | L9: =SUM(R9:BL9) -> 0 | P9: =L9-N9 -> 0 | R9: =if($D9="X",vlookup($B9,'Hours Spread - Filtered'!$B:$AX,R$1,false),"") | S9: =if($D9="X",vlookup($B9,'Hours Spread - Filtered'!$B:$AX,S$1,false),"") | T9: =if($D9="X",vlookup($B9,'Hours Spread - Filtered'!$B:$AX,T$1,false),"") | U9: =if($D9="X",vlookup($B9,'Hours Spread - Filtered'!$B:$AX,U$1,false),"") | V9: =if($D9="X",vlookup($B9,'Hours Spread - Filtered'!$B:$AX,V$1,false),"") | W9: =if($D9="X",vlookup($B9,'Hours Spread - Filtered'!$B:$AX,W$1,false),"") | X9: =if($D9="X",vlookup($B9,'Hours Spread - Filtered'!$B:$AX,X$1,false),"") | Y9: =if($D9="X",vlookup($B9,'Hours Spread - Filtered'!$B:$AX,Y$1,false),"") | ... BL9: =if($D9="X",vlookup($B9,'Hours Spread - Filtered'!$B:$AX,BL$1,false),"") | BM9: {=IFERROR(index('Rate Card'!U$3:AF135,match(B9,'Rate Card'!A$3:A135,0),match(Assumptions!C$11,'Rate Card'!U$2:AF$2,0)),"")} | BN9: {=(index('Rate Card'!$C$4:$T135, match(BM9,Controls!H$21:H135,0),match(Assumptions!$C$11,'Rate Card'!C$2:T$2,0)))} -> #N/A
A10: Other | B10: COO | C10: TRUE | E10: =if(D10="x","Needs Staffing","") | F10: =(L10-N10)*BN10 -> #N/A | G10: =iferror(if(C10=true,0,(L10*(BN10/1.55*1.2285))),"") -> 0 | H10: =G10 -> 0 | I10: =G10-H10 -> 0 | J10: =sumif('Job Report'!I:I,B10,'Job Report'!H:H) -> 0 | K10: =if(C10=false,H10-J10,0) -> 0 | L10: =SUM(R10:BL10) -> 0 | P10: =L10-N10 -> 0 | R10: =if($D10="X",vlookup($B10,'Hours Spread - Filtered'!$B:$AX,R$1,false),"") | S10: =if($D10="X",vlookup($B10,'Hours Spread - Filtered'!$B:$AX,S$1,false),"") | T10: =if($D10="X",vlookup($B10,'Hours Spread - Filtered'!$B:$AX,T$1,false),"") | U10: =if($D10="X",vlookup($B10,'Hours Spread - Filtered'!$B:$AX,U$1,false),"") | V10: =if($D10="X",vlookup($B10,'Hours Spread - Filtered'!$B:$AX,V$1,false),"") | W10: =if($D10="X",vlookup($B10,'Hours Spread - Filtered'!$B:$AX,W$1,false),"") | X10: =if($D10="X",vlookup($B10,'Hours Spread - Filtered'!$B:$AX,X$1,false),"") | Y10: =if($D10="X",vlookup($B10,'Hours Spread - Filtered'!$B:$AX,Y$1,false),"") | ... BL10: =if($D10="X",vlookup($B10,'Hours Spread - Filtered'!$B:$AX,BL$1,false),"") | BM10: {=IFERROR(index('Rate Card'!U$3:AF135,match(B10,'Rate Card'!A$3:A135,0),match(Assumptions!C$11,'Rate Card'!U$2:AF$2,0)),"")} | BN10: {=(index('Rate Card'!$C$4:$T135, match(BM10,Controls!H$21:H135,0),match(Assumptions!$C$11,'Rate Card'!C$2:T$2,0)))} -> #N/A
A11: Other | B11: CXO | C11: TRUE | E11: =if(D11="x","Needs Staffing","") | F11: =(L11-N11)*BN11 -> #N/A | G11: =iferror(if(C11=true,0,(L11*(BN11/1.55*1.2285))),"") -> 0 | H11: =G11 -> 0 | I11: =G11-H11 -> 0 | J11: =sumif('Job Report'!I:I,B11,'Job Report'!H:H) -> 0 | K11: =if(C11=false,H11-J11,0) -> 0 | L11: =SUM(R11:BL11) -> 0 | P11: =L11-N11 -> 0 | R11: =if($D11="X",vlookup($B11,'Hours Spread - Filtered'!$B:$AX,R$1,false),"") | S11: =if($D11="X",vlookup($B11,'Hours Spread - Filtered'!$B:$AX,S$1,false),"") | T11: =if($D11="X",vlookup($B11,'Hours Spread - Filtered'!$B:$AX,T$1,false),"") | U11: =if($D11="X",vlookup($B11,'Hours Spread - Filtered'!$B:$AX,U$1,false),"") | V11: =if($D11="X",vlookup($B11,'Hours Spread - Filtered'!$B:$AX,V$1,false),"") | W11: =if($D11="X",vlookup($B11,'Hours Spread - Filtered'!$B:$AX,W$1,false),"") | X11: =if($D11="X",vlookup($B11,'Hours Spread - Filtered'!$B:$AX,X$1,false),"") | Y11: =if($D11="X",vlookup($B11,'Hours Spread - Filtered'!$B:$AX,Y$1,false),"") | ... BL11: =if($D11="X",vlookup($B11,'Hours Spread - Filtered'!$B:$AX,BL$1,false),"") | BM11: {=IFERROR(index('Rate Card'!U$3:AF135,match(B11,'Rate Card'!A$3:A135,0),match(Assumptions!C$11,'Rate Card'!U$2:AF$2,0)),"")} | BN11: {=(index('Rate Card'!$C$4:$T135, match(BM11,Controls!H$21:H135,0),match(Assumptions!$C$11,'Rate Card'!C$2:T$2,0)))} -> #N/A
A12: ACCOUNTS | R12: =if($D12="X",vlookup($B12,'Hours Spread - Filtered'!$B:$AX,R$1,false),"") | S12: =if($D12="X",vlookup($B12,'Hours Spread - Filtered'!$B:$AX,S$1,false),"") | T12: =if($D12="X",vlookup($B12,'Hours Spread - Filtered'!$B:$AX,T$1,false),"") | U12: =if($D12="X",vlookup($B12,'Hours Spread - Filtered'!$B:$AX,U$1,false),"") | V12: =if($D12="X",vlookup($B12,'Hours Spread - Filtered'!$B:$AX,V$1,false),"") | W12: =if($D12="X",vlookup($B12,'Hours Spread - Filtered'!$B:$AX,W$1,false),"") | X12: =if($D12="X",vlookup($B12,'Hours Spread - Filtered'!$B:$AX,X$1,false),"") | Y12: =if($D12="X",vlookup($B12,'Hours Spread - Filtered'!$B:$AX,Y$1,false),"") | ... BL12: =if($D12="X",vlookup($B12,'Hours Spread - Filtered'!$B:$AX,BL$1,false),"")
A13: Accounts | B13: SVP Accounts | C13: TRUE | E13: =if(D13="x","Needs Staffing","") | F13: =(L13-N13)*BN13 -> #N/A | G13: =iferror(if(C13=true,0,(L13*(BN13/1.55*1.2285))),"") -> 0 | H13: =G13 -> 0 | I13: =G13-H13 -> 0 | J13: =sumif('Job Report'!I:I,B13,'Job Report'!H:H) -> 0 | K13: =if(C13=false,H13-J13,0) -> 0 | L13: =SUM(R13:BL13) -> 0 | P13: =L13-N13 -> 0 | R13: =if($D13="X",vlookup($B13,'Hours Spread - Filtered'!$B:$AX,R$1,false),"") | S13: =if($D13="X",vlookup($B13,'Hours Spread - Filtered'!$B:$AX,S$1,false),"") | T13: =if($D13="X",vlookup($B13,'Hours Spread - Filtered'!$B:$AX,T$1,false),"") | U13: =if($D13="X",vlookup($B13,'Hours Spread - Filtered'!$B:$AX,U$1,false),"") | V13: =if($D13="X",vlookup($B13,'Hours Spread - Filtered'!$B:$AX,V$1,false),"") | W13: =if($D13="X",vlookup($B13,'Hours Spread - Filtered'!$B:$AX,W$1,false),"") | X13: =if($D13="X",vlookup($B13,'Hours Spread - Filtered'!$B:$AX,X$1,false),"") | Y13: =if($D13="X",vlookup($B13,'Hours Spread - Filtered'!$B:$AX,Y$1,false),"") | ... BL13: =if($D13="X",vlookup($B13,'Hours Spread - Filtered'!$B:$AX,BL$1,false),"") | BM13: {=IFERROR(index('Rate Card'!U$3:AF135,match(B13,'Rate Card'!A$3:A135,0),match(Assumptions!C$11,'Rate Card'!U$2:AF$2,0)),"")} | BN13: {=(index('Rate Card'!$C$4:$T135, match(BM13,Controls!H$21:H135,0),match(Assumptions!$C$11,'Rate Card'!C$2:T$2,0)))} -> #N/A
A14: Accounts | B14: Accounts Director | C14: TRUE | E14: =if(D14="x","Needs Staffing","") | F14: =(L14-N14)*BN14 -> #N/A | G14: =iferror(if(C14=true,0,(L14*(BN14/1.55*1.2285))),"") -> 0 | H14: =G14 -> 0 | I14: =G14-H14 -> 0 | J14: =sumif('Job Report'!I:I,B14,'Job Report'!H:H) -> 0 | K14: =if(C14=false,H14-J14,0) -> 0 | L14: =SUM(R14:BL14) -> 0 | P14: =L14-N14 -> 0 | R14: =if($D14="X",vlookup($B14,'Hours Spread - Filtered'!$B:$AX,R$1,false),"") | S14: =if($D14="X",vlookup($B14,'Hours Spread - Filtered'!$B:$AX,S$1,false),"") | T14: =if($D14="X",vlookup($B14,'Hours Spread - Filtered'!$B:$AX,T$1,false),"") | U14: =if($D14="X",vlookup($B14,'Hours Spread - Filtered'!$B:$AX,U$1,false),"") | V14: =if($D14="X",vlookup($B14,'Hours Spread - Filtered'!$B:$AX,V$1,false),"") | W14: =if($D14="X",vlookup($B14,'Hours Spread - Filtered'!$B:$AX,W$1,false),"") | X14: =if($D14="X",vlookup($B14,'Hours Spread - Filtered'!$B:$AX,X$1,false),"") | Y14: =if($D14="X",vlookup($B14,'Hours Spread - Filtered'!$B:$AX,Y$1,false),"") | ... BL14: =if($D14="X",vlookup($B14,'Hours Spread - Filtered'!$B:$AX,BL$1,false),"") | BM14: {=IFERROR(index('Rate Card'!U$3:AF135,match(B14,'Rate Card'!A$3:A135,0),match(Assumptions!C$11,'Rate Card'!U$2:AF$2,0)),"")} | BN14: {=(index('Rate Card'!$C$4:$T135, match(BM14,Controls!H$21:H135,0),match(Assumptions!$C$11,'Rate Card'!C$2:T$2,0)))} -> #N/A
A15: Accounts | B15: Accounts Manager | C15: TRUE | F15: =(L15-N15)*BN15 -> #N/A | G15: =iferror(if(C15=true,0,(L15*(BN15/1.55*1.2285))),"") -> 0 | H15: =G15 -> 0 | I15: =G15-H15 -> 0 | J15: =sumif('Job Report'!I:I,B15,'Job Report'!H:H) -> 0 | K15: =if(C15=false,H15-J15,0) -> 0 | L15: =SUM(R15:BL15) -> 0 | P15: =L15-N15 -> 0 | R15: =if($D15="X",vlookup($B15,'Hours Spread - Filtered'!$B:$AX,R$1,false),"") | S15: =if($D15="X",vlookup($B15,'Hours Spread - Filtered'!$B:$AX,S$1,false),"") | T15: =if($D15="X",vlookup($B15,'Hours Spread - Filtered'!$B:$AX,T$1,false),"") | U15: =if($D15="X",vlookup($B15,'Hours Spread - Filtered'!$B:$AX,U$1,false),"") | V15: =if($D15="X",vlookup($B15,'Hours Spread - Filtered'!$B:$AX,V$1,false),"") | W15: =if($D15="X",vlookup($B15,'Hours Spread - Filtered'!$B:$AX,W$1,false),"") | X15: =if($D15="X",vlookup($B15,'Hours Spread - Filtered'!$B:$AX,X$1,false),"") | Y15: =if($D15="X",vlookup($B15,'Hours Spread - Filtered'!$B:$AX,Y$1,false),"") | ... BL15: =if($D15="X",vlookup($B15,'Hours Spread - Filtered'!$B:$AX,BL$1,false),"") | BM15: {=IFERROR(index('Rate Card'!U$3:AF135,match(B15,'Rate Card'!A$3:A135,0),match(Assumptions!C$11,'Rate Card'!U$2:AF$2,0)),"")} | BN15: {=(index('Rate Card'!$C$4:$T135, match(BM15,Controls!H$21:H135,0),match(Assumptions!$C$11,'Rate Card'!C$2:T$2,0)))} -> #N/A
A16: Accounts | B16: Accounts Coordinator | C16: TRUE | F16: =(L16-N16)*BN16 -> #N/A | G16: =iferror(if(C16=true,0,(L16*(BN16/1.55*1.2285))),"") -> 0 | H16: =G16 -> 0 | I16: =G16-H16 -> 0 | J16: =sumif('Job Report'!I:I,B16,'Job Report'!H:H) -> 0 | K16: =if(C16=false,H16-J16,0) -> 0 | L16: =SUM(R16:BL16) -> 0 | P16: =L16-N16 -> 0 | R16: =if($D16="X",vlookup($B16,'Hours Spread - Filtered'!$B:$AX,R$1,false),"") | S16: =if($D16="X",vlookup($B16,'Hours Spread - Filtered'!$B:$AX,S$1,false),"") | T16: =if($D16="X",vlookup($B16,'Hours Spread - Filtered'!$B:$AX,T$1,false),"") | U16: =if($D16="X",vlookup($B16,'Hours Spread - Filtered'!$B:$AX,U$1,false),"") | V16: =if($D16="X",vlookup($B16,'Hours Spread - Filtered'!$B:$AX,V$1,false),"") | W16: =if($D16="X",vlookup($B16,'Hours Spread - Filtered'!$B:$AX,W$1,false),"") | X16: =if($D16="X",vlookup($B16,'Hours Spread - Filtered'!$B:$AX,X$1,false),"") | Y16: =if($D16="X",vlookup($B16,'Hours Spread - Filtered'!$B:$AX,Y$1,false),"") | ... BL16: =if($D16="X",vlookup($B16,'Hours Spread - Filtered'!$B:$AX,BL$1,false),"") | BM16: {=IFERROR(index('Rate Card'!U$3:AF135,match(B16,'Rate Card'!A$3:A135,0),match(Assumptions!C$11,'Rate Card'!U$2:AF$2,0)),"")} | BN16: {=(index('Rate Card'!$C$4:$T135, match(BM16,Controls!H$21:H135,0),match(Assumptions!$C$11,'Rate Card'!C$2:T$2,0)))} -> #N/A
A17: CREATIVE | R17: =if($D17="X",vlookup($B17,'Hours Spread - Filtered'!$B:$AX,R$1,false),"") | S17: =if($D17="X",vlookup($B17,'Hours Spread - Filtered'!$B:$AX,S$1,false),"") | T17: =if($D17="X",vlookup($B17,'Hours Spread - Filtered'!$B:$AX,T$1,false),"") | U17: =if($D17="X",vlookup($B17,'Hours Spread - Filtered'!$B:$AX,U$1,false),"") | V17: =if($D17="X",vlookup($B17,'Hours Spread - Filtered'!$B:$AX,V$1,false),"") | W17: =if($D17="X",vlookup($B17,'Hours Spread - Filtered'!$B:$AX,W$1,false),"") | X17: =if($D17="X",vlookup($B17,'Hours Spread - Filtered'!$B:$AX,X$1,false),"") | Y17: =if($D17="X",vlookup($B17,'Hours Spread - Filtered'!$B:$AX,Y$1,false),"") | ... BL17: =if($D17="X",vlookup($B17,'Hours Spread - Filtered'!$B:$AX,BL$1,false),"")
A18: Creative | B18: EVP Creative | C18: TRUE | E18: =if(D18="x","Needs Staffing","") | F18: =(L18-N18)*BN18 -> #N/A | G18: =iferror(if(C18=true,0,(L18*(BN18/1.55*1.2285))),"") -> 0 | H18: =G18 -> 0 | I18: =G18-H18 -> 0 | J18: =sumif('Job Report'!I:I,B18,'Job Report'!H:H) -> 0 | K18: =if(C18=false,H18-J18,0) -> 0 | L18: =SUM(R18:BL18) -> 0 | N18: =if(B$4="Onsite Staffing in COGS", BF18,"") | O18: =BN18*N18 -> #N/A | P18: =L18-N18 -> 0 | R18: =if($D18="X",vlookup($B18,'Hours Spread - Filtered'!$B:$AX,R$1,false),"") | S18: =if($D18="X",vlookup($B18,'Hours Spread - Filtered'!$B:$AX,S$1,false),"") | T18: =if($D18="X",vlookup($B18,'Hours Spread - Filtered'!$B:$AX,T$1,false),"") | U18: =if($D18="X",vlookup($B18,'Hours Spread - Filtered'!$B:$AX,U$1,false),"") | V18: =if($D18="X",vlookup($B18,'Hours Spread - Filtered'!$B:$AX,V$1,false),"") | W18: =if($D18="X",vlookup($B18,'Hours Spread - Filtered'!$B:$AX,W$1,false),"") | X18: =if($D18="X",vlookup($B18,'Hours Spread - Filtered'!$B:$AX,X$1,false),"") | Y18: =if($D18="X",vlookup($B18,'Hours Spread - Filtered'!$B:$AX,Y$1,false),"") | ... BL18: =if($D18="X",vlookup($B18,'Hours Spread - Filtered'!$B:$AX,BL$1,false),"") | BM18: {=IFERROR(index('Rate Card'!U$3:AF135,match(B18,'Rate Card'!A$3:A135,0),match(Assumptions!C$11,'Rate Card'!U$2:AF$2,0)),"")} | BN18: {=(index('Rate Card'!$C$4:$T135, match(BM18,Controls!H$21:H135,0),match(Assumptions!$C$11,'Rate Card'!C$2:T$2,0)))} -> #N/A
A19: Creative | B19: Director of Strategy | C19: TRUE | E19: =if(D19="x","Needs Staffing","") | F19: =(L19-N19)*BN19 -> #N/A | G19: =iferror(if(C19=true,0,(L19*(BN19/1.55*1.2285))),"") -> 0 | H19: =G19 -> 0 | I19: =G19-H19 -> 0 | J19: =sumif('Job Report'!I:I,B19,'Job Report'!H:H) -> 0 | K19: =if(C19=false,H19-J19,0) -> 0 | L19: =SUM(R19:BL19) -> 0 | N19: =if(B$4="Onsite Staffing in COGS", BF19,"") | O19: =BN19*N19 -> #N/A | P19: =L19-N19 -> 0 | R19: =if($D19="X",vlookup($B19,'Hours Spread - Filtered'!$B:$AX,R$1,false),"") | S19: =if($D19="X",vlookup($B19,'Hours Spread - Filtered'!$B:$AX,S$1,false),"") | T19: =if($D19="X",vlookup($B19,'Hours Spread - Filtered'!$B:$AX,T$1,false),"") | U19: =if($D19="X",vlookup($B19,'Hours Spread - Filtered'!$B:$AX,U$1,false),"") | V19: =if($D19="X",vlookup($B19,'Hours Spread - Filtered'!$B:$AX,V$1,false),"") | W19: =if($D19="X",vlookup($B19,'Hours Spread - Filtered'!$B:$AX,W$1,false),"") | X19: =if($D19="X",vlookup($B19,'Hours Spread - Filtered'!$B:$AX,X$1,false),"") | Y19: =if($D19="X",vlookup($B19,'Hours Spread - Filtered'!$B:$AX,Y$1,false),"") | ... BL19: =if($D19="X",vlookup($B19,'Hours Spread - Filtered'!$B:$AX,BL$1,false),"") | BM19: {=IFERROR(index('Rate Card'!U$3:AF135,match(B19,'Rate Card'!A$3:A135,0),match(Assumptions!C$11,'Rate Card'!U$2:AF$2,0)),"")} | BN19: {=(index('Rate Card'!$C$4:$T135, match(BM19,Controls!H$21:H135,0),match(Assumptions!$C$11,'Rate Card'!C$2:T$2,0)))} -> #N/A
A20: Creative | B20: Creative Strategist | C20: TRUE | E20: =if(D20="x","Needs Staffing","") | F20: =(L20-N20)*BN20 -> #N/A | G20: =iferror(if(C20=true,0,(L20*(BN20/1.55*1.2285))),"") -> 0 | H20: =G20 -> 0 | I20: =G20-H20 -> 0 | J20: =sumif('Job Report'!I:I,B20,'Job Report'!H:H) -> 0 | K20: =if(C20=false,H20-J20,0) -> 0 | L20: =SUM(R20:BL20) -> 0 | N20: =if(B$4="Onsite Staffing in COGS", BF20,"") | O20: =BN20*N20 -> #N/A | P20: =L20-N20 -> 0 | R20: =if($D20="X",vlookup($B20,'Hours Spread - Filtered'!$B:$AX,R$1,false),"") | S20: =if($D20="X",vlookup($B20,'Hours Spread - Filtered'!$B:$AX,S$1,false),"") | T20: =if($D20="X",vlookup($B20,'Hours Spread - Filtered'!$B:$AX,T$1,false),"") | U20: =if($D20="X",vlookup($B20,'Hours Spread - Filtered'!$B:$AX,U$1,false),"") | V20: =if($D20="X",vlookup($B20,'Hours Spread - Filtered'!$B:$AX,V$1,false),"") | W20: =if($D20="X",vlookup($B20,'Hours Spread - Filtered'!$B:$AX,W$1,false),"") | X20: =if($D20="X",vlookup($B20,'Hours Spread - Filtered'!$B:$AX,X$1,false),"") | Y20: =if($D20="X",vlookup($B20,'Hours Spread - Filtered'!$B:$AX,Y$1,false),"") | ... BL20: =if($D20="X",vlookup($B20,'Hours Spread - Filtered'!$B:$AX,BL$1,false),"") | BM20: {=IFERROR(index('Rate Card'!U$3:AF135,match(B20,'Rate Card'!A$3:A135,0),match(Assumptions!C$11,'Rate Card'!U$2:AF$2,0)),"")} | BN20: {=(index('Rate Card'!$C$4:$T135, match(BM20,Controls!H$21:H135,0),match(Assumptions!$C$11,'Rate Card'!C$2:T$2,0)))} -> #N/A
A21: Creative | B21: Creative Strategist 2 | C21: TRUE | E21: =if(D21="x","Needs Staffing","") | F21: =(L21-N21)*BN21 -> #N/A | G21: =iferror(if(C21=true,0,(L21*(BN21/1.55*1.2285))),"") -> 0 | H21: =G21 -> 0 | I21: =G21-H21 -> 0 | J21: =sumif('Job Report'!I:I,B21,'Job Report'!H:H) -> 0 | K21: =if(C21=false,H21-J21,0) -> 0 | L21: =SUM(R21:BL21) -> 0 | N21: =if(B$4="Onsite Staffing in COGS", BF21,"") | O21: =BN21*N21 -> #N/A | P21: =L21-N21 -> 0 | R21: =if($D21="X",vlookup($B21,'Hours Spread - Filtered'!$B:$AX,R$1,false),"") | S21: =if($D21="X",vlookup($B21,'Hours Spread - Filtered'!$B:$AX,S$1,false),"") | T21: =if($D21="X",vlookup($B21,'Hours Spread - Filtered'!$B:$AX,T$1,false),"") | U21: =if($D21="X",vlookup($B21,'Hours Spread - Filtered'!$B:$AX,U$1,false),"") | V21: =if($D21="X",vlookup($B21,'Hours Spread - Filtered'!$B:$AX,V$1,false),"") | W21: =if($D21="X",vlookup($B21,'Hours Spread - Filtered'!$B:$AX,W$1,false),"") | X21: =if($D21="X",vlookup($B21,'Hours Spread - Filtered'!$B:$AX,X$1,false),"") | Y21: =if($D21="X",vlookup($B21,'Hours Spread - Filtered'!$B:$AX,Y$1,false),"") | ... BL21: =if($D21="X",vlookup($B21,'Hours Spread - Filtered'!$B:$AX,BL$1,false),"") | BM21: {=IFERROR(index('Rate Card'!U$3:AF135,match(B21,'Rate Card'!A$3:A135,0),match(Assumptions!C$11,'Rate Card'!U$2:AF$2,0)),"")} | BN21: {=(index('Rate Card'!$C$4:$T135, match(BM21,Controls!H$21:H135,0),match(Assumptions!$C$11,'Rate Card'!C$2:T$2,0)))} -> #N/A
A22: Creative | B22: Associate Creative Strategist | C22: TRUE | E22: =if(D22="x","Needs Staffing","") | F22: =(L22-N22)*BN22 -> #N/A | G22: =iferror(if(C22=true,0,(L22*(BN22/1.55*1.2285))),"") -> 0 | H22: =G22 -> 0 | I22: =G22-H22 -> 0 | J22: =sumif('Job Report'!I:I,B22,'Job Report'!H:H) -> 0 | K22: =if(C22=false,H22-J22,0) -> 0 | L22: =SUM(R22:BL22) -> 0 | N22: =if(B$4="Onsite Staffing in COGS", BF22,"") | O22: =BN22*N22 -> #N/A | P22: =L22-N22 -> 0 | R22: =if($D22="X",vlookup($B22,'Hours Spread - Filtered'!$B:$AX,R$1,false),"") | S22: =if($D22="X",vlookup($B22,'Hours Spread - Filtered'!$B:$AX,S$1,false),"") | T22: =if($D22="X",vlookup($B22,'Hours Spread - Filtered'!$B:$AX,T$1,false),"") | U22: =if($D22="X",vlookup($B22,'Hours Spread - Filtered'!$B:$AX,U$1,false),"") | V22: =if($D22="X",vlookup($B22,'Hours Spread - Filtered'!$B:$AX,V$1,false),"") | W22: =if($D22="X",vlookup($B22,'Hours Spread - Filtered'!$B:$AX,W$1,false),"") | X22: =if($D22="X",vlookup($B22,'Hours Spread - Filtered'!$B:$AX,X$1,false),"") | Y22: =if($D22="X",vlookup($B22,'Hours Spread - Filtered'!$B:$AX,Y$1,false),"") | ... BL22: =if($D22="X",vlookup($B22,'Hours Spread - Filtered'!$B:$AX,BL$1,false),"") | BM22: {=IFERROR(index('Rate Card'!U$3:AF135,match(B22,'Rate Card'!A$3:A135,0),match(Assumptions!C$11,'Rate Card'!U$2:AF$2,0)),"")} | BN22: {=(index('Rate Card'!$C$4:$T135, match(BM22,Controls!H$21:H135,0),match(Assumptions!$C$11,'Rate Card'!C$2:T$2,0)))} -> #N/A
A23: Creative | B23: Director of Creative | C23: TRUE | E23: =if(D23="x","Needs Staffing","") | F23: =(L23-N23)*BN23 -> #N/A | G23: =iferror(if(C23=true,0,(L23*(BN23/1.55*1.2285))),"") -> 0 | H23: =G23 -> 0 | I23: =G23-H23 -> 0 | J23: =sumif('Job Report'!I:I,B23,'Job Report'!H:H) -> 0 | K23: =if(C23=false,H23-J23,0) -> 0 | L23: =SUM(R23:BL23) -> 0 | N23: =if(B$4="Onsite Staffing in COGS", BF23,"") | O23: =BN23*N23 -> #N/A | P23: =L23-N23 -> 0 | R23: =if($D23="X",vlookup($B23,'Hours Spread - Filtered'!$B:$AX,R$1,false),"") | S23: =if($D23="X",vlookup($B23,'Hours Spread - Filtered'!$B:$AX,S$1,false),"") | T23: =if($D23="X",vlookup($B23,'Hours Spread - Filtered'!$B:$AX,T$1,false),"") | U23: =if($D23="X",vlookup($B23,'Hours Spread - Filtered'!$B:$AX,U$1,false),"") | V23: =if($D23="X",vlookup($B23,'Hours Spread - Filtered'!$B:$AX,V$1,false),"") | W23: =if($D23="X",vlookup($B23,'Hours Spread - Filtered'!$B:$AX,W$1,false),"") | X23: =if($D23="X",vlookup($B23,'Hours Spread - Filtered'!$B:$AX,X$1,false),"") | Y23: =if($D23="X",vlookup($B23,'Hours Spread - Filtered'!$B:$AX,Y$1,false),"") | ... BL23: =if($D23="X",vlookup($B23,'Hours Spread - Filtered'!$B:$AX,BL$1,false),"") | BM23: {=IFERROR(index('Rate Card'!U$3:AF135,match(B23,'Rate Card'!A$3:A135,0),match(Assumptions!C$11,'Rate Card'!U$2:AF$2,0)),"")} | BN23: {=(index('Rate Card'!$C$4:$T135, match(BM23,Controls!H$21:H135,0),match(Assumptions!$C$11,'Rate Card'!C$2:T$2,0)))} -> #N/A
A24: Creative | B24: Creative Director | C24: TRUE | E24: =if(D24="x","Needs Staffing","") | F24: =(L24-N24)*BN24 -> #N/A | G24: =iferror(if(C24=true,0,(L24*(BN24/1.55*1.2285))),"") -> 0 | H24: =G24 -> 0 | I24: =G24-H24 -> 0 | J24: =sumif('Job Report'!I:I,B24,'Job Report'!H:H) -> 0 | K24: =if(C24=false,H24-J24,0) -> 0 | L24: =SUM(R24:BL24) -> 0 | N24: =if(B$4="Onsite Staffing in COGS", BF24,"") | O24: =BN24*N24 -> #N/A | P24: =L24-N24 -> 0 | R24: =if($D24="X",vlookup($B24,'Hours Spread - Filtered'!$B:$AX,R$1,false),"") | S24: =if($D24="X",vlookup($B24,'Hours Spread - Filtered'!$B:$AX,S$1,false),"") | T24: =if($D24="X",vlookup($B24,'Hours Spread - Filtered'!$B:$AX,T$1,false),"") | U24: =if($D24="X",vlookup($B24,'Hours Spread - Filtered'!$B:$AX,U$1,false),"") | V24: =if($D24="X",vlookup($B24,'Hours Spread - Filtered'!$B:$AX,V$1,false),"") | W24: =if($D24="X",vlookup($B24,'Hours Spread - Filtered'!$B:$AX,W$1,false),"") | X24: =if($D24="X",vlookup($B24,'Hours Spread - Filtered'!$B:$AX,X$1,false),"") | Y24: =if($D24="X",vlookup($B24,'Hours Spread - Filtered'!$B:$AX,Y$1,false),"") | ... BL24: =if($D24="X",vlookup($B24,'Hours Spread - Filtered'!$B:$AX,BL$1,false),"") | BM24: {=IFERROR(index('Rate Card'!U$3:AF135,match(B24,'Rate Card'!A$3:A135,0),match(Assumptions!C$11,'Rate Card'!U$2:AF$2,0)),"")} | BN24: {=(index('Rate Card'!$C$4:$T135, match(BM24,Controls!H$21:H135,0),match(Assumptions!$C$11,'Rate Card'!C$2:T$2,0)))} -> #N/A
A25: Creative | B25: Creative Director 2 | C25: TRUE | E25: =if(D25="x","Needs Staffing","") | F25: =(L25-N25)*BN25 -> #N/A | G25: =iferror(if(C25=true,0,(L25*(BN25/1.55*1.2285))),"") -> 0 | H25: =G25 -> 0 | I25: =G25-H25 -> 0 | J25: =sumif('Job Report'!I:I,B25,'Job Report'!H:H) -> 0 | K25: =if(C25=false,H25-J25,0) -> 0 | L25: =SUM(R25:BL25) -> 0 | N25: =if(B$4="Onsite Staffing in COGS", BF25,"") | O25: =BN25*N25 -> #N/A | P25: =L25-N25 -> 0 | R25: =if($D25="X",vlookup($B25,'Hours Spread - Filtered'!$B:$AX,R$1,false),"") | S25: =if($D25="X",vlookup($B25,'Hours Spread - Filtered'!$B:$AX,S$1,false),"") | T25: =if($D25="X",vlookup($B25,'Hours Spread - Filtered'!$B:$AX,T$1,false),"") | U25: =if($D25="X",vlookup($B25,'Hours Spread - Filtered'!$B:$AX,U$1,false),"") | V25: =if($D25="X",vlookup($B25,'Hours Spread - Filtered'!$B:$AX,V$1,false),"") | W25: =if($D25="X",vlookup($B25,'Hours Spread - Filtered'!$B:$AX,W$1,false),"") | X25: =if($D25="X",vlookup($B25,'Hours Spread - Filtered'!$B:$AX,X$1,false),"") | Y25: =if($D25="X",vlookup($B25,'Hours Spread - Filtered'!$B:$AX,Y$1,false),"") | ... BL25: =if($D25="X",vlookup($B25,'Hours Spread - Filtered'!$B:$AX,BL$1,false),"") | BM25: {=IFERROR(index('Rate Card'!U$3:AF135,match(B25,'Rate Card'!A$3:A135,0),match(Assumptions!C$11,'Rate Card'!U$2:AF$2,0)),"")} | BN25: {=(index('Rate Card'!$C$4:$T135, match(BM25,Controls!H$21:H135,0),match(Assumptions!$C$11,'Rate Card'!C$2:T$2,0)))} -> #N/A
A26: Creative | B26: Art Director | C26: TRUE | E26: =if(D26="x","Needs Staffing","") | F26: =(L26-N26)*BN26 -> #N/A | G26: =iferror(if(C26=true,0,(L26*(BN26/1.55*1.2285))),"") -> 0 | H26: =G26 -> 0 | I26: =G26-H26 -> 0 | J26: =sumif('Job Report'!I:I,B26,'Job Report'!H:H) -> 0 | K26: =if(C26=false,H26-J26,0) -> 0 | L26: =SUM(R26:BL26) -> 0 | N26: =if(B$4="Onsite Staffing in COGS", BF26,"") | O26: =BN26*N26 -> #N/A | P26: =L26-N26 -> 0 | R26: =if($D26="X",vlookup($B26,'Hours Spread - Filtered'!$B:$AX,R$1,false),"") | S26: =if($D26="X",vlookup($B26,'Hours Spread - Filtered'!$B:$AX,S$1,false),"") | T26: =if($D26="X",vlookup($B26,'Hours Spread - Filtered'!$B:$AX,T$1,false),"") | U26: =if($D26="X",vlookup($B26,'Hours Spread - Filtered'!$B:$AX,U$1,false),"") | V26: =if($D26="X",vlookup($B26,'Hours Spread - Filtered'!$B:$AX,V$1,false),"") | W26: =if($D26="X",vlookup($B26,'Hours Spread - Filtered'!$B:$AX,W$1,false),"") | X26: =if($D26="X",vlookup($B26,'Hours Spread - Filtered'!$B:$AX,X$1,false),"") | Y26: =if($D26="X",vlookup($B26,'Hours Spread - Filtered'!$B:$AX,Y$1,false),"") | ... BL26: =if($D26="X",vlookup($B26,'Hours Spread - Filtered'!$B:$AX,BL$1,false),"") | BM26: {=IFERROR(index('Rate Card'!U$3:AF135,match(B26,'Rate Card'!A$3:A135,0),match(Assumptions!C$11,'Rate Card'!U$2:AF$2,0)),"")} | BN26: {=(index('Rate Card'!$C$4:$T135, match(BM26,Controls!H$21:H135,0),match(Assumptions!$C$11,'Rate Card'!C$2:T$2,0)))} -> #N/A
A27: Creative | B27: Art Director 2 | C27: TRUE | E27: =if(D27="x","Needs Staffing","") | F27: =(L27-N27)*BN27 -> #N/A | G27: =iferror(if(C27=true,0,(L27*(BN27/1.55*1.2285))),"") -> 0 | H27: =G27 -> 0 | I27: =G27-H27 -> 0 | J27: =sumif('Job Report'!I:I,B27,'Job Report'!H:H) -> 0 | K27: =if(C27=false,H27-J27,0) -> 0 | L27: =SUM(R27:BL27) -> 0 | N27: =if(B$4="Onsite Staffing in COGS", BF27,"") | O27: =BN27*N27 -> #N/A | P27: =L27-N27 -> 0 | R27: =if($D27="X",vlookup($B27,'Hours Spread - Filtered'!$B:$AX,R$1,false),"") | S27: =if($D27="X",vlookup($B27,'Hours Spread - Filtered'!$B:$AX,S$1,false),"") | T27: =if($D27="X",vlookup($B27,'Hours Spread - Filtered'!$B:$AX,T$1,false),"") | U27: =if($D27="X",vlookup($B27,'Hours Spread - Filtered'!$B:$AX,U$1,false),"") | V27: =if($D27="X",vlookup($B27,'Hours Spread - Filtered'!$B:$AX,V$1,false),"") | W27: =if($D27="X",vlookup($B27,'Hours Spread - Filtered'!$B:$AX,W$1,false),"") | X27: =if($D27="X",vlookup($B27,'Hours Spread - Filtered'!$B:$AX,X$1,false),"") | Y27: =if($D27="X",vlookup($B27,'Hours Spread - Filtered'!$B:$AX,Y$1,false),"") | ... BL27: =if($D27="X",vlookup($B27,'Hours Spread - Filtered'!$B:$AX,BL$1,false),"") | BM27: {=IFERROR(index('Rate Card'!U$3:AF135,match(B27,'Rate Card'!A$3:A135,0),match(Assumptions!C$11,'Rate Card'!U$2:AF$2,0)),"")} | BN27: {=(index('Rate Card'!$C$4:$T135, match(BM27,Controls!H$21:H135,0),match(Assumptions!$C$11,'Rate Card'!C$2:T$2,0)))} -> #N/A
A28: Creative | B28: Art Director 3 | C28: TRUE | E28: =if(D28="x","Needs Staffing","") | F28: =(L28-N28)*BN28 -> #N/A | G28: =iferror(if(C28=true,0,(L28*(BN28/1.55*1.2285))),"") -> 0 | H28: =G28 -> 0 | I28: =G28-H28 -> 0 | J28: =sumif('Job Report'!I:I,B28,'Job Report'!H:H) -> 0 | K28: =if(C28=false,H28-J28,0) -> 0 | L28: =SUM(R28:BL28) -> 0 | N28: =if(B$4="Onsite Staffing in COGS", BF28,"") | O28: =BN28*N28 -> #N/A | P28: =L28-N28 -> 0 | R28: =if($D28="X",vlookup($B28,'Hours Spread - Filtered'!$B:$AX,R$1,false),"") | S28: =if($D28="X",vlookup($B28,'Hours Spread - Filtered'!$B:$AX,S$1,false),"") | T28: =if($D28="X",vlookup($B28,'Hours Spread - Filtered'!$B:$AX,T$1,false),"") | U28: =if($D28="X",vlookup($B28,'Hours Spread - Filtered'!$B:$AX,U$1,false),"") | V28: =if($D28="X",vlookup($B28,'Hours Spread - Filtered'!$B:$AX,V$1,false),"") | W28: =if($D28="X",vlookup($B28,'Hours Spread - Filtered'!$B:$AX,W$1,false),"") | X28: =if($D28="X",vlookup($B28,'Hours Spread - Filtered'!$B:$AX,X$1,false),"") | Y28: =if($D28="X",vlookup($B28,'Hours Spread - Filtered'!$B:$AX,Y$1,false),"") | ... BL28: =if($D28="X",vlookup($B28,'Hours Spread - Filtered'!$B:$AX,BL$1,false),"") | BM28: {=IFERROR(index('Rate Card'!U$3:AF135,match(B28,'Rate Card'!A$3:A135,0),match(Assumptions!C$11,'Rate Card'!U$2:AF$2,0)),"")} | BN28: {=(index('Rate Card'!$C$4:$T135, match(BM28,Controls!H$21:H135,0),match(Assumptions!$C$11,'Rate Card'!C$2:T$2,0)))} -> #N/A
A29: Creative | B29: Associate Art Director | C29: TRUE | E29: =if(D29="x","Needs Staffing","") | F29: =(L29-N29)*BN29 -> #N/A | G29: =iferror(if(C29=true,0,(L29*(BN29/1.55*1.2285))),"") -> 0 | H29: =G29 -> 0 | I29: =G29-H29 -> 0 | J29: =sumif('Job Report'!I:I,B29,'Job Report'!H:H) -> 0 | K29: =if(C29=false,H29-J29,0) -> 0 | L29: =SUM(R29:BL29) -> 0 | N29: =if(B$4="Onsite Staffing in COGS", BF29,"") | O29: =BN29*N29 -> #N/A | P29: =L29-N29 -> 0 | R29: =if($D29="X",vlookup($B29,'Hours Spread - Filtered'!$B:$AX,R$1,false),"") | S29: =if($D29="X",vlookup($B29,'Hours Spread - Filtered'!$B:$AX,S$1,false),"") | T29: =if($D29="X",vlookup($B29,'Hours Spread - Filtered'!$B:$AX,T$1,false),"") | U29: =if($D29="X",vlookup($B29,'Hours Spread - Filtered'!$B:$AX,U$1,false),"") | V29: =if($D29="X",vlookup($B29,'Hours Spread - Filtered'!$B:$AX,V$1,false),"") | W29: =if($D29="X",vlookup($B29,'Hours Spread - Filtered'!$B:$AX,W$1,false),"") | X29: =if($D29="X",vlookup($B29,'Hours Spread - Filtered'!$B:$AX,X$1,false),"") | Y29: =if($D29="X",vlookup($B29,'Hours Spread - Filtered'!$B:$AX,Y$1,false),"") | ... BL29: =if($D29="X",vlookup($B29,'Hours Spread - Filtered'!$B:$AX,BL$1,false),"") | BM29: {=IFERROR(index('Rate Card'!U$3:AF135,match(B29,'Rate Card'!A$3:A135,0),match(Assumptions!C$11,'Rate Card'!U$2:AF$2,0)),"")} | BN29: {=(index('Rate Card'!$C$4:$T135, match(BM29,Controls!H$21:H135,0),match(Assumptions!$C$11,'Rate Card'!C$2:T$2,0)))} -> #N/A
A30: Creative | B30: Associate Art Director 2 | C30: TRUE | E30: =if(D30="x","Needs Staffing","") | F30: =(L30-N30)*BN30 -> #N/A | G30: =iferror(if(C30=true,0,(L30*(BN30/1.55*1.2285))),"") -> 0 | H30: =G30 -> 0 | I30: =G30-H30 -> 0 | J30: =sumif('Job Report'!I:I,B30,'Job Report'!H:H) -> 0 | K30: =if(C30=false,H30-J30,0) -> 0 | L30: =SUM(R30:BL30) -> 0 | N30: =if(B$4="Onsite Staffing in COGS", BF30,"") | O30: =BN30*N30 -> #N/A | P30: =L30-N30 -> 0 | R30: =if($D30="X",vlookup($B30,'Hours Spread - Filtered'!$B:$AX,R$1,false),"") | S30: =if($D30="X",vlookup($B30,'Hours Spread - Filtered'!$B:$AX,S$1,false),"") | T30: =if($D30="X",vlookup($B30,'Hours Spread - Filtered'!$B:$AX,T$1,false),"") | U30: =if($D30="X",vlookup($B30,'Hours Spread - Filtered'!$B:$AX,U$1,false),"") | V30: =if($D30="X",vlookup($B30,'Hours Spread - Filtered'!$B:$AX,V$1,false),"") | W30: =if($D30="X",vlookup($B30,'Hours Spread - Filtered'!$B:$AX,W$1,false),"") | X30: =if($D30="X",vlookup($B30,'Hours Spread - Filtered'!$B:$AX,X$1,false),"") | Y30: =if($D30="X",vlookup($B30,'Hours Spread - Filtered'!$B:$AX,Y$1,false),"") | ... BL30: =if($D30="X",vlookup($B30,'Hours Spread - Filtered'!$B:$AX,BL$1,false),"") | BM30: {=IFERROR(index('Rate Card'!U$3:AF135,match(B30,'Rate Card'!A$3:A135,0),match(Assumptions!C$11,'Rate Card'!U$2:AF$2,0)),"")} | BN30: {=(index('Rate Card'!$C$4:$T135, match(BM30,Controls!H$21:H135,0),match(Assumptions!$C$11,'Rate Card'!C$2:T$2,0)))} -> #N/A
A31: Creative | B31: Associate Art Director 3 | C31: TRUE | E31: =if(D31="x","Needs Staffing","") | F31: =(L31-N31)*BN31 -> #N/A | G31: =iferror(if(C31=true,0,(L31*(BN31/1.55*1.2285))),"") -> 0 | H31: =G31 -> 0 | I31: =G31-H31 -> 0 | J31: =sumif('Job Report'!I:I,B31,'Job Report'!H:H) -> 0 | K31: =if(C31=false,H31-J31,0) -> 0 | L31: =SUM(R31:BL31) -> 0 | N31: =if(B$4="Onsite Staffing in COGS", BF31,"") | O31: =BN31*N31 -> #N/A | P31: =L31-N31 -> 0 | R31: =if($D31="X",vlookup($B31,'Hours Spread - Filtered'!$B:$AX,R$1,false),"") | S31: =if($D31="X",vlookup($B31,'Hours Spread - Filtered'!$B:$AX,S$1,false),"") | T31: =if($D31="X",vlookup($B31,'Hours Spread - Filtered'!$B:$AX,T$1,false),"") | U31: =if($D31="X",vlookup($B31,'Hours Spread - Filtered'!$B:$AX,U$1,false),"") | V31: =if($D31="X",vlookup($B31,'Hours Spread - Filtered'!$B:$AX,V$1,false),"") | W31: =if($D31="X",vlookup($B31,'Hours Spread - Filtered'!$B:$AX,W$1,false),"") | X31: =if($D31="X",vlookup($B31,'Hours Spread - Filtered'!$B:$AX,X$1,false),"") | Y31: =if($D31="X",vlookup($B31,'Hours Spread - Filtered'!$B:$AX,Y$1,false),"") | ... BL31: =if($D31="X",vlookup($B31,'Hours Spread - Filtered'!$B:$AX,BL$1,false),"") | BM31: {=IFERROR(index('Rate Card'!U$3:AF135,match(B31,'Rate Card'!A$3:A135,0),match(Assumptions!C$11,'Rate Card'!U$2:AF$2,0)),"")} | BN31: {=(index('Rate Card'!$C$4:$T135, match(BM31,Controls!H$21:H135,0),match(Assumptions!$C$11,'Rate Card'!C$2:T$2,0)))} -> #N/A
A32: Creative | B32: Director of Design | C32: TRUE | E32: =if(D32="x","Needs Staffing","") | F32: =(L32-N32)*BN32 -> #N/A | G32: =iferror(if(C32=true,0,(L32*(BN32/1.55*1.2285))),"") -> 0 | H32: =G32 -> 0 | I32: =G32-H32 -> 0 | J32: =sumif('Job Report'!I:I,B32,'Job Report'!H:H) -> 0 | K32: =if(C32=false,H32-J32,0) -> 0 | L32: =SUM(R32:BL32) -> 0 | N32: =if(B$4="Onsite Staffing in COGS", BF32,"") | O32: =BN32*N32 -> #N/A | P32: =L32-N32 -> 0 | R32: =if($D32="X",vlookup($B32,'Hours Spread - Filtered'!$B:$AX,R$1,false),"") | S32: =if($D32="X",vlookup($B32,'Hours Spread - Filtered'!$B:$AX,S$1,false),"") | T32: =if($D32="X",vlookup($B32,'Hours Spread - Filtered'!$B:$AX,T$1,false),"") | U32: =if($D32="X",vlookup($B32,'Hours Spread - Filtered'!$B:$AX,U$1,false),"") | V32: =if($D32="X",vlookup($B32,'Hours Spread - Filtered'!$B:$AX,V$1,false),"") | W32: =if($D32="X",vlookup($B32,'Hours Spread - Filtered'!$B:$AX,W$1,false),"") | X32: =if($D32="X",vlookup($B32,'Hours Spread - Filtered'!$B:$AX,X$1,false),"") | Y32: =if($D32="X",vlookup($B32,'Hours Spread - Filtered'!$B:$AX,Y$1,false),"") | ... BL32: =if($D32="X",vlookup($B32,'Hours Spread - Filtered'!$B:$AX,BL$1,false),"") | BM32: {=IFERROR(index('Rate Card'!U$3:AF135,match(B32,'Rate Card'!A$3:A135,0),match(Assumptions!C$11,'Rate Card'!U$2:AF$2,0)),"")} | BN32: {=(index('Rate Card'!$C$4:$T135, match(BM32,Controls!H$21:H135,0),match(Assumptions!$C$11,'Rate Card'!C$2:T$2,0)))} -> #N/A
A33: Creative | B33: Motion Designer | C33: TRUE | E33: =if(D33="x","Needs Staffing","") | F33: =(L33-N33)*BN33 -> #N/A | G33: =iferror(if(C33=true,0,(L33*(BN33/1.55*1.2285))),"") -> 0 | H33: =G33 -> 0 | I33: =G33-H33 -> 0 | J33: =sumif('Job Report'!I:I,B33,'Job Report'!H:H) -> 0 | K33: =if(C33=false,H33-J33,0) -> 0 | L33: =SUM(R33:BL33) -> 0 | N33: =if(B$4="Onsite Staffing in COGS", BF33,"") | O33: =BN33*N33 -> #N/A | P33: =L33-N33 -> 0 | R33: =if($D33="X",vlookup($B33,'Hours Spread - Filtered'!$B:$AX,R$1,false),"") | S33: =if($D33="X",vlookup($B33,'Hours Spread - Filtered'!$B:$AX,S$1,false),"") | T33: =if($D33="X",vlookup($B33,'Hours Spread - Filtered'!$B:$AX,T$1,false),"") | U33: =if($D33="X",vlookup($B33,'Hours Spread - Filtered'!$B:$AX,U$1,false),"") | V33: =if($D33="X",vlookup($B33,'Hours Spread - Filtered'!$B:$AX,V$1,false),"") | W33: =if($D33="X",vlookup($B33,'Hours Spread - Filtered'!$B:$AX,W$1,false),"") | X33: =if($D33="X",vlookup($B33,'Hours Spread - Filtered'!$B:$AX,X$1,false),"") | Y33: =if($D33="X",vlookup($B33,'Hours Spread - Filtered'!$B:$AX,Y$1,false),"") | ... BL33: =if($D33="X",vlookup($B33,'Hours Spread - Filtered'!$B:$AX,BL$1,false),"") | BM33: {=IFERROR(index('Rate Card'!U$3:AF135,match(B33,'Rate Card'!A$3:A135,0),match(Assumptions!C$11,'Rate Card'!U$2:AF$2,0)),"")} | BN33: {=(index('Rate Card'!$C$4:$T135, match(BM33,Controls!H$21:H135,0),match(Assumptions!$C$11,'Rate Card'!C$2:T$2,0)))} -> #N/A
A34: Creative | B34: Motion Designer 2 | C34: TRUE | E34: =if(D34="x","Needs Staffing","") | F34: =(L34-N34)*BN34 -> #N/A | G34: =iferror(if(C34=true,0,(L34*(BN34/1.55*1.2285))),"") -> 0 | H34: =G34 -> 0 | I34: =G34-H34 -> 0 | J34: =sumif('Job Report'!I:I,B34,'Job Report'!H:H) -> 0 | K34: =if(C34=false,H34-J34,0) -> 0 | L34: =SUM(R34:BL34) -> 0 | N34: =if(B$4="Onsite Staffing in COGS", BF34,"") | O34: =BN34*N34 -> #N/A | P34: =L34-N34 -> 0 | R34: =if($D34="X",vlookup($B34,'Hours Spread - Filtered'!$B:$AX,R$1,false),"") | S34: =if($D34="X",vlookup($B34,'Hours Spread - Filtered'!$B:$AX,S$1,false),"") | T34: =if($D34="X",vlookup($B34,'Hours Spread - Filtered'!$B:$AX,T$1,false),"") | U34: =if($D34="X",vlookup($B34,'Hours Spread - Filtered'!$B:$AX,U$1,false),"") | V34: =if($D34="X",vlookup($B34,'Hours Spread - Filtered'!$B:$AX,V$1,false),"") | W34: =if($D34="X",vlookup($B34,'Hours Spread - Filtered'!$B:$AX,W$1,false),"") | X34: =if($D34="X",vlookup($B34,'Hours Spread - Filtered'!$B:$AX,X$1,false),"") | Y34: =if($D34="X",vlookup($B34,'Hours Spread - Filtered'!$B:$AX,Y$1,false),"") | ... BL34: =if($D34="X",vlookup($B34,'Hours Spread - Filtered'!$B:$AX,BL$1,false),"") | BM34: {=IFERROR(index('Rate Card'!U$3:AF135,match(B34,'Rate Card'!A$3:A135,0),match(Assumptions!C$11,'Rate Card'!U$2:AF$2,0)),"")} | BN34: {=(index('Rate Card'!$C$4:$T135, match(BM34,Controls!H$21:H135,0),match(Assumptions!$C$11,'Rate Card'!C$2:T$2,0)))} -> #N/A
A35: Creative | B35: Art Director, Graphics | C35: TRUE | E35: =if(D35="x","Needs Staffing","") | F35: =(L35-N35)*BN35 -> #N/A | G35: =iferror(if(C35=true,0,(L35*(BN35/1.55*1.2285))),"") -> 0 | H35: =G35 -> 0 | I35: =G35-H35 -> 0 | J35: =sumif('Job Report'!I:I,B35,'Job Report'!H:H) -> 0 | K35: =if(C35=false,H35-J35,0) -> 0 | L35: =SUM(R35:BL35) -> 0 | N35: =if(B$4="Onsite Staffing in COGS", BF35,"") | O35: =BN35*N35 -> #N/A | P35: =L35-N35 -> 0 | R35: =if($D35="X",vlookup($B35,'Hours Spread - Filtered'!$B:$AX,R$1,false),"") | S35: =if($D35="X",vlookup($B35,'Hours Spread - Filtered'!$B:$AX,S$1,false),"") | T35: =if($D35="X",vlookup($B35,'Hours Spread - Filtered'!$B:$AX,T$1,false),"") | U35: =if($D35="X",vlookup($B35,'Hours Spread - Filtered'!$B:$AX,U$1,false),"") | V35: =if($D35="X",vlookup($B35,'Hours Spread - Filtered'!$B:$AX,V$1,false),"") | W35: =if($D35="X",vlookup($B35,'Hours Spread - Filtered'!$B:$AX,W$1,false),"") | X35: =if($D35="X",vlookup($B35,'Hours Spread - Filtered'!$B:$AX,X$1,false),"") | Y35: =if($D35="X",vlookup($B35,'Hours Spread - Filtered'!$B:$AX,Y$1,false),"") | ... BL35: =if($D35="X",vlookup($B35,'Hours Spread - Filtered'!$B:$AX,BL$1,false),"") | BM35: {=IFERROR(index('Rate Card'!U$3:AF135,match(B35,'Rate Card'!A$3:A135,0),match(Assumptions!C$11,'Rate Card'!U$2:AF$2,0)),"")} | BN35: {=(index('Rate Card'!$C$4:$T135, match(BM35,Controls!H$21:H135,0),match(Assumptions!$C$11,'Rate Card'!C$2:T$2,0)))} -> #N/A
A36: Creative | B36: Art Director, Graphics 2 | C36: TRUE | E36: =if(D36="x","Needs Staffing","") | F36: =(L36-N36)*BN36 -> #N/A | G36: =iferror(if(C36=true,0,(L36*(BN36/1.55*1.2285))),"") -> 0 | H36: =G36 -> 0 | I36: =G36-H36 -> 0 | J36: =sumif('Job Report'!I:I,B36,'Job Report'!H:H) -> 0 | K36: =if(C36=false,H36-J36,0) -> 0 | L36: =SUM(R36:BL36) -> 0 | N36: =if(B$4="Onsite Staffing in COGS", BF36,"") | O36: =BN36*N36 -> #N/A | P36: =L36-N36 -> 0 | R36: =if($D36="X",vlookup($B36,'Hours Spread - Filtered'!$B:$AX,R$1,false),"") | S36: =if($D36="X",vlookup($B36,'Hours Spread - Filtered'!$B:$AX,S$1,false),"") | T36: =if($D36="X",vlookup($B36,'Hours Spread - Filtered'!$B:$AX,T$1,false),"") | U36: =if($D36="X",vlookup($B36,'Hours Spread - Filtered'!$B:$AX,U$1,false),"") | V36: =if($D36="X",vlookup($B36,'Hours Spread - Filtered'!$B:$AX,V$1,false),"") | W36: =if($D36="X",vlookup($B36,'Hours Spread - Filtered'!$B:$AX,W$1,false),"") | X36: =if($D36="X",vlookup($B36,'Hours Spread - Filtered'!$B:$AX,X$1,false),"") | Y36: =if($D36="X",vlookup($B36,'Hours Spread - Filtered'!$B:$AX,Y$1,false),"") | ... BL36: =if($D36="X",vlookup($B36,'Hours Spread - Filtered'!$B:$AX,BL$1,false),"") | BM36: {=IFERROR(index('Rate Card'!U$3:AF135,match(B36,'Rate Card'!A$3:A135,0),match(Assumptions!C$11,'Rate Card'!U$2:AF$2,0)),"")} | BN36: {=(index('Rate Card'!$C$4:$T135, match(BM36,Controls!H$21:H135,0),match(Assumptions!$C$11,'Rate Card'!C$2:T$2,0)))} -> #N/A
A37: Creative | B37: Renderer | C37: TRUE | E37: =if(D37="x","Needs Staffing","") | F37: =(L37-N37)*BN37 -> #N/A | G37: =iferror(if(C37=true,0,(L37*(BN37/1.55*1.2285))),"") -> 0 | H37: =G37 -> 0 | I37: =G37-H37 -> 0 | J37: =sumif('Job Report'!I:I,B37,'Job Report'!H:H) -> 0 | K37: =if(C37=false,H37-J37,0) -> 0 | L37: =SUM(R37:BL37) -> 0 | N37: =if(B$4="Onsite Staffing in COGS", BF37,"") | O37: =BN37*N37 -> #N/A | P37: =L37-N37 -> 0 | R37: =if($D37="X",vlookup($B37,'Hours Spread - Filtered'!$B:$AX,R$1,false),"") | S37: =if($D37="X",vlookup($B37,'Hours Spread - Filtered'!$B:$AX,S$1,false),"") | T37: =if($D37="X",vlookup($B37,'Hours Spread - Filtered'!$B:$AX,T$1,false),"") | U37: =if($D37="X",vlookup($B37,'Hours Spread - Filtered'!$B:$AX,U$1,false),"") | V37: =if($D37="X",vlookup($B37,'Hours Spread - Filtered'!$B:$AX,V$1,false),"") | W37: =if($D37="X",vlookup($B37,'Hours Spread - Filtered'!$B:$AX,W$1,false),"") | X37: =if($D37="X",vlookup($B37,'Hours Spread - Filtered'!$B:$AX,X$1,false),"") | Y37: =if($D37="X",vlookup($B37,'Hours Spread - Filtered'!$B:$AX,Y$1,false),"") | ... BL37: =if($D37="X",vlookup($B37,'Hours Spread - Filtered'!$B:$AX,BL$1,false),"") | BM37: {=IFERROR(index('Rate Card'!U$3:AF135,match(B37,'Rate Card'!A$3:A135,0),match(Assumptions!C$11,'Rate Card'!U$2:AF$2,0)),"")} | BN37: {=(index('Rate Card'!$C$4:$T135, match(BM37,Controls!H$21:H135,0),match(Assumptions!$C$11,'Rate Card'!C$2:T$2,0)))} -> #N/A
A38: Creative | B38: Renderer 2 | C38: TRUE | E38: =if(D38="x","Needs Staffing","") | F38: =(L38-N38)*BN38 -> #N/A | G38: =iferror(if(C38=true,0,(L38*(BN38/1.55*1.2285))),"") -> 0 | H38: =G38 -> 0 | I38: =G38-H38 -> 0 | J38: =sumif('Job Report'!I:I,B38,'Job Report'!H:H) -> 0 | K38: =if(C38=false,H38-J38,0) -> 0 | L38: =SUM(R38:BL38) -> 0 | N38: =if(B$4="Onsite Staffing in COGS", BF38,"") | O38: =BN38*N38 -> #N/A | P38: =L38-N38 -> 0 | R38: =if($D38="X",vlookup($B38,'Hours Spread - Filtered'!$B:$AX,R$1,false),"") | S38: =if($D38="X",vlookup($B38,'Hours Spread - Filtered'!$B:$AX,S$1,false),"") | T38: =if($D38="X",vlookup($B38,'Hours Spread - Filtered'!$B:$AX,T$1,false),"") | U38: =if($D38="X",vlookup($B38,'Hours Spread - Filtered'!$B:$AX,U$1,false),"") | V38: =if($D38="X",vlookup($B38,'Hours Spread - Filtered'!$B:$AX,V$1,false),"") | W38: =if($D38="X",vlookup($B38,'Hours Spread - Filtered'!$B:$AX,W$1,false),"") | X38: =if($D38="X",vlookup($B38,'Hours Spread - Filtered'!$B:$AX,X$1,false),"") | Y38: =if($D38="X",vlookup($B38,'Hours Spread - Filtered'!$B:$AX,Y$1,false),"") | ... BL38: =if($D38="X",vlookup($B38,'Hours Spread - Filtered'!$B:$AX,BL$1,false),"") | BM38: {=IFERROR(index('Rate Card'!U$3:AF135,match(B38,'Rate Card'!A$3:A135,0),match(Assumptions!C$11,'Rate Card'!U$2:AF$2,0)),"")} | BN38: {=(index('Rate Card'!$C$4:$T135, match(BM38,Controls!H$21:H135,0),match(Assumptions!$C$11,'Rate Card'!C$2:T$2,0)))} -> #N/A
A39: Creative | B39: Graphic Designer | C39: TRUE | E39: =if(D39="x","Needs Staffing","") | F39: =(L39-N39)*BN39 -> #N/A | G39: =iferror(if(C39=true,0,(L39*(BN39/1.55*1.2285))),"") -> 0 | H39: =G39 -> 0 | I39: =G39-H39 -> 0 | J39: =sumif('Job Report'!I:I,B39,'Job Report'!H:H) -> 0 | K39: =if(C39=false,H39-J39,0) -> 0 | L39: =SUM(R39:BL39) -> 0 | N39: =if(B$4="Onsite Staffing in COGS", BF39,"") | O39: =BN39*N39 -> #N/A | P39: =L39-N39 -> 0 | R39: =if($D39="X",vlookup($B39,'Hours Spread - Filtered'!$B:$AX,R$1,false),"") | S39: =if($D39="X",vlookup($B39,'Hours Spread - Filtered'!$B:$AX,S$1,false),"") | T39: =if($D39="X",vlookup($B39,'Hours Spread - Filtered'!$B:$AX,T$1,false),"") | U39: =if($D39="X",vlookup($B39,'Hours Spread - Filtered'!$B:$AX,U$1,false),"") | V39: =if($D39="X",vlookup($B39,'Hours Spread - Filtered'!$B:$AX,V$1,false),"") | W39: =if($D39="X",vlookup($B39,'Hours Spread - Filtered'!$B:$AX,W$1,false),"") | X39: =if($D39="X",vlookup($B39,'Hours Spread - Filtered'!$B:$AX,X$1,false),"") | Y39: =if($D39="X",vlookup($B39,'Hours Spread - Filtered'!$B:$AX,Y$1,false),"") | ... BL39: =if($D39="X",vlookup($B39,'Hours Spread - Filtered'!$B:$AX,BL$1,false),"") | BM39: {=IFERROR(index('Rate Card'!U$3:AF135,match(B39,'Rate Card'!A$3:A135,0),match(Assumptions!C$11,'Rate Card'!U$2:AF$2,0)),"")} | BN39: {=(index('Rate Card'!$C$4:$T135, match(BM39,Controls!H$21:H135,0),match(Assumptions!$C$11,'Rate Card'!C$2:T$2,0)))} -> #N/A
A40: Creative | B40: Graphic Designer 2 | C40: TRUE | E40: =if(D40="x","Needs Staffing","") | F40: =(L40-N40)*BN40 -> #N/A | G40: =iferror(if(C40=true,0,(L40*(BN40/1.55*1.2285))),"") -> 0 | H40: =G40 -> 0 | I40: =G40-H40 -> 0 | J40: =sumif('Job Report'!I:I,B40,'Job Report'!H:H) -> 0 | K40: =if(C40=false,H40-J40,0) -> 0 | L40: =SUM(R40:BL40) -> 0 | N40: =if(B$4="Onsite Staffing in COGS", BF40,"") | O40: =BN40*N40 -> #N/A | P40: =L40-N40 -> 0 | R40: =if($D40="X",vlookup($B40,'Hours Spread - Filtered'!$B:$AX,R$1,false),"") | S40: =if($D40="X",vlookup($B40,'Hours Spread - Filtered'!$B:$AX,S$1,false),"") | T40: =if($D40="X",vlookup($B40,'Hours Spread - Filtered'!$B:$AX,T$1,false),"") | U40: =if($D40="X",vlookup($B40,'Hours Spread - Filtered'!$B:$AX,U$1,false),"") | V40: =if($D40="X",vlookup($B40,'Hours Spread - Filtered'!$B:$AX,V$1,false),"") | W40: =if($D40="X",vlookup($B40,'Hours Spread - Filtered'!$B:$AX,W$1,false),"") | X40: =if($D40="X",vlookup($B40,'Hours Spread - Filtered'!$B:$AX,X$1,false),"") | Y40: =if($D40="X",vlookup($B40,'Hours Spread - Filtered'!$B:$AX,Y$1,false),"") | ... BL40: =if($D40="X",vlookup($B40,'Hours Spread - Filtered'!$B:$AX,BL$1,false),"") | BM40: {=IFERROR(index('Rate Card'!U$3:AF135,match(B40,'Rate Card'!A$3:A135,0),match(Assumptions!C$11,'Rate Card'!U$2:AF$2,0)),"")} | BN40: {=(index('Rate Card'!$C$4:$T135, match(BM40,Controls!H$21:H135,0),match(Assumptions!$C$11,'Rate Card'!C$2:T$2,0)))} -> #N/A
A41: Creative | B41: Graphic Designer 3 | C41: TRUE | E41: =if(D41="x","Needs Staffing","") | F41: =(L41-N41)*BN41 -> #N/A | G41: =iferror(if(C41=true,0,(L41*(BN41/1.55*1.2285))),"") -> 0 | H41: =G41 -> 0 | I41: =G41-H41 -> 0 | J41: =sumif('Job Report'!I:I,B41,'Job Report'!H:H) -> 0 | K41: =if(C41=false,H41-J41,0) -> 0 | L41: =SUM(R41:BL41) -> 0 | N41: =if(B$4="Onsite Staffing in COGS", BF41,"") | O41: =BN41*N41 -> #N/A | P41: =L41-N41 -> 0 | R41: =if($D41="X",vlookup($B41,'Hours Spread - Filtered'!$B:$AX,R$1,false),"") | S41: =if($D41="X",vlookup($B41,'Hours Spread - Filtered'!$B:$AX,S$1,false),"") | T41: =if($D41="X",vlookup($B41,'Hours Spread - Filtered'!$B:$AX,T$1,false),"") | U41: =if($D41="X",vlookup($B41,'Hours Spread - Filtered'!$B:$AX,U$1,false),"") | V41: =if($D41="X",vlookup($B41,'Hours Spread - Filtered'!$B:$AX,V$1,false),"") | W41: =if($D41="X",vlookup($B41,'Hours Spread - Filtered'!$B:$AX,W$1,false),"") | X41: =if($D41="X",vlookup($B41,'Hours Spread - Filtered'!$B:$AX,X$1,false),"") | Y41: =if($D41="X",vlookup($B41,'Hours Spread - Filtered'!$B:$AX,Y$1,false),"") | ... BL41: =if($D41="X",vlookup($B41,'Hours Spread - Filtered'!$B:$AX,BL$1,false),"") | BM41: {=IFERROR(index('Rate Card'!U$3:AF135,match(B41,'Rate Card'!A$3:A135,0),match(Assumptions!C$11,'Rate Card'!U$2:AF$2,0)),"")} | BN41: {=(index('Rate Card'!$C$4:$T135, match(BM41,Controls!H$21:H135,0),match(Assumptions!$C$11,'Rate Card'!C$2:T$2,0)))} -> #N/A
A42: Creative | B42: Graphics Producer | C42: TRUE | E42: =if(D42="x","Needs Staffing","") | F42: =(L42-N42)*BN42 -> #N/A | G42: =iferror(if(C42=true,0,(L42*(BN42/1.55*1.2285))),"") -> 0 | H42: =G42 -> 0 | I42: =G42-H42 -> 0 | J42: =sumif('Job Report'!I:I,B42,'Job Report'!H:H) -> 0 | K42: =if(C42=false,H42-J42,0) -> 0 | L42: =SUM(R42:BL42) -> 0 | N42: =if(B$4="Onsite Staffing in COGS", BF42,"") | O42: =BN42*N42 -> #N/A | P42: =L42-N42 -> 0 | R42: =if($D42="X",vlookup($B42,'Hours Spread - Filtered'!$B:$AX,R$1,false),"") | S42: =if($D42="X",vlookup($B42,'Hours Spread - Filtered'!$B:$AX,S$1,false),"") | T42: =if($D42="X",vlookup($B42,'Hours Spread - Filtered'!$B:$AX,T$1,false),"") | U42: =if($D42="X",vlookup($B42,'Hours Spread - Filtered'!$B:$AX,U$1,false),"") | V42: =if($D42="X",vlookup($B42,'Hours Spread - Filtered'!$B:$AX,V$1,false),"") | W42: =if($D42="X",vlookup($B42,'Hours Spread - Filtered'!$B:$AX,W$1,false),"") | X42: =if($D42="X",vlookup($B42,'Hours Spread - Filtered'!$B:$AX,X$1,false),"") | Y42: =if($D42="X",vlookup($B42,'Hours Spread - Filtered'!$B:$AX,Y$1,false),"") | ... BL42: =if($D42="X",vlookup($B42,'Hours Spread - Filtered'!$B:$AX,BL$1,false),"") | BM42: {=IFERROR(index('Rate Card'!U$3:AF135,match(B42,'Rate Card'!A$3:A135,0),match(Assumptions!C$11,'Rate Card'!U$2:AF$2,0)),"")} | BN42: {=(index('Rate Card'!$C$4:$T135, match(BM42,Controls!H$21:H135,0),match(Assumptions!$C$11,'Rate Card'!C$2:T$2,0)))} -> #N/A
A43: Creative | B43: Creative Coordinator, Graphics | C43: TRUE | E43: =if(D43="x","Needs Staffing","") | F43: =(L43-N43)*BN43 -> #N/A | G43: =iferror(if(C43=true,0,(L43*(BN43/1.55*1.2285))),"") -> 0 | H43: =G43 -> 0 | I43: =G43-H43 -> 0 | J43: =sumif('Job Report'!I:I,B43,'Job Report'!H:H) -> 0 | K43: =if(C43=false,H43-J43,0) -> 0 | L43: =SUM(R43:BL43) -> 0 | N43: =if(B$4="Onsite Staffing in COGS", BF43,"") | O43: =BN43*N43 -> #N/A | P43: =L43-N43 -> 0 | R43: =if($D43="X",vlookup($B43,'Hours Spread - Filtered'!$B:$AX,R$1,false),"") | S43: =if($D43="X",vlookup($B43,'Hours Spread - Filtered'!$B:$AX,S$1,false),"") | T43: =if($D43="X",vlookup($B43,'Hours Spread - Filtered'!$B:$AX,T$1,false),"") | U43: =if($D43="X",vlookup($B43,'Hours Spread - Filtered'!$B:$AX,U$1,false),"") | V43: =if($D43="X",vlookup($B43,'Hours Spread - Filtered'!$B:$AX,V$1,false),"") | W43: =if($D43="X",vlookup($B43,'Hours Spread - Filtered'!$B:$AX,W$1,false),"") | X43: =if($D43="X",vlookup($B43,'Hours Spread - Filtered'!$B:$AX,X$1,false),"") | Y43: =if($D43="X",vlookup($B43,'Hours Spread - Filtered'!$B:$AX,Y$1,false),"") | ... BL43: =if($D43="X",vlookup($B43,'Hours Spread - Filtered'!$B:$AX,BL$1,false),"") | BM43: {=IFERROR(index('Rate Card'!U$3:AF135,match(B43,'Rate Card'!A$3:A135,0),match(Assumptions!C$11,'Rate Card'!U$2:AF$2,0)),"")} | BN43: {=(index('Rate Card'!$C$4:$T135, match(BM43,Controls!H$21:H135,0),match(Assumptions!$C$11,'Rate Card'!C$2:T$2,0)))} -> #N/A
A44: PRODUCTION | R44: =if($D44="X",vlookup($B44,'Hours Spread - Filtered'!$B:$AX,R$1,false),"") | S44: =if($D44="X",vlookup($B44,'Hours Spread - Filtered'!$B:$AX,S$1,false),"") | T44: =if($D44="X",vlookup($B44,'Hours Spread - Filtered'!$B:$AX,T$1,false),"") | U44: =if($D44="X",vlookup($B44,'Hours Spread - Filtered'!$B:$AX,U$1,false),"") | V44: =if($D44="X",vlookup($B44,'Hours Spread - Filtered'!$B:$AX,V$1,false),"") | W44: =if($D44="X",vlookup($B44,'Hours Spread - Filtered'!$B:$AX,W$1,false),"") | X44: =if($D44="X",vlookup($B44,'Hours Spread - Filtered'!$B:$AX,X$1,false),"") | Y44: =if($D44="X",vlookup($B44,'Hours Spread - Filtered'!$B:$AX,Y$1,false),"") | ... BL44: =if($D44="X",vlookup($B44,'Hours Spread - Filtered'!$B:$AX,BL$1,false),"")
A45: Production | B45: Director of Production | C45: TRUE | E45: =if(D45="x","Needs Staffing","") | F45: =(L45-N45)*BN45 -> #N/A | G45: =iferror(if(C45=true,0,(L45*(BN45/1.55*1.2285))),"") -> 0 | H45: =G45 -> 0 | I45: =G45-H45 -> 0 | J45: =sumif('Job Report'!I:I,B45,'Job Report'!H:H) -> 0 | K45: =if(C45=false,H45-J45,0) -> 0 | L45: =SUM(R45:BL45) -> 0 | N45: =if(B$4="Onsite Staffing in COGS", BF45,"") | O45: =BN45*N45 -> #N/A | P45: =L45-N45 -> 0 | AL45: =if($D45="X",vlookup($B45,'Hours Spread - Filtered'!$B:$AX,AL$1,false),"") | AM45: =if($D45="X",vlookup($B45,'Hours Spread - Filtered'!$B:$AX,AM$1,false),"") | AN45: =if($D45="X",vlookup($B45,'Hours Spread - Filtered'!$B:$AX,AN$1,false),"") | AO45: =if($D45="X",vlookup($B45,'Hours Spread - Filtered'!$B:$AX,AO$1,false),"") | AP45: =if($D45="X",vlookup($B45,'Hours Spread - Filtered'!$B:$AX,AP$1,false),"") | AQ45: =if($D45="X",vlookup($B45,'Hours Spread - Filtered'!$B:$AX,AQ$1,false),"") | AR45: =if($D45="X",vlookup($B45,'Hours Spread - Filtered'!$B:$AX,AR$1,false),"") | AS45: =if($D45="X",vlookup($B45,'Hours Spread - Filtered'!$B:$AX,AS$1,false),"") | ... BL45: =if($D45="X",vlookup($B45,'Hours Spread - Filtered'!$B:$AX,BL$1,false),"") | BM45: {=IFERROR(index('Rate Card'!U$3:AF135,match(B45,'Rate Card'!A$3:A135,0),match(Assumptions!C$11,'Rate Card'!U$2:AF$2,0)),"")} | BN45: {=(index('Rate Card'!$C$4:$T135, match(BM45,Controls!H$21:H135,0),match(Assumptions!$C$11,'Rate Card'!C$2:T$2,0)))} -> #N/A
A46: Production | B46: Executive Producer | C46: TRUE | E46: =if(D46="x","Needs Staffing","") | F46: =(L46-N46)*BN46 -> #N/A | G46: =iferror(if(C46=true,0,(L46*(BN46/1.55*1.2285))),"") -> 0 | H46: =G46 -> 0 | I46: =G46-H46 -> 0 | J46: =sumif('Job Report'!I:I,B46,'Job Report'!H:H) -> 0 | K46: =if(C46=false,H46-J46,0) -> 0 | L46: =SUM(R46:BL46) -> 0 | N46: =if(B$4="Onsite Staffing in COGS", BF46,"") | O46: =BN46*N46 -> #N/A | P46: =L46-N46 -> 0 | R46: =if($D46="X",vlookup($B46,'Hours Spread - Filtered'!$B:$AX,R$1,false),"") | S46: =if($D46="X",vlookup($B46,'Hours Spread - Filtered'!$B:$AX,S$1,false),"") | T46: =if($D46="X",vlookup($B46,'Hours Spread - Filtered'!$B:$AX,T$1,false),"") | U46: =if($D46="X",vlookup($B46,'Hours Spread - Filtered'!$B:$AX,U$1,false),"") | V46: =if($D46="X",vlookup($B46,'Hours Spread - Filtered'!$B:$AX,V$1,false),"") | W46: =if($D46="X",vlookup($B46,'Hours Spread - Filtered'!$B:$AX,W$1,false),"") | X46: =if($D46="X",vlookup($B46,'Hours Spread - Filtered'!$B:$AX,X$1,false),"") | Y46: =if($D46="X",vlookup($B46,'Hours Spread - Filtered'!$B:$AX,Y$1,false),"") | ... BL46: =if($D46="X",vlookup($B46,'Hours Spread - Filtered'!$B:$AX,BL$1,false),"") | BM46: {=IFERROR(index('Rate Card'!U$3:AF135,match(B46,'Rate Card'!A$3:A135,0),match(Assumptions!C$11,'Rate Card'!U$2:AF$2,0)),"")} | BN46: {=(index('Rate Card'!$C$4:$T135, match(BM46,Controls!H$21:H135,0),match(Assumptions!$C$11,'Rate Card'!C$2:T$2,0)))} -> #N/A
A47: Production | B47: Executive Producer 2 | C47: TRUE | E47: =if(D47="x","Needs Staffing","") | F47: =(L47-N47)*BN47 -> #N/A | G47: =iferror(if(C47=true,0,(L47*(BN47/1.55*1.2285))),"") -> 0 | H47: =G47 -> 0 | I47: =G47-H47 -> 0 | J47: =sumif('Job Report'!I:I,B47,'Job Report'!H:H) -> 0 | K47: =if(C47=false,H47-J47,0) -> 0 | L47: =SUM(R47:BL47) -> 0 | N47: =if(B$4="Onsite Staffing in COGS", BF47,"") | O47: =BN47*N47 -> #N/A | P47: =L47-N47 -> 0 | R47: =if($D47="X",vlookup($B47,'Hours Spread - Filtered'!$B:$AX,R$1,false),"") | S47: =if($D47="X",vlookup($B47,'Hours Spread - Filtered'!$B:$AX,S$1,false),"") | T47: =if($D47="X",vlookup($B47,'Hours Spread - Filtered'!$B:$AX,T$1,false),"") | U47: =if($D47="X",vlookup($B47,'Hours Spread - Filtered'!$B:$AX,U$1,false),"") | V47: =if($D47="X",vlookup($B47,'Hours Spread - Filtered'!$B:$AX,V$1,false),"") | W47: =if($D47="X",vlookup($B47,'Hours Spread - Filtered'!$B:$AX,W$1,false),"") | X47: =if($D47="X",vlookup($B47,'Hours Spread - Filtered'!$B:$AX,X$1,false),"") | Y47: =if($D47="X",vlookup($B47,'Hours Spread - Filtered'!$B:$AX,Y$1,false),"") | ... BL47: =if($D47="X",vlookup($B47,'Hours Spread - Filtered'!$B:$AX,BL$1,false),"") | BM47: {=IFERROR(index('Rate Card'!U$3:AF135,match(B47,'Rate Card'!A$3:A135,0),match(Assumptions!C$11,'Rate Card'!U$2:AF$2,0)),"")} | BN47: {=(index('Rate Card'!$C$4:$T135, match(BM47,Controls!H$21:H135,0),match(Assumptions!$C$11,'Rate Card'!C$2:T$2,0)))} -> #N/A
A48: Production | B48: Producer | C48: TRUE | E48: =if(D48="x","Needs Staffing","") | F48: =(L48-N48)*BN48 -> #N/A | G48: =iferror(if(C48=true,0,(L48*(BN48/1.55*1.2285))),"") -> 0 | H48: =G48 -> 0 | I48: =G48-H48 -> 0 | J48: =sumif('Job Report'!I:I,B48,'Job Report'!H:H) -> 0 | K48: =if(C48=false,H48-J48,0) -> 0 | L48: =SUM(R48:BL48) -> 0 | N48: =if(B$4="Onsite Staffing in COGS", BF48,"") | O48: =BN48*N48 -> #N/A | P48: =L48-N48 -> 0 | R48: =if($D48="X",vlookup($B48,'Hours Spread - Filtered'!$B:$AX,R$1,false),"") | S48: =if($D48="X",vlookup($B48,'Hours Spread - Filtered'!$B:$AX,S$1,false),"") | T48: =if($D48="X",vlookup($B48,'Hours Spread - Filtered'!$B:$AX,T$1,false),"") | U48: =if($D48="X",vlookup($B48,'Hours Spread - Filtered'!$B:$AX,U$1,false),"") | V48: =if($D48="X",vlookup($B48,'Hours Spread - Filtered'!$B:$AX,V$1,false),"") | W48: =if($D48="X",vlookup($B48,'Hours Spread - Filtered'!$B:$AX,W$1,false),"") | X48: =if($D48="X",vlookup($B48,'Hours Spread - Filtered'!$B:$AX,X$1,false),"") | Y48: =if($D48="X",vlookup($B48,'Hours Spread - Filtered'!$B:$AX,Y$1,false),"") | ... BL48: =if($D48="X",vlookup($B48,'Hours Spread - Filtered'!$B:$AX,BL$1,false),"") | BM48: {=IFERROR(index('Rate Card'!U$3:AF135,match(B48,'Rate Card'!A$3:A135,0),match(Assumptions!C$11,'Rate Card'!U$2:AF$2,0)),"")} | BN48: {=(index('Rate Card'!$C$4:$T135, match(BM48,Controls!H$21:H135,0),match(Assumptions!$C$11,'Rate Card'!C$2:T$2,0)))} -> #N/A
A49: Production | B49: Producer 2 | C49: TRUE | E49: =if(D49="x","Needs Staffing","") | F49: =(L49-N49)*BN49 -> #N/A | G49: =iferror(if(C49=true,0,(L49*(BN49/1.55*1.2285))),"") -> 0 | H49: =G49 -> 0 | I49: =G49-H49 -> 0 | J49: =sumif('Job Report'!I:I,B49,'Job Report'!H:H) -> 0 | K49: =if(C49=false,H49-J49,0) -> 0 | L49: =SUM(R49:BL49) -> 0 | N49: =if(B$4="Onsite Staffing in COGS", BF49,"") | O49: =BN49*N49 -> #N/A | P49: =L49-N49 -> 0 | R49: =if($D49="X",vlookup($B49,'Hours Spread - Filtered'!$B:$AX,R$1,false),"") | S49: =if($D49="X",vlookup($B49,'Hours Spread - Filtered'!$B:$AX,S$1,false),"") | T49: =if($D49="X",vlookup($B49,'Hours Spread - Filtered'!$B:$AX,T$1,false),"") | U49: =if($D49="X",vlookup($B49,'Hours Spread - Filtered'!$B:$AX,U$1,false),"") | V49: =if($D49="X",vlookup($B49,'Hours Spread - Filtered'!$B:$AX,V$1,false),"") | W49: =if($D49="X",vlookup($B49,'Hours Spread - Filtered'!$B:$AX,W$1,false),"") | X49: =if($D49="X",vlookup($B49,'Hours Spread - Filtered'!$B:$AX,X$1,false),"") | Y49: =if($D49="X",vlookup($B49,'Hours Spread - Filtered'!$B:$AX,Y$1,false),"") | ... BL49: =if($D49="X",vlookup($B49,'Hours Spread - Filtered'!$B:$AX,BL$1,false),"") | BM49: {=IFERROR(index('Rate Card'!U$3:AF135,match(B49,'Rate Card'!A$3:A135,0),match(Assumptions!C$11,'Rate Card'!U$2:AF$2,0)),"")} | BN49: {=(index('Rate Card'!$C$4:$T135, match(BM49,Controls!H$21:H135,0),match(Assumptions!$C$11,'Rate Card'!C$2:T$2,0)))} -> #N/A
A50: Production | B50: Producer 3 | C50: TRUE | E50: =if(D50="x","Needs Staffing","") | F50: =(L50-N50)*BN50 -> #N/A | G50: =iferror(if(C50=true,0,(L50*(BN50/1.55*1.2285))),"") -> 0 | H50: =G50 -> 0 | I50: =G50-H50 -> 0 | J50: =sumif('Job Report'!I:I,B50,'Job Report'!H:H) -> 0 | K50: =if(C50=false,H50-J50,0) -> 0 | L50: =SUM(R50:BL50) -> 0 | N50: =if(B$4="Onsite Staffing in COGS", BF50,"") | O50: =BN50*N50 -> #N/A | P50: =L50-N50 -> 0 | R50: =if($D50="X",vlookup($B50,'Hours Spread - Filtered'!$B:$AX,R$1,false),"") | S50: =if($D50="X",vlookup($B50,'Hours Spread - Filtered'!$B:$AX,S$1,false),"") | T50: =if($D50="X",vlookup($B50,'Hours Spread - Filtered'!$B:$AX,T$1,false),"") | U50: =if($D50="X",vlookup($B50,'Hours Spread - Filtered'!$B:$AX,U$1,false),"") | V50: =if($D50="X",vlookup($B50,'Hours Spread - Filtered'!$B:$AX,V$1,false),"") | W50: =if($D50="X",vlookup($B50,'Hours Spread - Filtered'!$B:$AX,W$1,false),"") | X50: =if($D50="X",vlookup($B50,'Hours Spread - Filtered'!$B:$AX,X$1,false),"") | Y50: =if($D50="X",vlookup($B50,'Hours Spread - Filtered'!$B:$AX,Y$1,false),"") | ... BL50: =if($D50="X",vlookup($B50,'Hours Spread - Filtered'!$B:$AX,BL$1,false),"") | BM50: {=IFERROR(index('Rate Card'!U$3:AF135,match(B50,'Rate Card'!A$3:A135,0),match(Assumptions!C$11,'Rate Card'!U$2:AF$2,0)),"")} | BN50: {=(index('Rate Card'!$C$4:$T135, match(BM50,Controls!H$21:H135,0),match(Assumptions!$C$11,'Rate Card'!C$2:T$2,0)))} -> #N/A
A51: Production | B51: Associate Producer | C51: TRUE | E51: =if(D51="x","Needs Staffing","") | F51: =(L51-N51)*BN51 -> #N/A | G51: =iferror(if(C51=true,0,(L51*(BN51/1.55*1.2285))),"") -> 0 | H51: =G51 -> 0 | I51: =G51-H51 -> 0 | J51: =sumif('Job Report'!I:I,B51,'Job Report'!H:H) -> 0 | K51: =if(C51=false,H51-J51,0) -> 0 | L51: =SUM(R51:BL51) -> 0 | N51: =if(B$4="Onsite Staffing in COGS", BF51,"") | O51: =BN51*N51 -> #N/A | P51: =L51-N51 -> 0 | R51: =if($D51="X",vlookup($B51,'Hours Spread - Filtered'!$B:$AX,R$1,false),"") | S51: =if($D51="X",vlookup($B51,'Hours Spread - Filtered'!$B:$AX,S$1,false),"") | T51: =if($D51="X",vlookup($B51,'Hours Spread - Filtered'!$B:$AX,T$1,false),"") | U51: =if($D51="X",vlookup($B51,'Hours Spread - Filtered'!$B:$AX,U$1,false),"") | V51: =if($D51="X",vlookup($B51,'Hours Spread - Filtered'!$B:$AX,V$1,false),"") | W51: =if($D51="X",vlookup($B51,'Hours Spread - Filtered'!$B:$AX,W$1,false),"") | X51: =if($D51="X",vlookup($B51,'Hours Spread - Filtered'!$B:$AX,X$1,false),"") | Y51: =if($D51="X",vlookup($B51,'Hours Spread - Filtered'!$B:$AX,Y$1,false),"") | ... BL51: =if($D51="X",vlookup($B51,'Hours Spread - Filtered'!$B:$AX,BL$1,false),"") | BM51: {=IFERROR(index('Rate Card'!U$3:AF135,match(B51,'Rate Card'!A$3:A135,0),match(Assumptions!C$11,'Rate Card'!U$2:AF$2,0)),"")} | BN51: {=(index('Rate Card'!$C$4:$T135, match(BM51,Controls!H$21:H135,0),match(Assumptions!$C$11,'Rate Card'!C$2:T$2,0)))} -> #N/A
A52: Production | B52: Associate Producer 2 | C52: TRUE | E52: =if(D52="x","Needs Staffing","") | F52: =(L52-N52)*BN52 -> #N/A | G52: =iferror(if(C52=true,0,(L52*(BN52/1.55*1.2285))),"") -> 0 | H52: =G52 -> 0 | I52: =G52-H52 -> 0 | J52: =sumif('Job Report'!I:I,B52,'Job Report'!H:H) -> 0 | K52: =if(C52=false,H52-J52,0) -> 0 | L52: =SUM(R52:BL52) -> 0 | N52: =if(B$4="Onsite Staffing in COGS", BF52,"") | O52: =BN52*N52 -> #N/A | P52: =L52-N52 -> 0 | R52: =if($D52="X",vlookup($B52,'Hours Spread - Filtered'!$B:$AX,R$1,false),"") | S52: =if($D52="X",vlookup($B52,'Hours Spread - Filtered'!$B:$AX,S$1,false),"") | T52: =if($D52="X",vlookup($B52,'Hours Spread - Filtered'!$B:$AX,T$1,false),"") | U52: =if($D52="X",vlookup($B52,'Hours Spread - Filtered'!$B:$AX,U$1,false),"") | V52: =if($D52="X",vlookup($B52,'Hours Spread - Filtered'!$B:$AX,V$1,false),"") | W52: =if($D52="X",vlookup($B52,'Hours Spread - Filtered'!$B:$AX,W$1,false),"") | X52: =if($D52="X",vlookup($B52,'Hours Spread - Filtered'!$B:$AX,X$1,false),"") | Y52: =if($D52="X",vlookup($B52,'Hours Spread - Filtered'!$B:$AX,Y$1,false),"") | ... BL52: =if($D52="X",vlookup($B52,'Hours Spread - Filtered'!$B:$AX,BL$1,false),"") | BM52: {=IFERROR(index('Rate Card'!U$3:AF135,match(B52,'Rate Card'!A$3:A135,0),match(Assumptions!C$11,'Rate Card'!U$2:AF$2,0)),"")} | BN52: {=(index('Rate Card'!$C$4:$T135, match(BM52,Controls!H$21:H135,0),match(Assumptions!$C$11,'Rate Card'!C$2:T$2,0)))} -> #N/A
A53: Production | B53: Sr. Coordinator | C53: TRUE | E53: =if(D53="x","Needs Staffing","") | F53: =(L53-N53)*BN53 -> #N/A | G53: =iferror(if(C53=true,0,(L53*(BN53/1.55*1.2285))),"") -> 0 | H53: =G53 -> 0 | I53: =G53-H53 -> 0 | J53: =sumif('Job Report'!I:I,B53,'Job Report'!H:H) -> 0 | K53: =if(C53=false,H53-J53,0) -> 0 | L53: =SUM(R53:BL53) -> 0 | N53: =if(B$4="Onsite Staffing in COGS", BF53,"") | O53: =BN53*N53 -> #N/A | P53: =L53-N53 -> 0 | R53: =if($D53="X",vlookup($B53,'Hours Spread - Filtered'!$B:$AX,R$1,false),"") | S53: =if($D53="X",vlookup($B53,'Hours Spread - Filtered'!$B:$AX,S$1,false),"") | T53: =if($D53="X",vlookup($B53,'Hours Spread - Filtered'!$B:$AX,T$1,false),"") | U53: =if($D53="X",vlookup($B53,'Hours Spread - Filtered'!$B:$AX,U$1,false),"") | V53: =if($D53="X",vlookup($B53,'Hours Spread - Filtered'!$B:$AX,V$1,false),"") | W53: =if($D53="X",vlookup($B53,'Hours Spread - Filtered'!$B:$AX,W$1,false),"") | X53: =if($D53="X",vlookup($B53,'Hours Spread - Filtered'!$B:$AX,X$1,false),"") | Y53: =if($D53="X",vlookup($B53,'Hours Spread - Filtered'!$B:$AX,Y$1,false),"") | ... BL53: =if($D53="X",vlookup($B53,'Hours Spread - Filtered'!$B:$AX,BL$1,false),"") | BM53: {=IFERROR(index('Rate Card'!U$3:AF135,match(B53,'Rate Card'!A$3:A135,0),match(Assumptions!C$11,'Rate Card'!U$2:AF$2,0)),"")} | BN53: {=(index('Rate Card'!$C$4:$T135, match(BM53,Controls!H$21:H135,0),match(Assumptions!$C$11,'Rate Card'!C$2:T$2,0)))} -> #N/A
A54: Production | B54: Sr. Coordinator 2 | C54: TRUE | E54: =if(D54="x","Needs Staffing","") | F54: =(L54-N54)*BN54 -> #N/A | G54: =iferror(if(C54=true,0,(L54*(BN54/1.55*1.2285))),"") -> 0 | H54: =G54 -> 0 | I54: =G54-H54 -> 0 | J54: =sumif('Job Report'!I:I,B54,'Job Report'!H:H) -> 0 | K54: =if(C54=false,H54-J54,0) -> 0 | L54: =SUM(R54:BL54) -> 0 | N54: =if(B$4="Onsite Staffing in COGS", BF54,"") | O54: =BN54*N54 -> #N/A | P54: =L54-N54 -> 0 | R54: =if($D54="X",vlookup($B54,'Hours Spread - Filtered'!$B:$AX,R$1,false),"") | S54: =if($D54="X",vlookup($B54,'Hours Spread - Filtered'!$B:$AX,S$1,false),"") | T54: =if($D54="X",vlookup($B54,'Hours Spread - Filtered'!$B:$AX,T$1,false),"") | U54: =if($D54="X",vlookup($B54,'Hours Spread - Filtered'!$B:$AX,U$1,false),"") | V54: =if($D54="X",vlookup($B54,'Hours Spread - Filtered'!$B:$AX,V$1,false),"") | W54: =if($D54="X",vlookup($B54,'Hours Spread - Filtered'!$B:$AX,W$1,false),"") | X54: =if($D54="X",vlookup($B54,'Hours Spread - Filtered'!$B:$AX,X$1,false),"") | Y54: =if($D54="X",vlookup($B54,'Hours Spread - Filtered'!$B:$AX,Y$1,false),"") | ... BL54: =if($D54="X",vlookup($B54,'Hours Spread - Filtered'!$B:$AX,BL$1,false),"") | BM54: {=IFERROR(index('Rate Card'!U$3:AF135,match(B54,'Rate Card'!A$3:A135,0),match(Assumptions!C$11,'Rate Card'!U$2:AF$2,0)),"")} | BN54: {=(index('Rate Card'!$C$4:$T135, match(BM54,Controls!H$21:H135,0),match(Assumptions!$C$11,'Rate Card'!C$2:T$2,0)))} -> #N/A
A55: Production | B55: Sr. Coordinator 3 | C55: TRUE | E55: =if(D55="x","Needs Staffing","") | F55: =(L55-N55)*BN55 -> #N/A | G55: =iferror(if(C55=true,0,(L55*(BN55/1.55*1.2285))),"") -> 0 | H55: =G55 -> 0 | I55: =G55-H55 -> 0 | J55: =sumif('Job Report'!I:I,B55,'Job Report'!H:H) -> 0 | K55: =if(C55=false,H55-J55,0) -> 0 | L55: =SUM(R55:BL55) -> 0 | N55: =if(B$4="Onsite Staffing in COGS", BF55,"") | O55: =BN55*N55 -> #N/A | P55: =L55-N55 -> 0 | R55: =if($D55="X",vlookup($B55,'Hours Spread - Filtered'!$B:$AX,R$1,false),"") | S55: =if($D55="X",vlookup($B55,'Hours Spread - Filtered'!$B:$AX,S$1,false),"") | T55: =if($D55="X",vlookup($B55,'Hours Spread - Filtered'!$B:$AX,T$1,false),"") | U55: =if($D55="X",vlookup($B55,'Hours Spread - Filtered'!$B:$AX,U$1,false),"") | V55: =if($D55="X",vlookup($B55,'Hours Spread - Filtered'!$B:$AX,V$1,false),"") | W55: =if($D55="X",vlookup($B55,'Hours Spread - Filtered'!$B:$AX,W$1,false),"") | X55: =if($D55="X",vlookup($B55,'Hours Spread - Filtered'!$B:$AX,X$1,false),"") | Y55: =if($D55="X",vlookup($B55,'Hours Spread - Filtered'!$B:$AX,Y$1,false),"") | ... BL55: =if($D55="X",vlookup($B55,'Hours Spread - Filtered'!$B:$AX,BL$1,false),"") | BM55: {=IFERROR(index('Rate Card'!U$3:AF135,match(B55,'Rate Card'!A$3:A135,0),match(Assumptions!C$11,'Rate Card'!U$2:AF$2,0)),"")} | BN55: {=(index('Rate Card'!$C$4:$T135, match(BM55,Controls!H$21:H135,0),match(Assumptions!$C$11,'Rate Card'!C$2:T$2,0)))} -> #N/A
A56: Production | B56: Registration Producer | C56: TRUE | E56: =if(D56="x","Needs Staffing","") | F56: =(L56-N56)*BN56 -> #N/A | G56: =iferror(if(C56=true,0,(L56*(BN56/1.55*1.2285))),"") -> 0 | H56: =G56 -> 0 | I56: =G56-H56 -> 0 | J56: =sumif('Job Report'!I:I,B56,'Job Report'!H:H) -> 0 | K56: =if(C56=false,H56-J56,0) -> 0 | L56: =SUM(R56:BL56) -> 0 | N56: =if(B$4="Onsite Staffing in COGS", BF56,"") | O56: =BN56*N56 -> #N/A | P56: =L56-N56 -> 0 | R56: =if($D56="X",vlookup($B56,'Hours Spread - Filtered'!$B:$AX,R$1,false),"") | S56: =if($D56="X",vlookup($B56,'Hours Spread - Filtered'!$B:$AX,S$1,false),"") | T56: =if($D56="X",vlookup($B56,'Hours Spread - Filtered'!$B:$AX,T$1,false),"") | U56: =if($D56="X",vlookup($B56,'Hours Spread - Filtered'!$B:$AX,U$1,false),"") | V56: =if($D56="X",vlookup($B56,'Hours Spread - Filtered'!$B:$AX,V$1,false),"") | W56: =if($D56="X",vlookup($B56,'Hours Spread - Filtered'!$B:$AX,W$1,false),"") | X56: =if($D56="X",vlookup($B56,'Hours Spread - Filtered'!$B:$AX,X$1,false),"") | Y56: =if($D56="X",vlookup($B56,'Hours Spread - Filtered'!$B:$AX,Y$1,false),"") | ... BL56: =if($D56="X",vlookup($B56,'Hours Spread - Filtered'!$B:$AX,BL$1,false),"") | BM56: {=IFERROR(index('Rate Card'!U$3:AF135,match(B56,'Rate Card'!A$3:A135,0),match(Assumptions!C$11,'Rate Card'!U$2:AF$2,0)),"")} | BN56: {=(index('Rate Card'!$C$4:$T135, match(BM56,Controls!H$21:H135,0),match(Assumptions!$C$11,'Rate Card'!C$2:T$2,0)))} -> #N/A
A57: Production | B57: Sustainability Producer | C57: TRUE | E57: =if(D57="x","Needs Staffing","") | F57: =(L57-N57)*BN57 -> #N/A | G57: =iferror(if(C57=true,0,(L57*(BN57/1.55*1.2285))),"") -> 0 | H57: =G57 -> 0 | I57: =G57-H57 -> 0 | J57: =sumif('Job Report'!I:I,B57,'Job Report'!H:H) -> 0 | K57: =if(C57=false,H57-J57,0) -> 0 | L57: =SUM(R57:BL57) -> 0 | N57: =if(B$4="Onsite Staffing in COGS", BF57,"") | O57: =BN57*N57 -> #N/A | P57: =L57-N57 -> 0 | R57: =if($D57="X",vlookup($B57,'Hours Spread - Filtered'!$B:$AX,R$1,false),"") | S57: =if($D57="X",vlookup($B57,'Hours Spread - Filtered'!$B:$AX,S$1,false),"") | T57: =if($D57="X",vlookup($B57,'Hours Spread - Filtered'!$B:$AX,T$1,false),"") | U57: =if($D57="X",vlookup($B57,'Hours Spread - Filtered'!$B:$AX,U$1,false),"") | V57: =if($D57="X",vlookup($B57,'Hours Spread - Filtered'!$B:$AX,V$1,false),"") | W57: =if($D57="X",vlookup($B57,'Hours Spread - Filtered'!$B:$AX,W$1,false),"") | X57: =if($D57="X",vlookup($B57,'Hours Spread - Filtered'!$B:$AX,X$1,false),"") | Y57: =if($D57="X",vlookup($B57,'Hours Spread - Filtered'!$B:$AX,Y$1,false),"") | ... BL57: =if($D57="X",vlookup($B57,'Hours Spread - Filtered'!$B:$AX,BL$1,false),"") | BM57: {=IFERROR(index('Rate Card'!U$3:AF135,match(B57,'Rate Card'!A$3:A135,0),match(Assumptions!C$11,'Rate Card'!U$2:AF$2,0)),"")} | BN57: {=(index('Rate Card'!$C$4:$T135, match(BM57,Controls!H$21:H135,0),match(Assumptions!$C$11,'Rate Card'!C$2:T$2,0)))} -> #N/A
A58: Production | B58: Line Producer | C58: TRUE | E58: =if(D58="x","Needs Staffing","") | F58: =(L58-N58)*BN58 -> #N/A | G58: =iferror(if(C58=true,0,(L58*(BN58/1.55*1.2285))),"") -> 0 | H58: =G58 -> 0 | I58: =G58-H58 -> 0 | J58: =sumif('Job Report'!I:I,B58,'Job Report'!H:H) -> 0 | K58: =if(C58=false,H58-J58,0) -> 0 | L58: =SUM(R58:BL58) -> 0 | N58: =if(B$4="Onsite Staffing in COGS", BF58,"") | O58: =BN58*N58 -> #N/A | P58: =L58-N58 -> 0 | R58: =if($D58="X",vlookup($B58,'Hours Spread - Filtered'!$B:$AX,R$1,false),"") | S58: =if($D58="X",vlookup($B58,'Hours Spread - Filtered'!$B:$AX,S$1,false),"") | T58: =if($D58="X",vlookup($B58,'Hours Spread - Filtered'!$B:$AX,T$1,false),"") | U58: =if($D58="X",vlookup($B58,'Hours Spread - Filtered'!$B:$AX,U$1,false),"") | V58: =if($D58="X",vlookup($B58,'Hours Spread - Filtered'!$B:$AX,V$1,false),"") | W58: =if($D58="X",vlookup($B58,'Hours Spread - Filtered'!$B:$AX,W$1,false),"") | X58: =if($D58="X",vlookup($B58,'Hours Spread - Filtered'!$B:$AX,X$1,false),"") | Y58: =if($D58="X",vlookup($B58,'Hours Spread - Filtered'!$B:$AX,Y$1,false),"") | ... BL58: =if($D58="X",vlookup($B58,'Hours Spread - Filtered'!$B:$AX,BL$1,false),"") | BM58: {=IFERROR(index('Rate Card'!U$3:AF135,match(B58,'Rate Card'!A$3:A135,0),match(Assumptions!C$11,'Rate Card'!U$2:AF$2,0)),"")} | BN58: {=(index('Rate Card'!$C$4:$T135, match(BM58,Controls!H$21:H135,0),match(Assumptions!$C$11,'Rate Card'!C$2:T$2,0)))} -> #N/A
A59: Production | B59: Sr. Technology Director | C59: TRUE | E59: =if(D59="x","Needs Staffing","") | F59: =(L59-N59)*BN59 -> #N/A | G59: =iferror(if(C59=true,0,(L59*(BN59/1.55*1.2285))),"") -> 0 | H59: =G59 -> 0 | I59: =G59-H59 -> 0 | J59: =sumif('Job Report'!I:I,B59,'Job Report'!H:H) -> 0 | K59: =if(C59=false,H59-J59,0) -> 0 | L59: =SUM(R59:BL59) -> 0 | N59: =if(B$4="Onsite Staffing in COGS", BF59,"") | O59: =BN59*N59 -> #N/A | P59: =L59-N59 -> 0 | R59: =if($D59="X",vlookup($B59,'Hours Spread - Filtered'!$B:$AX,R$1,false),"") | S59: =if($D59="X",vlookup($B59,'Hours Spread - Filtered'!$B:$AX,S$1,false),"") | T59: =if($D59="X",vlookup($B59,'Hours Spread - Filtered'!$B:$AX,T$1,false),"") | U59: =if($D59="X",vlookup($B59,'Hours Spread - Filtered'!$B:$AX,U$1,false),"") | V59: =if($D59="X",vlookup($B59,'Hours Spread - Filtered'!$B:$AX,V$1,false),"") | W59: =if($D59="X",vlookup($B59,'Hours Spread - Filtered'!$B:$AX,W$1,false),"") | X59: =if($D59="X",vlookup($B59,'Hours Spread - Filtered'!$B:$AX,X$1,false),"") | Y59: =if($D59="X",vlookup($B59,'Hours Spread - Filtered'!$B:$AX,Y$1,false),"") | ... BL59: =if($D59="X",vlookup($B59,'Hours Spread - Filtered'!$B:$AX,BL$1,false),"") | BM59: {=IFERROR(index('Rate Card'!U$3:AF135,match(B59,'Rate Card'!A$3:A135,0),match(Assumptions!C$11,'Rate Card'!U$2:AF$2,0)),"")} | BN59: {=(index('Rate Card'!$C$4:$T135, match(BM59,Controls!H$21:H135,0),match(Assumptions!$C$11,'Rate Card'!C$2:T$2,0)))} -> #N/A
A60: Technical | B60: Technical Director | C60: TRUE | E60: =if(D60="x","Needs Staffing","") | F60: =(L60-N60)*BN60 -> #N/A | G60: =iferror(if(C60=true,0,(L60*(BN60/1.55*1.2285))),"") -> 0 | H60: =G60 -> 0 | I60: =G60-H60 -> 0 | J60: =sumif('Job Report'!I:I,B60,'Job Report'!H:H) -> 0 | K60: =if(C60=false,H60-J60,0) -> 0 | L60: =SUM(R60:BL60) -> 0 | N60: =if(B$4="Onsite Staffing in COGS", BF60,"") | O60: =BN60*N60 -> #N/A | P60: =L60-N60 -> 0 | R60: =if($D60="X",vlookup($B60,'Hours Spread - Filtered'!$B:$AX,R$1,false),"") | S60: =if($D60="X",vlookup($B60,'Hours Spread - Filtered'!$B:$AX,S$1,false),"") | T60: =if($D60="X",vlookup($B60,'Hours Spread - Filtered'!$B:$AX,T$1,false),"") | U60: =if($D60="X",vlookup($B60,'Hours Spread - Filtered'!$B:$AX,U$1,false),"") | V60: =if($D60="X",vlookup($B60,'Hours Spread - Filtered'!$B:$AX,V$1,false),"") | W60: =if($D60="X",vlookup($B60,'Hours Spread - Filtered'!$B:$AX,W$1,false),"") | X60: =if($D60="X",vlookup($B60,'Hours Spread - Filtered'!$B:$AX,X$1,false),"") | Y60: =if($D60="X",vlookup($B60,'Hours Spread - Filtered'!$B:$AX,Y$1,false),"") | ... BL60: =if($D60="X",vlookup($B60,'Hours Spread - Filtered'!$B:$AX,BL$1,false),"") | BM60: {=IFERROR(index('Rate Card'!U$3:AF135,match(B60,'Rate Card'!A$3:A135,0),match(Assumptions!C$11,'Rate Card'!U$2:AF$2,0)),"")} | BN60: {=(index('Rate Card'!$C$4:$T135, match(BM60,Controls!H$21:H135,0),match(Assumptions!$C$11,'Rate Card'!C$2:T$2,0)))} -> #N/A
A61: Technical | B61: Technical Director 2 | C61: FALSE | E61: =if(D61="x","Needs Staffing","") | F61: =(L61-N61)*BN61 -> #N/A | G61: =iferror(if(C61=true,0,(L61*(BN61/1.55*1.2285))),"") | H61: =G61 | I61: =G61-H61 -> 0 | J61: =sumif('Job Report'!I:I,B61,'Job Report'!H:H) -> 0 | K61: =if(C61=false,H61-J61,0) -> 0 | L61: =SUM(R61:BL61) -> 0 | N61: =if(B$4="Onsite Staffing in COGS", BF61,"") | O61: =BN61*N61 -> #N/A | P61: =L61-N61 -> 0 | R61: =if($D61="X",vlookup($B61,'Hours Spread - Filtered'!$B:$AX,R$1,false),"") | S61: =if($D61="X",vlookup($B61,'Hours Spread - Filtered'!$B:$AX,S$1,false),"") | T61: =if($D61="X",vlookup($B61,'Hours Spread - Filtered'!$B:$AX,T$1,false),"") | U61: =if($D61="X",vlookup($B61,'Hours Spread - Filtered'!$B:$AX,U$1,false),"") | V61: =if($D61="X",vlookup($B61,'Hours Spread - Filtered'!$B:$AX,V$1,false),"") | W61: =if($D61="X",vlookup($B61,'Hours Spread - Filtered'!$B:$AX,W$1,false),"") | X61: =if($D61="X",vlookup($B61,'Hours Spread - Filtered'!$B:$AX,X$1,false),"") | Y61: =if($D61="X",vlookup($B61,'Hours Spread - Filtered'!$B:$AX,Y$1,false),"") | ... BL61: =if($D61="X",vlookup($B61,'Hours Spread - Filtered'!$B:$AX,BL$1,false),"") | BM61: {=IFERROR(index('Rate Card'!U$3:AF135,match(B61,'Rate Card'!A$3:A135,0),match(Assumptions!C$11,'Rate Card'!U$2:AF$2,0)),"")} | BN61: {=(index('Rate Card'!$C$4:$T135, match(BM61,Controls!H$21:H135,0),match(Assumptions!$C$11,'Rate Card'!C$2:T$2,0)))} -> #N/A
A62: Technical | B62: Technical Producer | C62: FALSE | E62: =if(D62="x","Needs Staffing","") | F62: =(L62-N62)*BN62 -> #N/A | G62: =iferror(if(C62=true,0,(L62*(BN62/1.55*1.2285))),"") | H62: =G62 | I62: =G62-H62 -> 0 | J62: =sumif('Job Report'!I:I,B62,'Job Report'!H:H) -> 0 | K62: =if(C62=false,H62-J62,0) -> 0 | L62: =SUM(R62:BL62) -> 0 | N62: =if(B$4="Onsite Staffing in COGS", BF62,"") | O62: =BN62*N62 -> #N/A | P62: =L62-N62 -> 0 | R62: =if($D62="X",vlookup($B62,'Hours Spread - Filtered'!$B:$AX,R$1,false),"") | S62: =if($D62="X",vlookup($B62,'Hours Spread - Filtered'!$B:$AX,S$1,false),"") | T62: =if($D62="X",vlookup($B62,'Hours Spread - Filtered'!$B:$AX,T$1,false),"") | U62: =if($D62="X",vlookup($B62,'Hours Spread - Filtered'!$B:$AX,U$1,false),"") | V62: =if($D62="X",vlookup($B62,'Hours Spread - Filtered'!$B:$AX,V$1,false),"") | W62: =if($D62="X",vlookup($B62,'Hours Spread - Filtered'!$B:$AX,W$1,false),"") | X62: =if($D62="X",vlookup($B62,'Hours Spread - Filtered'!$B:$AX,X$1,false),"") | Y62: =if($D62="X",vlookup($B62,'Hours Spread - Filtered'!$B:$AX,Y$1,false),"") | ... BL62: =if($D62="X",vlookup($B62,'Hours Spread - Filtered'!$B:$AX,BL$1,false),"") | BM62: {=IFERROR(index('Rate Card'!U$3:AF135,match(B62,'Rate Card'!A$3:A135,0),match(Assumptions!C$11,'Rate Card'!U$2:AF$2,0)),"")} | BN62: {=(index('Rate Card'!$C$4:$T135, match(BM62,Controls!H$21:H135,0),match(Assumptions!$C$11,'Rate Card'!C$2:T$2,0)))} -> #N/A
A63: Technical | B63: Associate Technical Producer | C63: TRUE | E63: =if(D63="x","Needs Staffing","") | F63: =(L63-N63)*BN63 -> #N/A | G63: =iferror(if(C63=true,0,(L63*(BN63/1.55*1.2285))),"") -> 0 | H63: =G63 -> 0 | I63: =G63-H63 -> 0 | J63: =sumif('Job Report'!I:I,B63,'Job Report'!H:H) -> 0 | K63: =if(C63=false,H63-J63,0) -> 0 | L63: =SUM(R63:BL63) -> 0 | N63: =if(B$4="Onsite Staffing in COGS", BF63,"") | O63: =BN63*N63 -> #N/A | P63: =L63-N63 -> 0 | R63: =if($D63="X",vlookup($B63,'Hours Spread - Filtered'!$B:$AX,R$1,false),"") | S63: =if($D63="X",vlookup($B63,'Hours Spread - Filtered'!$B:$AX,S$1,false),"") | T63: =if($D63="X",vlookup($B63,'Hours Spread - Filtered'!$B:$AX,T$1,false),"") | U63: =if($D63="X",vlookup($B63,'Hours Spread - Filtered'!$B:$AX,U$1,false),"") | V63: =if($D63="X",vlookup($B63,'Hours Spread - Filtered'!$B:$AX,V$1,false),"") | W63: =if($D63="X",vlookup($B63,'Hours Spread - Filtered'!$B:$AX,W$1,false),"") | X63: =if($D63="X",vlookup($B63,'Hours Spread - Filtered'!$B:$AX,X$1,false),"") | Y63: =if($D63="X",vlookup($B63,'Hours Spread - Filtered'!$B:$AX,Y$1,false),"") | ... BL63: =if($D63="X",vlookup($B63,'Hours Spread - Filtered'!$B:$AX,BL$1,false),"") | BM63: {=IFERROR(index('Rate Card'!U$3:AF135,match(B63,'Rate Card'!A$3:A135,0),match(Assumptions!C$11,'Rate Card'!U$2:AF$2,0)),"")} | BN63: {=(index('Rate Card'!$C$4:$T135, match(BM63,Controls!H$21:H135,0),match(Assumptions!$C$11,'Rate Card'!C$2:T$2,0)))} -> #N/A
A64: Technical | B64: Project Manager | C64: TRUE | E64: =if(D64="x","Needs Staffing","") | F64: =(L64-N64)*BN64 -> #N/A | G64: =iferror(if(C64=true,0,(L64*(BN64/1.55*1.2285))),"") -> 0 | H64: =G64 -> 0 | I64: =G64-H64 -> 0 | J64: =sumif('Job Report'!I:I,B64,'Job Report'!H:H) -> 0 | K64: =if(C64=false,H64-J64,0) -> 0 | L64: =SUM(R64:BL64) -> 0 | N64: =if(B$4="Onsite Staffing in COGS", BF64,"") | O64: =BN64*N64 -> #N/A | P64: =L64-N64 -> 0 | R64: =if($D64="X",vlookup($B64,'Hours Spread - Filtered'!$B:$AX,R$1,false),"") | S64: =if($D64="X",vlookup($B64,'Hours Spread - Filtered'!$B:$AX,S$1,false),"") | T64: =if($D64="X",vlookup($B64,'Hours Spread - Filtered'!$B:$AX,T$1,false),"") | U64: =if($D64="X",vlookup($B64,'Hours Spread - Filtered'!$B:$AX,U$1,false),"") | V64: =if($D64="X",vlookup($B64,'Hours Spread - Filtered'!$B:$AX,V$1,false),"") | W64: =if($D64="X",vlookup($B64,'Hours Spread - Filtered'!$B:$AX,W$1,false),"") | X64: =if($D64="X",vlookup($B64,'Hours Spread - Filtered'!$B:$AX,X$1,false),"") | Y64: =if($D64="X",vlookup($B64,'Hours Spread - Filtered'!$B:$AX,Y$1,false),"") | ... BL64: =if($D64="X",vlookup($B64,'Hours Spread - Filtered'!$B:$AX,BL$1,false),"") | BM64: {=IFERROR(index('Rate Card'!U$3:AF135,match(B64,'Rate Card'!A$3:A135,0),match(Assumptions!C$11,'Rate Card'!U$2:AF$2,0)),"")} | BN64: {=(index('Rate Card'!$C$4:$T135, match(BM64,Controls!H$21:H135,0),match(Assumptions!$C$11,'Rate Card'!C$2:T$2,0)))} -> #N/A
A65: Production | B65: Logistics Manager | C65: TRUE | E65: =if(D65="x","Needs Staffing","") | F65: =(L65-N65)*BN65 -> #N/A | G65: =iferror(if(C65=true,0,(L65*(BN65/1.55*1.2285))),"") -> 0 | H65: =G65 -> 0 | I65: =G65-H65 -> 0 | J65: =sumif('Job Report'!I:I,B65,'Job Report'!H:H) -> 0 | K65: =if(C65=false,H65-J65,0) -> 0 | L65: =SUM(R65:BL65) -> 0 | N65: =if(B$4="Onsite Staffing in COGS", BF65,"") | O65: =BN65*N65 -> #N/A | P65: =L65-N65 -> 0 | R65: =if($D65="X",vlookup($B65,'Hours Spread - Filtered'!$B:$AX,R$1,false),"") | S65: =if($D65="X",vlookup($B65,'Hours Spread - Filtered'!$B:$AX,S$1,false),"") | T65: =if($D65="X",vlookup($B65,'Hours Spread - Filtered'!$B:$AX,T$1,false),"") | U65: =if($D65="X",vlookup($B65,'Hours Spread - Filtered'!$B:$AX,U$1,false),"") | V65: =if($D65="X",vlookup($B65,'Hours Spread - Filtered'!$B:$AX,V$1,false),"") | W65: =if($D65="X",vlookup($B65,'Hours Spread - Filtered'!$B:$AX,W$1,false),"") | X65: =if($D65="X",vlookup($B65,'Hours Spread - Filtered'!$B:$AX,X$1,false),"") | Y65: =if($D65="X",vlookup($B65,'Hours Spread - Filtered'!$B:$AX,Y$1,false),"") | ... BL65: =if($D65="X",vlookup($B65,'Hours Spread - Filtered'!$B:$AX,BL$1,false),"") | BM65: {=IFERROR(index('Rate Card'!U$3:AF135,match(B65,'Rate Card'!A$3:A135,0),match(Assumptions!C$11,'Rate Card'!U$2:AF$2,0)),"")} | BN65: {=(index('Rate Card'!$C$4:$T135, match(BM65,Controls!H$21:H135,0),match(Assumptions!$C$11,'Rate Card'!C$2:T$2,0)))} -> #N/A
A66: Production | B66: Business Affairs | C66: TRUE | E66: =if(D66="x","Needs Staffing","") | F66: =(L66-N66)*BN66 -> #N/A | G66: =iferror(if(C66=true,0,(L66*(BN66/1.55*1.2285))),"") -> 0 | H66: =G66 -> 0 | I66: =G66-H66 -> 0 | J66: =sumif('Job Report'!I:I,B66,'Job Report'!H:H) -> 0 | K66: =if(C66=false,H66-J66,0) -> 0 | L66: =SUM(R66:BL66) -> 0 | N66: =if(B$4="Onsite Staffing in COGS", BF66,"") | O66: =BN66*N66 -> #N/A | P66: =L66-N66 -> 0 | R66: =if($D66="X",vlookup($B66,'Hours Spread - Filtered'!$B:$AX,R$1,false),"") | S66: =if($D66="X",vlookup($B66,'Hours Spread - Filtered'!$B:$AX,S$1,false),"") | T66: =if($D66="X",vlookup($B66,'Hours Spread - Filtered'!$B:$AX,T$1,false),"") | U66: =if($D66="X",vlookup($B66,'Hours Spread - Filtered'!$B:$AX,U$1,false),"") | V66: =if($D66="X",vlookup($B66,'Hours Spread - Filtered'!$B:$AX,V$1,false),"") | W66: =if($D66="X",vlookup($B66,'Hours Spread - Filtered'!$B:$AX,W$1,false),"") | X66: =if($D66="X",vlookup($B66,'Hours Spread - Filtered'!$B:$AX,X$1,false),"") | Y66: =if($D66="X",vlookup($B66,'Hours Spread - Filtered'!$B:$AX,Y$1,false),"") | ... BL66: =if($D66="X",vlookup($B66,'Hours Spread - Filtered'!$B:$AX,BL$1,false),"") | BM66: {=IFERROR(index('Rate Card'!U$3:AF135,match(B66,'Rate Card'!A$3:A135,0),match(Assumptions!C$11,'Rate Card'!U$2:AF$2,0)),"")} | BN66: {=(index('Rate Card'!$C$4:$T135, match(BM66,Controls!H$21:H135,0),match(Assumptions!$C$11,'Rate Card'!C$2:T$2,0)))} -> #N/A
A67: CONTENT | R67: =if($D67="X",vlookup($B67,'Hours Spread - Filtered'!$B:$AX,R$1,false),"") | S67: =if($D67="X",vlookup($B67,'Hours Spread - Filtered'!$B:$AX,S$1,false),"") | T67: =if($D67="X",vlookup($B67,'Hours Spread - Filtered'!$B:$AX,T$1,false),"") | U67: =if($D67="X",vlookup($B67,'Hours Spread - Filtered'!$B:$AX,U$1,false),"") | V67: =if($D67="X",vlookup($B67,'Hours Spread - Filtered'!$B:$AX,V$1,false),"") | W67: =if($D67="X",vlookup($B67,'Hours Spread - Filtered'!$B:$AX,W$1,false),"") | X67: =if($D67="X",vlookup($B67,'Hours Spread - Filtered'!$B:$AX,X$1,false),"") | Y67: =if($D67="X",vlookup($B67,'Hours Spread - Filtered'!$B:$AX,Y$1,false),"") | ... BM67: =if($D67="X",vlookup($B67,'Hours Spread - Filtered'!$B:$AX,BM$1,false),"")
A68: Content | B68: Content Producer | C68: FALSE | E68: =if(D68="x","Needs Staffing","") | F68: =(L68-N68)*BN68 -> #N/A | G68: =iferror(if(C68=true,0,(L68*(BN68/1.55*1.2285))),"") | H68: =G68 | I68: =G68-H68 -> 0 | J68: =sumif('Job Report'!I:I,B68,'Job Report'!H:H) -> 0 | K68: =if(C68=false,H68-J68,0) -> 0 | L68: =SUM(R68:BL68) -> 0 | N68: =if(B$4="Onsite Staffing in COGS", BF68,"") | O68: =BN68*N68 -> #N/A | P68: =L68-N68 -> 0 | R68: =if($D68="X",vlookup($B68,'Hours Spread - Filtered'!$B:$AX,R$1,false),"") | S68: =if($D68="X",vlookup($B68,'Hours Spread - Filtered'!$B:$AX,S$1,false),"") | T68: =if($D68="X",vlookup($B68,'Hours Spread - Filtered'!$B:$AX,T$1,false),"") | U68: =if($D68="X",vlookup($B68,'Hours Spread - Filtered'!$B:$AX,U$1,false),"") | V68: =if($D68="X",vlookup($B68,'Hours Spread - Filtered'!$B:$AX,V$1,false),"") | W68: =if($D68="X",vlookup($B68,'Hours Spread - Filtered'!$B:$AX,W$1,false),"") | X68: =if($D68="X",vlookup($B68,'Hours Spread - Filtered'!$B:$AX,X$1,false),"") | Y68: =if($D68="X",vlookup($B68,'Hours Spread - Filtered'!$B:$AX,Y$1,false),"") | ... BL68: =if($D68="X",vlookup($B68,'Hours Spread - Filtered'!$B:$AX,BL$1,false),"") | BM68: {=IFERROR(index('Rate Card'!U$3:AF135,match(B68,'Rate Card'!A$3:A135,0),match(Assumptions!C$11,'Rate Card'!U$2:AF$2,0)),"")} | BN68: {=(index('Rate Card'!$C$4:$T135, match(BM68,Controls!H$21:H135,0),match(Assumptions!$C$11,'Rate Card'!C$2:T$2,0)))} -> #N/A
A69: Content | B69: Creative Technologist | C69: FALSE | E69: =if(D69="x","Needs Staffing","") | F69: =(L69-N69)*BN69 -> #N/A | G69: =iferror(if(C69=true,0,(L69*(BN69/1.55*1.2285))),"") | H69: =G69 | I69: =G69-H69 -> 0 | J69: =sumif('Job Report'!I:I,B69,'Job Report'!H:H) -> 0 | K69: =if(C69=false,H69-J69,0) -> 0 | L69: =SUM(R69:BL69) -> 0 | N69: =if(B$4="Onsite Staffing in COGS", BF69,"") | O69: =BN69*N69 -> #N/A | P69: =L69-N69 -> 0 | R69: =if($D69="X",vlookup($B69,'Hours Spread - Filtered'!$B:$AX,R$1,false),"") | S69: =if($D69="X",vlookup($B69,'Hours Spread - Filtered'!$B:$AX,S$1,false),"") | T69: =if($D69="X",vlookup($B69,'Hours Spread - Filtered'!$B:$AX,T$1,false),"") | U69: =if($D69="X",vlookup($B69,'Hours Spread - Filtered'!$B:$AX,U$1,false),"") | V69: =if($D69="X",vlookup($B69,'Hours Spread - Filtered'!$B:$AX,V$1,false),"") | W69: =if($D69="X",vlookup($B69,'Hours Spread - Filtered'!$B:$AX,W$1,false),"") | X69: =if($D69="X",vlookup($B69,'Hours Spread - Filtered'!$B:$AX,X$1,false),"") | Y69: =if($D69="X",vlookup($B69,'Hours Spread - Filtered'!$B:$AX,Y$1,false),"") | ... BL69: =if($D69="X",vlookup($B69,'Hours Spread - Filtered'!$B:$AX,BL$1,false),"") | BM69: {=IFERROR(index('Rate Card'!U$3:AF135,match(B69,'Rate Card'!A$3:A135,0),match(Assumptions!C$11,'Rate Card'!U$2:AF$2,0)),"")} | BN69: {=(index('Rate Card'!$C$4:$T135, match(BM69,Controls!H$21:H135,0),match(Assumptions!$C$11,'Rate Card'!C$2:T$2,0)))} -> #N/A
A70: Content | B70: Digital Platform Director | C70: FALSE | E70: =if(D70="x","Needs Staffing","") | F70: =(L70-N70)*BN70 -> #N/A | G70: =iferror(if(C70=true,0,(L70*(BN70/1.55*1.2285))),"") | H70: =G70 | I70: =G70-H70 -> 0 | J70: =sumif('Job Report'!I:I,B70,'Job Report'!H:H) -> 0 | K70: =if(C70=false,H70-J70,0) -> 0 | L70: =SUM(R70:BL70) -> 0 | N70: =if(B$4="Onsite Staffing in COGS", BF70,"") | O70: =BN70*N70 -> #N/A | P70: =L70-N70 -> 0 | R70: =if($D70="X",vlookup($B70,'Hours Spread - Filtered'!$B:$AX,R$1,false),"") | S70: =if($D70="X",vlookup($B70,'Hours Spread - Filtered'!$B:$AX,S$1,false),"") | T70: =if($D70="X",vlookup($B70,'Hours Spread - Filtered'!$B:$AX,T$1,false),"") | U70: =if($D70="X",vlookup($B70,'Hours Spread - Filtered'!$B:$AX,U$1,false),"") | V70: =if($D70="X",vlookup($B70,'Hours Spread - Filtered'!$B:$AX,V$1,false),"") | W70: =if($D70="X",vlookup($B70,'Hours Spread - Filtered'!$B:$AX,W$1,false),"") | X70: =if($D70="X",vlookup($B70,'Hours Spread - Filtered'!$B:$AX,X$1,false),"") | Y70: =if($D70="X",vlookup($B70,'Hours Spread - Filtered'!$B:$AX,Y$1,false),"") | ... BL70: =if($D70="X",vlookup($B70,'Hours Spread - Filtered'!$B:$AX,BL$1,false),"") | BM70: {=IFERROR(index('Rate Card'!U$3:AF135,match(B70,'Rate Card'!A$3:A135,0),match(Assumptions!C$11,'Rate Card'!U$2:AF$2,0)),"")} | BN70: {=(index('Rate Card'!$C$4:$T135, match(BM70,Controls!H$21:H135,0),match(Assumptions!$C$11,'Rate Card'!C$2:T$2,0)))} -> #N/A
A71: Content | B71: Full Stack Developer | C71: FALSE | E71: =if(D71="x","Needs Staffing","") | F71: =(L71-N71)*BN71 -> #N/A | G71: =iferror(if(C71=true,0,(L71*(BN71/1.55*1.2285))),"") | H71: =G71 | I71: =G71-H71 -> 0 | J71: =sumif('Job Report'!I:I,B71,'Job Report'!H:H) -> 0 | K71: =if(C71=false,H71-J71,0) -> 0 | L71: =SUM(R71:BL71) -> 0 | N71: =if(B$4="Onsite Staffing in COGS", BF71,"") | O71: =BN71*N71 -> #N/A | P71: =L71-N71 -> 0 | R71: =if($D71="X",vlookup($B71,'Hours Spread - Filtered'!$B:$AX,R$1,false),"") | S71: =if($D71="X",vlookup($B71,'Hours Spread - Filtered'!$B:$AX,S$1,false),"") | T71: =if($D71="X",vlookup($B71,'Hours Spread - Filtered'!$B:$AX,T$1,false),"") | U71: =if($D71="X",vlookup($B71,'Hours Spread - Filtered'!$B:$AX,U$1,false),"") | V71: =if($D71="X",vlookup($B71,'Hours Spread - Filtered'!$B:$AX,V$1,false),"") | W71: =if($D71="X",vlookup($B71,'Hours Spread - Filtered'!$B:$AX,W$1,false),"") | X71: =if($D71="X",vlookup($B71,'Hours Spread - Filtered'!$B:$AX,X$1,false),"") | Y71: =if($D71="X",vlookup($B71,'Hours Spread - Filtered'!$B:$AX,Y$1,false),"") | ... BL71: =if($D71="X",vlookup($B71,'Hours Spread - Filtered'!$B:$AX,BL$1,false),"") | BM71: {=IFERROR(index('Rate Card'!U$3:AF135,match(B71,'Rate Card'!A$3:A135,0),match(Assumptions!C$11,'Rate Card'!U$2:AF$2,0)),"")} | BN71: {=(index('Rate Card'!$C$4:$T135, match(BM71,Controls!H$21:H135,0),match(Assumptions!$C$11,'Rate Card'!C$2:T$2,0)))} -> #N/A
A72: Content | B72: UI / UX Designer | C72: TRUE | E72: =if(D72="x","Needs Staffing","") | F72: =(L72-N72)*BN72 -> #N/A | G72: =iferror(if(C72=true,0,(L72*(BN72/1.55*1.2285))),"") -> 0 | H72: =G72 -> 0 | I72: =G72-H72 -> 0 | J72: =sumif('Job Report'!I:I,B72,'Job Report'!H:H) -> 0 | K72: =if(C72=false,H72-J72,0) -> 0 | L72: =SUM(R72:BL72) -> 0 | N72: =if(B$4="Onsite Staffing in COGS", BF72,"") | O72: =BN72*N72 -> #N/A | P72: =L72-N72 -> 0 | R72: =if($D72="X",vlookup($B72,'Hours Spread - Filtered'!$B:$AX,R$1,false),"") | S72: =if($D72="X",vlookup($B72,'Hours Spread - Filtered'!$B:$AX,S$1,false),"") | T72: =if($D72="X",vlookup($B72,'Hours Spread - Filtered'!$B:$AX,T$1,false),"") | U72: =if($D72="X",vlookup($B72,'Hours Spread - Filtered'!$B:$AX,U$1,false),"") | V72: =if($D72="X",vlookup($B72,'Hours Spread - Filtered'!$B:$AX,V$1,false),"") | W72: =if($D72="X",vlookup($B72,'Hours Spread - Filtered'!$B:$AX,W$1,false),"") | X72: =if($D72="X",vlookup($B72,'Hours Spread - Filtered'!$B:$AX,X$1,false),"") | Y72: =if($D72="X",vlookup($B72,'Hours Spread - Filtered'!$B:$AX,Y$1,false),"") | ... BL72: =if($D72="X",vlookup($B72,'Hours Spread - Filtered'!$B:$AX,BL$1,false),"") | BM72: {=IFERROR(index('Rate Card'!U$3:AF135,match(B72,'Rate Card'!A$3:A135,0),match(Assumptions!C$11,'Rate Card'!U$2:AF$2,0)),"")} | BN72: {=(index('Rate Card'!$C$4:$T135, match(BM72,Controls!H$21:H135,0),match(Assumptions!$C$11,'Rate Card'!C$2:T$2,0)))} -> #N/A
A73: Content | B73: Interactive Producer | C73: FALSE | E73: =if(D73="x","Needs Staffing","") | F73: =(L73-N73)*BN73 -> #N/A | G73: =iferror(if(C73=true,0,(L73*(BN73/1.55*1.2285))),"") | H73: =G73 | I73: =G73-H73 -> 0 | J73: =sumif('Job Report'!I:I,B73,'Job Report'!H:H) -> 0 | K73: =if(C73=false,H73-J73,0) -> 0 | L73: =SUM(R73:BL73) -> 0 | N73: =if(B$4="Onsite Staffing in COGS", BF73,"") | O73: =BN73*N73 -> #N/A | P73: =L73-N73 -> 0 | R73: =if($D73="X",vlookup($B73,'Hours Spread - Filtered'!$B:$AX,R$1,false),"") | S73: =if($D73="X",vlookup($B73,'Hours Spread - Filtered'!$B:$AX,S$1,false),"") | T73: =if($D73="X",vlookup($B73,'Hours Spread - Filtered'!$B:$AX,T$1,false),"") | U73: =if($D73="X",vlookup($B73,'Hours Spread - Filtered'!$B:$AX,U$1,false),"") | V73: =if($D73="X",vlookup($B73,'Hours Spread - Filtered'!$B:$AX,V$1,false),"") | W73: =if($D73="X",vlookup($B73,'Hours Spread - Filtered'!$B:$AX,W$1,false),"") | X73: =if($D73="X",vlookup($B73,'Hours Spread - Filtered'!$B:$AX,X$1,false),"") | Y73: =if($D73="X",vlookup($B73,'Hours Spread - Filtered'!$B:$AX,Y$1,false),"") | ... BL73: =if($D73="X",vlookup($B73,'Hours Spread - Filtered'!$B:$AX,BL$1,false),"") | BM73: {=IFERROR(index('Rate Card'!U$3:AF135,match(B73,'Rate Card'!A$3:A135,0),match(Assumptions!C$11,'Rate Card'!U$2:AF$2,0)),"")} | BN73: {=(index('Rate Card'!$C$4:$T135, match(BM73,Controls!H$21:H135,0),match(Assumptions!$C$11,'Rate Card'!C$2:T$2,0)))} -> #N/A
A74: Content | B74: Graphic Designer, Content | C74: TRUE | E74: =if(D74="x","Needs Staffing","") | F74: =(L74-N74)*BN74 -> #N/A | G74: =iferror(if(C74=true,0,(L74*(BN74/1.55*1.2285))),"") -> 0 | H74: =G74 -> 0 | I74: =G74-H74 -> 0 | J74: =sumif('Job Report'!I:I,B74,'Job Report'!H:H) -> 0 | K74: =if(C74=false,H74-J74,0) -> 0 | L74: =SUM(R74:BL74) -> 0 | N74: =if(B$4="Onsite Staffing in COGS", BF74,"") | O74: =BN74*N74 -> #N/A | P74: =L74-N74 -> 0 | R74: =if($D74="X",vlookup($B74,'Hours Spread - Filtered'!$B:$AX,R$1,false),"") | S74: =if($D74="X",vlookup($B74,'Hours Spread - Filtered'!$B:$AX,S$1,false),"") | T74: =if($D74="X",vlookup($B74,'Hours Spread - Filtered'!$B:$AX,T$1,false),"") | U74: =if($D74="X",vlookup($B74,'Hours Spread - Filtered'!$B:$AX,U$1,false),"") | V74: =if($D74="X",vlookup($B74,'Hours Spread - Filtered'!$B:$AX,V$1,false),"") | W74: =if($D74="X",vlookup($B74,'Hours Spread - Filtered'!$B:$AX,W$1,false),"") | X74: =if($D74="X",vlookup($B74,'Hours Spread - Filtered'!$B:$AX,X$1,false),"") | Y74: =if($D74="X",vlookup($B74,'Hours Spread - Filtered'!$B:$AX,Y$1,false),"") | ... BL74: =if($D74="X",vlookup($B74,'Hours Spread - Filtered'!$B:$AX,BL$1,false),"") | BM74: {=IFERROR(index('Rate Card'!U$3:AF135,match(B74,'Rate Card'!A$3:A135,0),match(Assumptions!C$11,'Rate Card'!U$2:AF$2,0)),"")} | BN74: {=(index('Rate Card'!$C$4:$T135, match(BM74,Controls!H$21:H135,0),match(Assumptions!$C$11,'Rate Card'!C$2:T$2,0)))} -> #N/A
A75: Content | B75: Presentation Designer, Content | C75: TRUE | E75: =if(D75="x","Needs Staffing","") | F75: =(L75-N75)*BN75 -> #N/A | G75: =iferror(if(C75=true,0,(L75*(BN75/1.55*1.2285))),"") -> 0 | H75: =G75 -> 0 | I75: =G75-H75 -> 0 | J75: =sumif('Job Report'!I:I,B75,'Job Report'!H:H) -> 0 | K75: =if(C75=false,H75-J75,0) -> 0 | L75: =SUM(R75:BL75) -> 0 | N75: =if(B$4="Onsite Staffing in COGS", BF75,"") | O75: =BN75*N75 -> #N/A | P75: =L75-N75 -> 0 | R75: =if($D75="X",vlookup($B75,'Hours Spread - Filtered'!$B:$AX,R$1,false),"") | S75: =if($D75="X",vlookup($B75,'Hours Spread - Filtered'!$B:$AX,S$1,false),"") | T75: =if($D75="X",vlookup($B75,'Hours Spread - Filtered'!$B:$AX,T$1,false),"") | U75: =if($D75="X",vlookup($B75,'Hours Spread - Filtered'!$B:$AX,U$1,false),"") | V75: =if($D75="X",vlookup($B75,'Hours Spread - Filtered'!$B:$AX,V$1,false),"") | W75: =if($D75="X",vlookup($B75,'Hours Spread - Filtered'!$B:$AX,W$1,false),"") | X75: =if($D75="X",vlookup($B75,'Hours Spread - Filtered'!$B:$AX,X$1,false),"") | Y75: =if($D75="X",vlookup($B75,'Hours Spread - Filtered'!$B:$AX,Y$1,false),"") | ... BL75: =if($D75="X",vlookup($B75,'Hours Spread - Filtered'!$B:$AX,BL$1,false),"") | BM75: {=IFERROR(index('Rate Card'!U$3:AF135,match(B75,'Rate Card'!A$3:A135,0),match(Assumptions!C$11,'Rate Card'!U$2:AF$2,0)),"")} | BN75: {=(index('Rate Card'!$C$4:$T135, match(BM75,Controls!H$21:H135,0),match(Assumptions!$C$11,'Rate Card'!C$2:T$2,0)))} -> #N/A
A76: Content | B76: Motion Designer, Content | C76: TRUE | E76: =if(D76="x","Needs Staffing","") | F76: =(L76-N76)*BN76 -> #N/A | G76: =iferror(if(C76=true,0,(L76*(BN76/1.55*1.2285))),"") -> 0 | H76: =G76 -> 0 | I76: =G76-H76 -> 0 | J76: =sumif('Job Report'!I:I,B76,'Job Report'!H:H) -> 0 | K76: =if(C76=false,H76-J76,0) -> 0 | L76: =SUM(R76:BL76) -> 0 | N76: =if(B$4="Onsite Staffing in COGS", BF76,"") | O76: =BN76*N76 -> #N/A | P76: =L76-N76 -> 0 | R76: =if($D76="X",vlookup($B76,'Hours Spread - Filtered'!$B:$AX,R$1,false),"") | S76: =if($D76="X",vlookup($B76,'Hours Spread - Filtered'!$B:$AX,S$1,false),"") | T76: =if($D76="X",vlookup($B76,'Hours Spread - Filtered'!$B:$AX,T$1,false),"") | U76: =if($D76="X",vlookup($B76,'Hours Spread - Filtered'!$B:$AX,U$1,false),"") | V76: =if($D76="X",vlookup($B76,'Hours Spread - Filtered'!$B:$AX,V$1,false),"") | W76: =if($D76="X",vlookup($B76,'Hours Spread - Filtered'!$B:$AX,W$1,false),"") | X76: =if($D76="X",vlookup($B76,'Hours Spread - Filtered'!$B:$AX,X$1,false),"") | Y76: =if($D76="X",vlookup($B76,'Hours Spread - Filtered'!$B:$AX,Y$1,false),"") | ... BL76: =if($D76="X",vlookup($B76,'Hours Spread - Filtered'!$B:$AX,BL$1,false),"") | BM76: {=IFERROR(index('Rate Card'!U$3:AF135,match(B76,'Rate Card'!A$3:A135,0),match(Assumptions!C$11,'Rate Card'!U$2:AF$2,0)),"")} | BN76: {=(index('Rate Card'!$C$4:$T135, match(BM76,Controls!H$21:H135,0),match(Assumptions!$C$11,'Rate Card'!C$2:T$2,0)))} -> #N/A
A77: Content | B77: Copy Writer | C77: FALSE | E77: =if(D77="x","Needs Staffing","") | F77: =(L77-N77)*BN77 -> #N/A | G77: =iferror(if(C77=true,0,(L77*(BN77/1.55*1.2285))),"") | H77: =G77 | I77: =G77-H77 -> 0 | J77: =sumif('Job Report'!I:I,B77,'Job Report'!H:H) -> 0 | K77: =if(C77=false,H77-J77,0) -> 0 | L77: =SUM(R77:BL77) -> 0 | N77: =if(B$4="Onsite Staffing in COGS", BF77,"") | O77: =BN77*N77 -> #N/A | P77: =L77-N77 -> 0 | R77: =if($D77="X",vlookup($B77,'Hours Spread - Filtered'!$B:$AX,R$1,false),"") | S77: =if($D77="X",vlookup($B77,'Hours Spread - Filtered'!$B:$AX,S$1,false),"") | T77: =if($D77="X",vlookup($B77,'Hours Spread - Filtered'!$B:$AX,T$1,false),"") | U77: =if($D77="X",vlookup($B77,'Hours Spread - Filtered'!$B:$AX,U$1,false),"") | V77: =if($D77="X",vlookup($B77,'Hours Spread - Filtered'!$B:$AX,V$1,false),"") | W77: =if($D77="X",vlookup($B77,'Hours Spread - Filtered'!$B:$AX,W$1,false),"") | X77: =if($D77="X",vlookup($B77,'Hours Spread - Filtered'!$B:$AX,X$1,false),"") | Y77: =if($D77="X",vlookup($B77,'Hours Spread - Filtered'!$B:$AX,Y$1,false),"") | ... BL77: =if($D77="X",vlookup($B77,'Hours Spread - Filtered'!$B:$AX,BL$1,false),"") | BM77: {=IFERROR(index('Rate Card'!U$3:AF135,match(B77,'Rate Card'!A$3:A135,0),match(Assumptions!C$11,'Rate Card'!U$2:AF$2,0)),"")} | BN77: {=(index('Rate Card'!$C$4:$T135, match(BM77,Controls!H$21:H135,0),match(Assumptions!$C$11,'Rate Card'!C$2:T$2,0)))} -> #N/A
A79: ADDITIONAL STAFFING
B80: Placeholder 1 | C80: TRUE | E80: =if(D80="x","Needs Staffing","") | F80: =(L80-N80)*BN80 -> 0 | G80: =iferror(if(C80=true,0,(L80*(BN80/1.55*1.2285))),"") -> 0 | H80: =G80 -> 0 | I80: =G80-H80 -> 0 | J80: =sumif('Job Report'!I:I,B80,'Job Report'!H:H) -> 0 | K80: =if(C80=false,H80-J80,0) -> 0 | L80: =SUM(R80:BL80) -> 0 | N80: =if(B$4="Onsite Staffing in COGS", BF80,"") | O80: =BN80*N80 -> 0 | P80: =L80-N80 -> 0 | BM80: {=IFERROR(index('Rate Card'!U$3:AF135,match(B80,'Rate Card'!A$3:A135,0),match(Assumptions!C$11,'Rate Card'!U$2:AF$2,0)),"")} | BN80: {=IFERROR(index('Rate Card'!$C$4:$T135, match(BM80,Controls!G$21:G135,0),match(Assumptions!$C$11,'Rate Card'!C$2:T$2,0)),"")}
B81: Placeholder 2 | C81: TRUE | E81: =if(D81="x","Needs Staffing","") | F81: =(L81-N81)*BN81 -> 0 | G81: =iferror(if(C81=true,0,(L81*(BN81/1.55*1.2285))),"") -> 0 | H81: =G81 -> 0 | I81: =G81-H81 -> 0 | J81: =sumif('Job Report'!I:I,B81,'Job Report'!H:H) -> 0 | K81: =if(C81=false,H81-J81,0) -> 0 | L81: =SUM(R81:BL81) -> 0 | N81: =if(B$4="Onsite Staffing in COGS", BF81,"") | O81: =BN81*N81 -> 0 | P81: =L81-N81 -> 0 | BM81: {=IFERROR(index('Rate Card'!U$3:AF135,match(B81,'Rate Card'!A$3:A135,0),match(Assumptions!C$11,'Rate Card'!U$2:AF$2,0)),"")} | BN81: {=IFERROR(index('Rate Card'!$C$4:$T135, match(BM81,Controls!G$21:G135,0),match(Assumptions!$C$11,'Rate Card'!C$2:T$2,0)),"")}
B82: Placeholder 3 | C82: TRUE | E82: =if(D82="x","Needs Staffing","") | F82: =(L82-N82)*BN82 -> 0 | G82: =iferror(if(C82=true,0,(L82*(BN82/1.55*1.2285))),"") -> 0 | H82: =G82 -> 0 | I82: =G82-H82 -> 0 | J82: =sumif('Job Report'!I:I,B82,'Job Report'!H:H) -> 0 | K82: =if(C82=false,H82-J82,0) -> 0 | L82: =SUM(R82:BL82) -> 0 | N82: =if(B$4="Onsite Staffing in COGS", BF82,"") | O82: =BN82*N82 -> 0 | P82: =L82-N82 -> 0 | BM82: {=IFERROR(index('Rate Card'!U$3:AF135,match(B82,'Rate Card'!A$3:A135,0),match(Assumptions!C$11,'Rate Card'!U$2:AF$2,0)),"")} | BN82: {=IFERROR(index('Rate Card'!$C$4:$T135, match(BM82,Controls!G$21:G135,0),match(Assumptions!$C$11,'Rate Card'!C$2:T$2,0)),"")}
B83: Placeholder 4 | C83: TRUE | E83: =if(D83="x","Needs Staffing","") | F83: =(L83-N83)*BN83 -> 0 | G83: =iferror(if(C83=true,0,(L83*(BN83/1.55*1.2285))),"") -> 0 | H83: =G83 -> 0 | I83: =G83-H83 -> 0 | J83: =sumif('Job Report'!I:I,B83,'Job Report'!H:H) -> 0 | K83: =if(C83=false,H83-J83,0) -> 0 | L83: =SUM(R83:BL83) -> 0 | N83: =if(B$4="Onsite Staffing in COGS", BF83,"") | O83: =BN83*N83 -> 0 | P83: =L83-N83 -> 0 | BM83: {=IFERROR(index('Rate Card'!U$3:AF135,match(B83,'Rate Card'!A$3:A135,0),match(Assumptions!C$11,'Rate Card'!U$2:AF$2,0)),"")} | BN83: {=IFERROR(index('Rate Card'!$C$4:$T135, match(BM83,Controls!G$21:G135,0),match(Assumptions!$C$11,'Rate Card'!C$2:T$2,0)),"")}
B84: Placeholder 5 | C84: TRUE | E84: =if(D84="x","Needs Staffing","") | F84: =(L84-N84)*BN84 -> 0 | G84: =iferror(if(C84=true,0,(L84*(BN84/1.55*1.2285))),"") -> 0 | H84: =G84 -> 0 | I84: =G84-H84 -> 0 | J84: =sumif('Job Report'!I:I,B84,'Job Report'!H:H) -> 0 | K84: =if(C84=false,H84-J84,0) -> 0 | L84: =SUM(R84:BL84) -> 0 | N84: =if(B$4="Onsite Staffing in COGS", BF84,"") | O84: =BN84*N84 -> 0 | P84: =L84-N84 -> 0 | BM84: {=IFERROR(index('Rate Card'!U$3:AF135,match(B84,'Rate Card'!A$3:A135,0),match(Assumptions!C$11,'Rate Card'!U$2:AF$2,0)),"")} | BN84: {=IFERROR(index('Rate Card'!$C$4:$T135, match(BM84,Controls!G$21:G135,0),match(Assumptions!$C$11,'Rate Card'!C$2:T$2,0)),"")}
B85: Placeholder 6 | C85: TRUE | E85: =if(D85="x","Needs Staffing","") | F85: =(L85-N85)*BN85 -> 0 | G85: =iferror(if(C85=true,0,(L85*(BN85/1.55*1.2285))),"") -> 0 | H85: =G85 -> 0 | I85: =G85-H85 -> 0 | J85: =sumif('Job Report'!I:I,B85,'Job Report'!H:H) -> 0 | K85: =if(C85=false,H85-J85,0) -> 0 | L85: =SUM(R85:BL85) -> 0 | N85: =if(B$4="Onsite Staffing in COGS", BF85,"") | O85: =BN85*N85 -> 0 | P85: =L85-N85 -> 0 | BM85: {=IFERROR(index('Rate Card'!U$3:AF135,match(B85,'Rate Card'!A$3:A135,0),match(Assumptions!C$11,'Rate Card'!U$2:AF$2,0)),"")} | BN85: {=IFERROR(index('Rate Card'!$C$4:$T135, match(BM85,Controls!G$21:G135,0),match(Assumptions!$C$11,'Rate Card'!C$2:T$2,0)),"")}
B86: Placeholder 7 | C86: TRUE | E86: =if(D86="x","Needs Staffing","") | F86: =(L86-N86)*BN86 -> 0 | G86: =iferror(if(C86=true,0,(L86*(BN86/1.55*1.2285))),"") -> 0 | H86: =G86 -> 0 | I86: =G86-H86 -> 0 | J86: =sumif('Job Report'!I:I,B86,'Job Report'!H:H) -> 0 | K86: =if(C86=false,H86-J86,0) -> 0 | L86: =SUM(R86:BL86) -> 0 | N86: =if(B$4="Onsite Staffing in COGS", BF86,"") | O86: =BN86*N86 -> 0 | P86: =L86-N86 -> 0 | BM86: {=IFERROR(index('Rate Card'!U$3:AF135,match(B86,'Rate Card'!A$3:A135,0),match(Assumptions!C$11,'Rate Card'!U$2:AF$2,0)),"")} | BN86: {=IFERROR(index('Rate Card'!$C$4:$T135, match(BM86,Controls!G$21:G135,0),match(Assumptions!$C$11,'Rate Card'!C$2:T$2,0)),"")}
B87: Placeholder 8 | C87: TRUE | E87: =if(D87="x","Needs Staffing","") | F87: =(L87-N87)*BN87 -> 0 | G87: =iferror(if(C87=true,0,(L87*(BN87/1.55*1.2285))),"") -> 0 | H87: =G87 -> 0 | I87: =G87-H87 -> 0 | J87: =sumif('Job Report'!I:I,B87,'Job Report'!H:H) -> 0 | K87: =if(C87=false,H87-J87,0) -> 0 | L87: =SUM(R87:BL87) -> 0 | N87: =if(B$4="Onsite Staffing in COGS", BF87,"") | O87: =BN87*N87 -> 0 | P87: =L87-N87 -> 0 | BM87: {=IFERROR(index('Rate Card'!U$3:AF135,match(B87,'Rate Card'!A$3:A135,0),match(Assumptions!C$11,'Rate Card'!U$2:AF$2,0)),"")} | BN87: {=IFERROR(index('Rate Card'!$C$4:$T135, match(BM87,Controls!G$21:G135,0),match(Assumptions!$C$11,'Rate Card'!C$2:T$2,0)),"")}
B88: Placeholder 9 | C88: TRUE | E88: =if(D88="x","Needs Staffing","") | F88: =(L88-N88)*BN88 -> 0 | G88: =iferror(if(C88=true,0,(L88*(BN88/1.55*1.2285))),"") -> 0 | H88: =G88 -> 0 | I88: =G88-H88 -> 0 | J88: =sumif('Job Report'!I:I,B88,'Job Report'!H:H) -> 0 | K88: =if(C88=false,H88-J88,0) -> 0 | L88: =SUM(R88:BL88) -> 0 | N88: =if(B$4="Onsite Staffing in COGS", BF88,"") | O88: =BN88*N88 -> 0 | P88: =L88-N88 -> 0 | BM88: {=IFERROR(index('Rate Card'!U$3:AF135,match(B88,'Rate Card'!A$3:A135,0),match(Assumptions!C$11,'Rate Card'!U$2:AF$2,0)),"")} | BN88: {=IFERROR(index('Rate Card'!$C$4:$T135, match(BM88,Controls!G$21:G135,0),match(Assumptions!$C$11,'Rate Card'!C$2:T$2,0)),"")}
B89: Placeholder 10 | C89: TRUE | E89: =if(D89="x","Needs Staffing","") | F89: =(L89-N89)*BN89 -> 0 | G89: =iferror(if(C89=true,0,(L89*(BN89/1.55*1.2285))),"") -> 0 | H89: =G89 -> 0 | I89: =G89-H89 -> 0 | J89: =sumif('Job Report'!I:I,B89,'Job Report'!H:H) -> 0 | K89: =if(C89=false,H89-J89,0) -> 0 | L89: =SUM(R89:BL89) -> 0 | N89: =if(B$4="Onsite Staffing in COGS", BF89,"") | O89: =BN89*N89 -> 0 | P89: =L89-N89 -> 0 | BM89: {=IFERROR(index('Rate Card'!U$3:AF135,match(B89,'Rate Card'!A$3:A135,0),match(Assumptions!C$11,'Rate Card'!U$2:AF$2,0)),"")} | BN89: {=IFERROR(index('Rate Card'!$C$4:$T135, match(BM89,Controls!G$21:G135,0),match(Assumptions!$C$11,'Rate Card'!C$2:T$2,0)),"")}
B90: Placeholder 11 | C90: TRUE | E90: =if(D90="x","Needs Staffing","") | F90: =(L90-N90)*BN90 -> 0 | G90: =iferror(if(C90=true,0,(L90*(BN90/1.55*1.2285))),"") -> 0 | H90: =G90 -> 0 | I90: =G90-H90 -> 0 | J90: =sumif('Job Report'!I:I,B90,'Job Report'!H:H) -> 0 | K90: =if(C90=false,H90-J90,0) -> 0 | L90: =SUM(R90:BL90) -> 0 | N90: =if(B$4="Onsite Staffing in COGS", BF90,"") | O90: =BN90*N90 -> 0 | P90: =L90-N90 -> 0 | BM90: {=IFERROR(index('Rate Card'!U$3:AF135,match(B90,'Rate Card'!A$3:A135,0),match(Assumptions!C$11,'Rate Card'!U$2:AF$2,0)),"")} | BN90: {=IFERROR(index('Rate Card'!$C$4:$T135, match(BM90,Controls!G$21:G135,0),match(Assumptions!$C$11,'Rate Card'!C$2:T$2,0)),"")}
B91: Placeholder 12 | C91: TRUE | E91: =if(D91="x","Needs Staffing","") | F91: =(L91-N91)*BN91 -> 0 | G91: =iferror(if(C91=true,0,(L91*(BN91/1.55*1.2285))),"") -> 0 | H91: =G91 -> 0 | I91: =G91-H91 -> 0 | J91: =sumif('Job Report'!I:I,B91,'Job Report'!H:H) -> 0 | K91: =if(C91=false,H91-J91,0) -> 0 | L91: =SUM(R91:BL91) -> 0 | N91: =if(B$4="Onsite Staffing in COGS", BF91,"") | O91: =BN91*N91 -> 0 | P91: =L91-N91 -> 0 | BM91: {=IFERROR(index('Rate Card'!U$3:AF135,match(B91,'Rate Card'!A$3:A135,0),match(Assumptions!C$11,'Rate Card'!U$2:AF$2,0)),"")} | BN91: {=IFERROR(index('Rate Card'!$C$4:$T135, match(BM91,Controls!G$21:G135,0),match(Assumptions!$C$11,'Rate Card'!C$2:T$2,0)),"")}
B92: Placeholder 13 | C92: TRUE | E92: =if(D92="x","Needs Staffing","") | F92: =(L92-N92)*BN92 -> 0 | G92: =iferror(if(C92=true,0,(L92*(BN92/1.55*1.2285))),"") -> 0 | H92: =G92 -> 0 | I92: =G92-H92 -> 0 | J92: =sumif('Job Report'!I:I,B92,'Job Report'!H:H) -> 0 | K92: =if(C92=false,H92-J92,0) -> 0 | L92: =SUM(R92:BL92) -> 0 | N92: =if(B$4="Onsite Staffing in COGS", BF92,"") | O92: =BN92*N92 -> 0 | P92: =L92-N92 -> 0 | BM92: {=IFERROR(index('Rate Card'!U$3:AF135,match(B92,'Rate Card'!A$3:A135,0),match(Assumptions!C$11,'Rate Card'!U$2:AF$2,0)),"")} | BN92: {=IFERROR(index('Rate Card'!$C$4:$T135, match(BM92,Controls!G$21:G135,0),match(Assumptions!$C$11,'Rate Card'!C$2:T$2,0)),"")}
B93: Placeholder 14 | C93: TRUE | E93: =if(D93="x","Needs Staffing","") | F93: =(L93-N93)*BN93 -> 0 | G93: =iferror(if(C93=true,0,(L93*(BN93/1.55*1.2285))),"") -> 0 | H93: =G93 -> 0 | I93: =G93-H93 -> 0 | J93: =sumif('Job Report'!I:I,B93,'Job Report'!H:H) -> 0 | K93: =if(C93=false,H93-J93,0) -> 0 | L93: =SUM(R93:BL93) -> 0 | N93: =if(B$4="Onsite Staffing in COGS", BF93,"") | O93: =BN93*N93 -> 0 | P93: =L93-N93 -> 0 | BM93: {=IFERROR(index('Rate Card'!U$3:AF135,match(B93,'Rate Card'!A$3:A135,0),match(Assumptions!C$11,'Rate Card'!U$2:AF$2,0)),"")} | BN93: {=IFERROR(index('Rate Card'!$C$4:$T135, match(BM93,Controls!G$21:G135,0),match(Assumptions!$C$11,'Rate Card'!C$2:T$2,0)),"")}
B94: Placeholder 15 | C94: TRUE | E94: =if(D94="x","Needs Staffing","") | F94: =(L94-N94)*BN94 -> 0 | G94: =iferror(if(C94=true,0,(L94*(BN94/1.55*1.2285))),"") -> 0 | H94: =G94 -> 0 | I94: =G94-H94 -> 0 | J94: =sumif('Job Report'!I:I,B94,'Job Report'!H:H) -> 0 | K94: =if(C94=false,H94-J94,0) -> 0 | L94: =SUM(R94:BL94) -> 0 | N94: =if(B$4="Onsite Staffing in COGS", BF94,"") | O94: =BN94*N94 -> 0 | P94: =L94-N94 -> 0 | BM94: {=IFERROR(index('Rate Card'!U$3:AF135,match(B94,'Rate Card'!A$3:A135,0),match(Assumptions!C$11,'Rate Card'!U$2:AF$2,0)),"")} | BN94: {=IFERROR(index('Rate Card'!$C$4:$T135, match(BM94,Controls!G$21:G135,0),match(Assumptions!$C$11,'Rate Card'!C$2:T$2,0)),"")}
B95: Placeholder 16 | C95: TRUE | E95: =if(D95="x","Needs Staffing","") | F95: =(L95-N95)*BN95 -> 0 | G95: =iferror(if(C95=true,0,(L95*(BN95/1.55*1.2285))),"") -> 0 | H95: =G95 -> 0 | I95: =G95-H95 -> 0 | J95: =sumif('Job Report'!I:I,B95,'Job Report'!H:H) -> 0 | K95: =if(C95=false,H95-J95,0) -> 0 | L95: =SUM(R95:BL95) -> 0 | N95: =if(B$4="Onsite Staffing in COGS", BF95,"") | O95: =BN95*N95 -> 0 | P95: =L95-N95 -> 0 | BM95: {=IFERROR(index('Rate Card'!U$3:AF135,match(B95,'Rate Card'!A$3:A135,0),match(Assumptions!C$11,'Rate Card'!U$2:AF$2,0)),"")} | BN95: {=IFERROR(index('Rate Card'!$C$4:$T135, match(BM95,Controls!G$21:G135,0),match(Assumptions!$C$11,'Rate Card'!C$2:T$2,0)),"")}
A97: VERVE STAFFING | F97: Client | G97: Internal | H97: Forecast | I97: +/- | J97: Actuals | K97: +/- | L97: Verve Hours | M97: Verve Rate Card | N97: Client Hours | O97: Mark Up For viz only | BN97: =BN7
L98: Enter Hours | M98: Enter Rate in FX | N98: FALSE | O98: Adjust Hours
E99: Verve | F99: =BN99*N99 -> 0 | G99: =L99*M99*'Internal Budget'!$J$3 -> 0 | H99: =G99 -> 0 | I99: =G99-H99 -> 0 | J99: =sumif('Job Report'!I:I,B99,'Job Report'!H:H) -> 0 | K99: =if(C99=false,H99-J99,0) -> 0 | N99: =IFERROR(if($N$98=true,G99*1.2094/BN99,L99),"") | O99: =iferror((F99-G99)/G99,"") | P99: =L99-N99 -> 0 | BM99: {=IFERROR(index('Rate Card'!U$3:AF135,match(B99,'Rate Card'!B$3:B135,0),match(Assumptions!C$11,'Rate Card'!U$2:AF$2,0)),"")} | BN99: {=IFERROR(index('Rate Card'!$C$4:$T135, match(BM99,Controls!G$21:G135,0),match(Assumptions!$C$11,'Rate Card'!C$2:T$2,0)),"")}
E100: Verve | F100: =BN100*N100 -> 0 | G100: =L100*M100*'Internal Budget'!$J$3 -> 0 | H100: =G100 -> 0 | I100: =G100-H100 -> 0 | J100: =sumif('Job Report'!I:I,B100,'Job Report'!H:H) -> 0 | K100: =if(C100=false,H100-J100,0) -> 0 | N100: =IFERROR(if($N$98=true,G100*1.2094/BN100,L100),"") | O100: =iferror((F100-G100)/G100,"") | P100: =L100-N100 -> 0 | BM100: {=IFERROR(index('Rate Card'!U$3:AF135,match(B100,'Rate Card'!B$3:B135,0),match(Assumptions!C$11,'Rate Card'!U$2:AF$2,0)),"")} | BN100: {=IFERROR(index('Rate Card'!$C$4:$T135, match(BM100,Controls!G$21:G135,0),match(Assumptions!$C$11,'Rate Card'!C$2:T$2,0)),"")}
E101: Verve | F101: =BN101*N101 -> 0 | G101: =L101*M101*'Internal Budget'!$J$3 -> 0 | H101: =G101 -> 0 | I101: =G101-H101 -> 0 | J101: =sumif('Job Report'!I:I,B101,'Job Report'!H:H) -> 0 | K101: =if(C101=false,H101-J101,0) -> 0 | N101: =IFERROR(if($N$98=true,G101*1.2094/BN101,L101),"") | O101: =iferror((F101-G101)/G101,"") | P101: =L101-N101 -> 0 | BM101: {=IFERROR(index('Rate Card'!U$3:AF135,match(B101,'Rate Card'!B$3:B135,0),match(Assumptions!C$11,'Rate Card'!U$2:AF$2,0)),"")} | BN101: {=IFERROR(index('Rate Card'!$C$4:$T135, match(BM101,Controls!G$21:G135,0),match(Assumptions!$C$11,'Rate Card'!C$2:T$2,0)),"")}
E102: Verve | F102: =BN102*N102 -> 0 | G102: =L102*M102*'Internal Budget'!$J$3 -> 0 | H102: =G102 -> 0 | I102: =G102-H102 -> 0 | J102: =sumif('Job Report'!I:I,B102,'Job Report'!H:H) -> 0 | K102: =if(C102=false,H102-J102,0) -> 0 | N102: =IFERROR(if($N$98=true,G102*1.2094/BN102,L102),"") | O102: =iferror((F102-G102)/G102,"") | P102: =L102-N102 -> 0 | BM102: {=IFERROR(index('Rate Card'!U$3:AF135,match(B102,'Rate Card'!B$3:B135,0),match(Assumptions!C$11,'Rate Card'!U$2:AF$2,0)),"")} | BN102: {=IFERROR(index('Rate Card'!$C$4:$T135, match(BM102,Controls!G$21:G135,0),match(Assumptions!$C$11,'Rate Card'!C$2:T$2,0)),"")}
E103: Verve | F103: =BN103*N103 -> 0 | G103: =L103*M103*'Internal Budget'!$J$3 -> 0 | H103: =G103 -> 0 | I103: =G103-H103 -> 0 | J103: =sumif('Job Report'!I:I,B103,'Job Report'!H:H) -> 0 | K103: =if(C103=false,H103-J103,0) -> 0 | N103: =IFERROR(if($N$98=true,G103*1.2094/BN103,L103),"") | O103: =iferror((F103-G103)/G103,"") | P103: =L103-N103 -> 0 | BM103: {=IFERROR(index('Rate Card'!U$3:AF135,match(B103,'Rate Card'!B$3:B135,0),match(Assumptions!C$11,'Rate Card'!U$2:AF$2,0)),"")} | BN103: {=IFERROR(index('Rate Card'!$C$4:$T135, match(BM103,Controls!G$21:G135,0),match(Assumptions!$C$11,'Rate Card'!C$2:T$2,0)),"")}
...

Sheet Staffing Names
A1: STAFFING NAMES
A3: =IFERROR(__xludf.DUMMYFUNCTION("importrange(""https://docs.google.com/spreadsheets/d/1tPdrumQu7yTHPPe3CUfS8G2vUSXAfmvGb7cm2rQihRY/edit#gid=1195252998"",""Employee List!B:B"")"),"#REF!") -> #REF! | B3: Enter Additional Names Here Please ping Operations if you are adding new staff.

Sheet Client Staffing Calculator
A1: See notes on this cell for instructions. | C1: STAFFING CALCULATOR
D3: =sum(D6:D67) -> 0 | E3: =sum(E6:E67) -> 0 | G3: =iferror(H3-WEEKDAY(H3,3)-7,"") -> -12 | H3: =iferror(I3-WEEKDAY(I3,3)-7,"") | I3: =iferror(J3-WEEKDAY(J3,3)-7,"") -> -12 | J3: =iferror(K3-WEEKDAY(K3,3)-7,"") | K3: =iferror(L3-WEEKDAY(L3,3)-7,"") -> -12 | L3: =iferror(M3-WEEKDAY(M3,3)-7,"") | M3: =iferror(N3-WEEKDAY(N3,3)-7,"") -> -12 | N3: =iferror(O3-WEEKDAY(O3,3)-7,"") | ... AT3: =iferror(AU3-WEEKDAY(AU3,3)-7,"") | AU3: ='Internal Staffing Calculator'!BF5 -> -5 | AV3: =AU3+7 -> 2 | AW3: =AV3+7 -> 9 | AX3: =AW3+7 -> 16 | AY3: =AX3+7 -> 23 | AZ3: =AY3+7 -> 30 | BA3: =AZ3+7 -> 37
A5: Internal Role | B5: Hours to Compare | C5: Role | D5: Estimate | E5: Hours | G5: -40 | H5: -39 | I5: -38 | J5: -37 | K5: -36 | L5: -35 | M5: -34 | N5: -33 | O5: -32 | P5: -31 | Q5: -30 | R5: -29 | S5: -28 | T5: -27 | U5: -26 | V5: -25 | W5: -24 | X5: -23 | Y5: -22 | Z5: -21 | AA5: -20 | AB5: -19 | AC5: -18 | AD5: -17 | AE5: -16 | AF5: -15 | AG5: -14 | AH5: -13 | AI5: -12 | AJ5: -11 | AK5: -10 | AL5: -9 | AM5: -8 | AN5: -7 | AO5: -6 | AP5: -5 | AQ5: -4 | AR5: -3 | AS5: -2 | AT5: -1 | AU5: 0 | AV5: 1 | AW5: 2 | AX5: 3 | AY5: 4 | AZ5: 5 | BA5: 6
B6: {=iferror(index('Internal Staffing Calculator'!P:P,match(A6,'Internal Staffing Calculator'!B:B,0)),"")} | C6: {=iferror(index('Internal Staffing Calculator'!BM:BM,match(A6,'Internal Staffing Calculator'!B:B,0)),"")} | D6: {=iferror(index('Internal Staffing Calculator'!F:F,match(A6,'Internal Staffing Calculator'!B:B,0)),"")} | E6: =SUM(G6:BA6) -> 0 | G6: {=iferror(index('Internal Staffing Calculator'!$R$9:$BL$115, match($A6,'Internal Staffing Calculator'!$B$9:$B169,0),match(G$5,'Internal Staffing Calculator'!$R$7:$BL$7,0)),"")} | H6: {=iferror(index('Internal Staffing Calculator'!$R$9:$BL$115, match($A6,'Internal Staffing Calculator'!$B$9:$B169,0),match(H$5,'Internal Staffing Calculator'!$R$7:$BL$7,0)),"")} | I6: {=iferror(index('Internal Staffing Calculator'!$R$9:$BL$115, match($A6,'Internal Staffing Calculator'!$B$9:$B169,0),match(I$5,'Internal Staffing Calculator'!$R$7:$BL$7,0)),"")} | J6: {=iferror(index('Internal Staffing Calculator'!$R$9:$BL$115, match($A6,'Internal Staffing Calculator'!$B$9:$B169,0),match(J$5,'Internal Staffing Calculator'!$R$7:$BL$7,0)),"")} | K6: {=iferror(index('Internal Staffing Calculator'!$R$9:$BL$115, match($A6,'Internal Staffing Calculator'!$B$9:$B169,0),match(K$5,'Internal Staffing Calculator'!$R$7:$BL$7,0)),"")} | L6: {=iferror(index('Internal Staffing Calculator'!$R$9:$BL$115, match($A6,'Internal Staffing Calculator'!$B$9:$B169,0),match(L$5,'Internal Staffing Calculator'!$R$7:$BL$7,0)),"")} | M6: {=iferror(index('Internal Staffing Calculator'!$R$9:$BL$115, match($A6,'Internal Staffing Calculator'!$B$9:$B169,0),match(M$5,'Internal Staffing Calculator'!$R$7:$BL$7,0)),"")} | N6: {=iferror(index('Internal Staffing Calculator'!$R$9:$BL$115, match($A6,'Internal Staffing Calculator'!$B$9:$B169,0),match(N$5,'Internal Staffing Calculator'!$R$7:$BL$7,0)),"")} | ... BA6: {=iferror(index('Internal Staffing Calculator'!$R$9:$BL$115, match($A6,'Internal Staffing Calculator'!$B$9:$B169,0),match(BA$5,'Internal Staffing Calculator'!$R$7:$BL$7,0)),"")}
B7: {=iferror(index('Internal Staffing Calculator'!P:P,match(A7,'Internal Staffing Calculator'!B:B,0)),"")} | C7: {=iferror(index('Internal Staffing Calculator'!BM:BM,match(A7,'Internal Staffing Calculator'!B:B,0)),"")} | D7: {=iferror(index('Internal Staffing Calculator'!F:F,match(A7,'Internal Staffing Calculator'!B:B,0)),"")} | E7: =SUM(G7:BA7) -> 0 | G7: {=iferror(index('Internal Staffing Calculator'!$R$9:$BL$115, match($A7,'Internal Staffing Calculator'!$B$9:$B169,0),match(G$5,'Internal Staffing Calculator'!$R$7:$BL$7,0)),"")} | H7: {=iferror(index('Internal Staffing Calculator'!$R$9:$BL$115, match($A7,'Internal Staffing Calculator'!$B$9:$B169,0),match(H$5,'Internal Staffing Calculator'!$R$7:$BL$7,0)),"")} | I7: {=iferror(index('Internal Staffing Calculator'!$R$9:$BL$115, match($A7,'Internal Staffing Calculator'!$B$9:$B169,0),match(I$5,'Internal Staffing Calculator'!$R$7:$BL$7,0)),"")} | J7: {=iferror(index('Internal Staffing Calculator'!$R$9:$BL$115, match($A7,'Internal Staffing Calculator'!$B$9:$B169,0),match(J$5,'Internal Staffing Calculator'!$R$7:$BL$7,0)),"")} | K7: {=iferror(index('Internal Staffing Calculator'!$R$9:$BL$115, match($A7,'Internal Staffing Calculator'!$B$9:$B169,0),match(K$5,'Internal Staffing Calculator'!$R$7:$BL$7,0)),"")} | L7: {=iferror(index('Internal Staffing Calculator'!$R$9:$BL$115, match($A7,'Internal Staffing Calculator'!$B$9:$B169,0),match(L$5,'Internal Staffing Calculator'!$R$7:$BL$7,0)),"")} | M7: {=iferror(index('Internal Staffing Calculator'!$R$9:$BL$115, match($A7,'Internal Staffing Calculator'!$B$9:$B169,0),match(M$5,'Internal Staffing Calculator'!$R$7:$BL$7,0)),"")} | N7: {=iferror(index('Internal Staffing Calculator'!$R$9:$BL$115, match($A7,'Internal Staffing Calculator'!$B$9:$B169,0),match(N$5,'Internal Staffing Calculator'!$R$7:$BL$7,0)),"")} | ... BA7: {=iferror(index('Internal Staffing Calculator'!$R$9:$BL$115, match($A7,'Internal Staffing Calculator'!$B$9:$B169,0),match(BA$5,'Internal Staffing Calculator'!$R$7:$BL$7,0)),"")}
B8: {=iferror(index('Internal Staffing Calculator'!P:P,match(A8,'Internal Staffing Calculator'!B:B,0)),"")} | C8: {=iferror(index('Internal Staffing Calculator'!BM:BM,match(A8,'Internal Staffing Calculator'!B:B,0)),"")} | D8: {=iferror(index('Internal Staffing Calculator'!F:F,match(A8,'Internal Staffing Calculator'!B:B,0)),"")} | E8: =SUM(G8:BA8) -> 0 | G8: {=iferror(index('Internal Staffing Calculator'!$R$9:$BL$115, match($A8,'Internal Staffing Calculator'!$B$9:$B169,0),match(G$5,'Internal Staffing Calculator'!$R$7:$BL$7,0)),"")} | H8: {=iferror(index('Internal Staffing Calculator'!$R$9:$BL$115, match($A8,'Internal Staffing Calculator'!$B$9:$B169,0),match(H$5,'Internal Staffing Calculator'!$R$7:$BL$7,0)),"")} | I8: {=iferror(index('Internal Staffing Calculator'!$R$9:$BL$115, match($A8,'Internal Staffing Calculator'!$B$9:$B169,0),match(I$5,'Internal Staffing Calculator'!$R$7:$BL$7,0)),"")} | J8: {=iferror(index('Internal Staffing Calculator'!$R$9:$BL$115, match($A8,'Internal Staffing Calculator'!$B$9:$B169,0),match(J$5,'Internal Staffing Calculator'!$R$7:$BL$7,0)),"")} | K8: {=iferror(index('Internal Staffing Calculator'!$R$9:$BL$115, match($A8,'Internal Staffing Calculator'!$B$9:$B169,0),match(K$5,'Internal Staffing Calculator'!$R$7:$BL$7,0)),"")} | L8: {=iferror(index('Internal Staffing Calculator'!$R$9:$BL$115, match($A8,'Internal Staffing Calculator'!$B$9:$B169,0),match(L$5,'Internal Staffing Calculator'!$R$7:$BL$7,0)),"")} | M8: {=iferror(index('Internal Staffing Calculator'!$R$9:$BL$115, match($A8,'Internal Staffing Calculator'!$B$9:$B169,0),match(M$5,'Internal Staffing Calculator'!$R$7:$BL$7,0)),"")} | N8: {=iferror(index('Internal Staffing Calculator'!$R$9:$BL$115, match($A8,'Internal Staffing Calculator'!$B$9:$B169,0),match(N$5,'Internal Staffing Calculator'!$R$7:$BL$7,0)),"")} | ... BA8: {=iferror(index('Internal Staffing Calculator'!$R$9:$BL$115, match($A8,'Internal Staffing Calculator'!$B$9:$B169,0),match(BA$5,'Internal Staffing Calculator'!$R$7:$BL$7,0)),"")}
B9: {=iferror(index('Internal Staffing Calculator'!P:P,match(A9,'Internal Staffing Calculator'!B:B,0)),"")} | C9: {=iferror(index('Internal Staffing Calculator'!BM:BM,match(A9,'Internal Staffing Calculator'!B:B,0)),"")} | D9: {=iferror(index('Internal Staffing Calculator'!F:F,match(A9,'Internal Staffing Calculator'!B:B,0)),"")} | E9: =SUM(G9:BA9) -> 0 | G9: {=iferror(index('Internal Staffing Calculator'!$R$9:$BL$115, match($A9,'Internal Staffing Calculator'!$B$9:$B169,0),match(G$5,'Internal Staffing Calculator'!$R$7:$BL$7,0)),"")} | H9: {=iferror(index('Internal Staffing Calculator'!$R$9:$BL$115, match($A9,'Internal Staffing Calculator'!$B$9:$B169,0),match(H$5,'Internal Staffing Calculator'!$R$7:$BL$7,0)),"")} | I9: {=iferror(index('Internal Staffing Calculator'!$R$9:$BL$115, match($A9,'Internal Staffing Calculator'!$B$9:$B169,0),match(I$5,'Internal Staffing Calculator'!$R$7:$BL$7,0)),"")} | J9: {=iferror(index('Internal Staffing Calculator'!$R$9:$BL$115, match($A9,'Internal Staffing Calculator'!$B$9:$B169,0),match(J$5,'Internal Staffing Calculator'!$R$7:$BL$7,0)),"")} | K9: {=iferror(index('Internal Staffing Calculator'!$R$9:$BL$115, match($A9,'Internal Staffing Calculator'!$B$9:$B169,0),match(K$5,'Internal Staffing Calculator'!$R$7:$BL$7,0)),"")} | L9: {=iferror(index('Internal Staffing Calculator'!$R$9:$BL$115, match($A9,'Internal Staffing Calculator'!$B$9:$B169,0),match(L$5,'Internal Staffing Calculator'!$R$7:$BL$7,0)),"")} | M9: {=iferror(index('Internal Staffing Calculator'!$R$9:$BL$115, match($A9,'Internal Staffing Calculator'!$B$9:$B169,0),match(M$5,'Internal Staffing Calculator'!$R$7:$BL$7,0)),"")} | N9: {=iferror(index('Internal Staffing Calculator'!$R$9:$BL$115, match($A9,'Internal Staffing Calculator'!$B$9:$B169,0),match(N$5,'Internal Staffing Calculator'!$R$7:$BL$7,0)),"")} | ... BA9: {=iferror(index('Internal Staffing Calculator'!$R$9:$BL$115, match($A9,'Internal Staffing Calculator'!$B$9:$B169,0),match(BA$5,'Internal Staffing Calculator'!$R$7:$BL$7,0)),"")}
B10: {=iferror(index('Internal Staffing Calculator'!P:P,match(A10,'Internal Staffing Calculator'!B:B,0)),"")} | C10: {=iferror(index('Internal Staffing Calculator'!BM:BM,match(A10,'Internal Staffing Calculator'!B:B,0)),"")} | D10: {=iferror(index('Internal Staffing Calculator'!F:F,match(A10,'Internal Staffing Calculator'!B:B,0)),"")} | E10: =SUM(G10:BA10) -> 0 | G10: {=iferror(index('Internal Staffing Calculator'!$R$9:$BL$115, match($A10,'Internal Staffing Calculator'!$B$9:$B169,0),match(G$5,'Internal Staffing Calculator'!$R$7:$BL$7,0)),"")} | H10: {=iferror(index('Internal Staffing Calculator'!$R$9:$BL$115, match($A10,'Internal Staffing Calculator'!$B$9:$B169,0),match(H$5,'Internal Staffing Calculator'!$R$7:$BL$7,0)),"")} | I10: {=iferror(index('Internal Staffing Calculator'!$R$9:$BL$115, match($A10,'Internal Staffing Calculator'!$B$9:$B169,0),match(I$5,'Internal Staffing Calculator'!$R$7:$BL$7,0)),"")} | J10: {=iferror(index('Internal Staffing Calculator'!$R$9:$BL$115, match($A10,'Internal Staffing Calculator'!$B$9:$B169,0),match(J$5,'Internal Staffing Calculator'!$R$7:$BL$7,0)),"")} | K10: {=iferror(index('Internal Staffing Calculator'!$R$9:$BL$115, match($A10,'Internal Staffing Calculator'!$B$9:$B169,0),match(K$5,'Internal Staffing Calculator'!$R$7:$BL$7,0)),"")} | L10: {=iferror(index('Internal Staffing Calculator'!$R$9:$BL$115, match($A10,'Internal Staffing Calculator'!$B$9:$B169,0),match(L$5,'Internal Staffing Calculator'!$R$7:$BL$7,0)),"")} | M10: {=iferror(index('Internal Staffing Calculator'!$R$9:$BL$115, match($A10,'Internal Staffing Calculator'!$B$9:$B169,0),match(M$5,'Internal Staffing Calculator'!$R$7:$BL$7,0)),"")} | N10: {=iferror(index('Internal Staffing Calculator'!$R$9:$BL$115, match($A10,'Internal Staffing Calculator'!$B$9:$B169,0),match(N$5,'Internal Staffing Calculator'!$R$7:$BL$7,0)),"")} | ... BA10: {=iferror(index('Internal Staffing Calculator'!$R$9:$BL$115, match($A10,'Internal Staffing Calculator'!$B$9:$B169,0),match(BA$5,'Internal Staffing Calculator'!$R$7:$BL$7,0)),"")}
B11: {=iferror(index('Internal Staffing Calculator'!P:P,match(A11,'Internal Staffing Calculator'!B:B,0)),"")} | C11: {=iferror(index('Internal Staffing Calculator'!BM:BM,match(A11,'Internal Staffing Calculator'!B:B,0)),"")} | D11: {=iferror(index('Internal Staffing Calculator'!F:F,match(A11,'Internal Staffing Calculator'!B:B,0)),"")} | E11: =SUM(G11:BA11) -> 0 | G11: {=iferror(index('Internal Staffing Calculator'!$R$9:$BL$115, match($A11,'Internal Staffing Calculator'!$B$9:$B169,0),match(G$5,'Internal Staffing Calculator'!$R$7:$BL$7,0)),"")} | H11: {=iferror(index('Internal Staffing Calculator'!$R$9:$BL$115, match($A11,'Internal Staffing Calculator'!$B$9:$B169,0),match(H$5,'Internal Staffing Calculator'!$R$7:$BL$7,0)),"")} | I11: {=iferror(index('Internal Staffing Calculator'!$R$9:$BL$115, match($A11,'Internal Staffing Calculator'!$B$9:$B169,0),match(I$5,'Internal Staffing Calculator'!$R$7:$BL$7,0)),"")} | J11: {=iferror(index('Internal Staffing Calculator'!$R$9:$BL$115, match($A11,'Internal Staffing Calculator'!$B$9:$B169,0),match(J$5,'Internal Staffing Calculator'!$R$7:$BL$7,0)),"")} | K11: {=iferror(index('Internal Staffing Calculator'!$R$9:$BL$115, match($A11,'Internal Staffing Calculator'!$B$9:$B169,0),match(K$5,'Internal Staffing Calculator'!$R$7:$BL$7,0)),"")} | L11: {=iferror(index('Internal Staffing Calculator'!$R$9:$BL$115, match($A11,'Internal Staffing Calculator'!$B$9:$B169,0),match(L$5,'Internal Staffing Calculator'!$R$7:$BL$7,0)),"")} | M11: {=iferror(index('Internal Staffing Calculator'!$R$9:$BL$115, match($A11,'Internal Staffing Calculator'!$B$9:$B169,0),match(M$5,'Internal Staffing Calculator'!$R$7:$BL$7,0)),"")} | N11: {=iferror(index('Internal Staffing Calculator'!$R$9:$BL$115, match($A11,'Internal Staffing Calculator'!$B$9:$B169,0),match(N$5,'Internal Staffing Calculator'!$R$7:$BL$7,0)),"")} | ... BA11: {=iferror(index('Internal Staffing Calculator'!$R$9:$BL$115, match($A11,'Internal Staffing Calculator'!$B$9:$B169,0),match(BA$5,'Internal Staffing Calculator'!$R$7:$BL$7,0)),"")}
B12: {=iferror(index('Internal Staffing Calculator'!P:P,match(A12,'Internal Staffing Calculator'!B:B,0)),"")} | C12: {=iferror(index('Internal Staffing Calculator'!BM:BM,match(A12,'Internal Staffing Calculator'!B:B,0)),"")} | D12: {=iferror(index('Internal Staffing Calculator'!F:F,match(A12,'Internal Staffing Calculator'!B:B,0)),"")} | E12: =SUM(G12:BA12) -> 0 | G12: {=iferror(index('Internal Staffing Calculator'!$R$9:$BL$115, match($A12,'Internal Staffing Calculator'!$B$9:$B169,0),match(G$5,'Internal Staffing Calculator'!$R$7:$BL$7,0)),"")} | H12: {=iferror(index('Internal Staffing Calculator'!$R$9:$BL$115, match($A12,'Internal Staffing Calculator'!$B$9:$B169,0),match(H$5,'Internal Staffing Calculator'!$R$7:$BL$7,0)),"")} | I12: {=iferror(index('Internal Staffing Calculator'!$R$9:$BL$115, match($A12,'Internal Staffing Calculator'!$B$9:$B169,0),match(I$5,'Internal Staffing Calculator'!$R$7:$BL$7,0)),"")} | J12: {=iferror(index('Internal Staffing Calculator'!$R$9:$BL$115, match($A12,'Internal Staffing Calculator'!$B$9:$B169,0),match(J$5,'Internal Staffing Calculator'!$R$7:$BL$7,0)),"")} | K12: {=iferror(index('Internal Staffing Calculator'!$R$9:$BL$115, match($A12,'Internal Staffing Calculator'!$B$9:$B169,0),match(K$5,'Internal Staffing Calculator'!$R$7:$BL$7,0)),"")} | L12: {=iferror(index('Internal Staffing Calculator'!$R$9:$BL$115, match($A12,'Internal Staffing Calculator'!$B$9:$B169,0),match(L$5,'Internal Staffing Calculator'!$R$7:$BL$7,0)),"")} | M12: {=iferror(index('Internal Staffing Calculator'!$R$9:$BL$115, match($A12,'Internal Staffing Calculator'!$B$9:$B169,0),match(M$5,'Internal Staffing Calculator'!$R$7:$BL$7,0)),"")} | N12: {=iferror(index('Internal Staffing Calculator'!$R$9:$BL$115, match($A12,'Internal Staffing Calculator'!$B$9:$B169,0),match(N$5,'Internal Staffing Calculator'!$R$7:$BL$7,0)),"")} | ... BA12: {=iferror(index('Internal Staffing Calculator'!$R$9:$BL$115, match($A12,'Internal Staffing Calculator'!$B$9:$B169,0),match(BA$5,'Internal Staffing Calculator'!$R$7:$BL$7,0)),"")}
B13: {=iferror(index('Internal Staffing Calculator'!P:P,match(A13,'Internal Staffing Calculator'!B:B,0)),"")} | C13: {=iferror(index('Internal Staffing Calculator'!BM:BM,match(A13,'Internal Staffing Calculator'!B:B,0)),"")} | D13: {=iferror(index('Internal Staffing Calculator'!F:F,match(A13,'Internal Staffing Calculator'!B:B,0)),"")} | E13: =SUM(G13:BA13) -> 0 | G13: {=iferror(index('Internal Staffing Calculator'!$R$9:$BL$115, match($A13,'Internal Staffing Calculator'!$B$9:$B169,0),match(G$5,'Internal Staffing Calculator'!$R$7:$BL$7,0)),"")} | H13: {=iferror(index('Internal Staffing Calculator'!$R$9:$BL$115, match($A13,'Internal Staffing Calculator'!$B$9:$B169,0),match(H$5,'Internal Staffing Calculator'!$R$7:$BL$7,0)),"")} | I13: {=iferror(index('Internal Staffing Calculator'!$R$9:$BL$115, match($A13,'Internal Staffing Calculator'!$B$9:$B169,0),match(I$5,'Internal Staffing Calculator'!$R$7:$BL$7,0)),"")} | J13: {=iferror(index('Internal Staffing Calculator'!$R$9:$BL$115, match($A13,'Internal Staffing Calculator'!$B$9:$B169,0),match(J$5,'Internal Staffing Calculator'!$R$7:$BL$7,0)),"")} | K13: {=iferror(index('Internal Staffing Calculator'!$R$9:$BL$115, match($A13,'Internal Staffing Calculator'!$B$9:$B169,0),match(K$5,'Internal Staffing Calculator'!$R$7:$BL$7,0)),"")} | L13: {=iferror(index('Internal Staffing Calculator'!$R$9:$BL$115, match($A13,'Internal Staffing Calculator'!$B$9:$B169,0),match(L$5,'Internal Staffing Calculator'!$R$7:$BL$7,0)),"")} | M13: {=iferror(index('Internal Staffing Calculator'!$R$9:$BL$115, match($A13,'Internal Staffing Calculator'!$B$9:$B169,0),match(M$5,'Internal Staffing Calculator'!$R$7:$BL$7,0)),"")} | N13: {=iferror(index('Internal Staffing Calculator'!$R$9:$BL$115, match($A13,'Internal Staffing Calculator'!$B$9:$B169,0),match(N$5,'Internal Staffing Calculator'!$R$7:$BL$7,0)),"")} | ... BA13: {=iferror(index('Internal Staffing Calculator'!$R$9:$BL$115, match($A13,'Internal Staffing Calculator'!$B$9:$B169,0),match(BA$5,'Internal Staffing Calculator'!$R$7:$BL$7,0)),"")}
B14: {=iferror(index('Internal Staffing Calculator'!P:P,match(A14,'Internal Staffing Calculator'!B:B,0)),"")} | C14: {=iferror(index('Internal Staffing Calculator'!BM:BM,match(A14,'Internal Staffing Calculator'!B:B,0)),"")} | D14: {=iferror(index('Internal Staffing Calculator'!F:F,match(A14,'Internal Staffing Calculator'!B:B,0)),"")} | E14: =SUM(G14:BA14) -> 0 | G14: {=iferror(index('Internal Staffing Calculator'!$R$9:$BL$115, match($A14,'Internal Staffing Calculator'!$B$9:$B169,0),match(G$5,'Internal Staffing Calculator'!$R$7:$BL$7,0)),"")} | H14: {=iferror(index('Internal Staffing Calculator'!$R$9:$BL$115, match($A14,'Internal Staffing Calculator'!$B$9:$B169,0),match(H$5,'Internal Staffing Calculator'!$R$7:$BL$7,0)),"")} | I14: {=iferror(index('Internal Staffing Calculator'!$R$9:$BL$115, match($A14,'Internal Staffing Calculator'!$B$9:$B169,0),match(I$5,'Internal Staffing Calculator'!$R$7:$BL$7,0)),"")} | J14: {=iferror(index('Internal Staffing Calculator'!$R$9:$BL$115, match($A14,'Internal Staffing Calculator'!$B$9:$B169,0),match(J$5,'Internal Staffing Calculator'!$R$7:$BL$7,0)),"")} | K14: {=iferror(index('Internal Staffing Calculator'!$R$9:$BL$115, match($A14,'Internal Staffing Calculator'!$B$9:$B169,0),match(K$5,'Internal Staffing Calculator'!$R$7:$BL$7,0)),"")} | L14: {=iferror(index('Internal Staffing Calculator'!$R$9:$BL$115, match($A14,'Internal Staffing Calculator'!$B$9:$B169,0),match(L$5,'Internal Staffing Calculator'!$R$7:$BL$7,0)),"")} | M14: {=iferror(index('Internal Staffing Calculator'!$R$9:$BL$115, match($A14,'Internal Staffing Calculator'!$B$9:$B169,0),match(M$5,'Internal Staffing Calculator'!$R$7:$BL$7,0)),"")} | N14: {=iferror(index('Internal Staffing Calculator'!$R$9:$BL$115, match($A14,'Internal Staffing Calculator'!$B$9:$B169,0),match(N$5,'Internal Staffing Calculator'!$R$7:$BL$7,0)),"")} | ... BA14: {=iferror(index('Internal Staffing Calculator'!$R$9:$BL$115, match($A14,'Internal Staffing Calculator'!$B$9:$B169,0),match(BA$5,'Internal Staffing Calculator'!$R$7:$BL$7,0)),"")}
B15: {=iferror(index('Internal Staffing Calculator'!P:P,match(A15,'Internal Staffing Calculator'!B:B,0)),"")} | C15: {=iferror(index('Internal Staffing Calculator'!BM:BM,match(A15,'Internal Staffing Calculator'!B:B,0)),"")} | D15: {=iferror(index('Internal Staffing Calculator'!F:F,match(A15,'Internal Staffing Calculator'!B:B,0)),"")} | E15: =SUM(G15:BA15) -> 0 | G15: {=iferror(index('Internal Staffing Calculator'!$R$9:$BL$115, match($A15,'Internal Staffing Calculator'!$B$9:$B169,0),match(G$5,'Internal Staffing Calculator'!$R$7:$BL$7,0)),"")} | H15: {=iferror(index('Internal Staffing Calculator'!$R$9:$BL$115, match($A15,'Internal Staffing Calculator'!$B$9:$B169,0),match(H$5,'Internal Staffing Calculator'!$R$7:$BL$7,0)),"")} | I15: {=iferror(index('Internal Staffing Calculator'!$R$9:$BL$115, match($A15,'Internal Staffing Calculator'!$B$9:$B169,0),match(I$5,'Internal Staffing Calculator'!$R$7:$BL$7,0)),"")} | J15: {=iferror(index('Internal Staffing Calculator'!$R$9:$BL$115, match($A15,'Internal Staffing Calculator'!$B$9:$B169,0),match(J$5,'Internal Staffing Calculator'!$R$7:$BL$7,0)),"")} | K15: {=iferror(index('Internal Staffing Calculator'!$R$9:$BL$115, match($A15,'Internal Staffing Calculator'!$B$9:$B169,0),match(K$5,'Internal Staffing Calculator'!$R$7:$BL$7,0)),"")} | L15: {=iferror(index('Internal Staffing Calculator'!$R$9:$BL$115, match($A15,'Internal Staffing Calculator'!$B$9:$B169,0),match(L$5,'Internal Staffing Calculator'!$R$7:$BL$7,0)),"")} | M15: {=iferror(index('Internal Staffing Calculator'!$R$9:$BL$115, match($A15,'Internal Staffing Calculator'!$B$9:$B169,0),match(M$5,'Internal Staffing Calculator'!$R$7:$BL$7,0)),"")} | N15: {=iferror(index('Internal Staffing Calculator'!$R$9:$BL$115, match($A15,'Internal Staffing Calculator'!$B$9:$B169,0),match(N$5,'Internal Staffing Calculator'!$R$7:$BL$7,0)),"")} | ... BA15: {=iferror(index('Internal Staffing Calculator'!$R$9:$BL$115, match($A15,'Internal Staffing Calculator'!$B$9:$B169,0),match(BA$5,'Internal Staffing Calculator'!$R$7:$BL$7,0)),"")}
B16: {=iferror(index('Internal Staffing Calculator'!P:P,match(A16,'Internal Staffing Calculator'!B:B,0)),"")} | C16: {=iferror(index('Internal Staffing Calculator'!BM:BM,match(A16,'Internal Staffing Calculator'!B:B,0)),"")} | D16: {=iferror(index('Internal Staffing Calculator'!F:F,match(A16,'Internal Staffing Calculator'!B:B,0)),"")} | E16: =SUM(G16:BA16) -> 0 | G16: {=iferror(index('Internal Staffing Calculator'!$R$9:$BL$115, match($A16,'Internal Staffing Calculator'!$B$9:$B169,0),match(G$5,'Internal Staffing Calculator'!$R$7:$BL$7,0)),"")} | H16: {=iferror(index('Internal Staffing Calculator'!$R$9:$BL$115, match($A16,'Internal Staffing Calculator'!$B$9:$B169,0),match(H$5,'Internal Staffing Calculator'!$R$7:$BL$7,0)),"")} | I16: {=iferror(index('Internal Staffing Calculator'!$R$9:$BL$115, match($A16,'Internal Staffing Calculator'!$B$9:$B169,0),match(I$5,'Internal Staffing Calculator'!$R$7:$BL$7,0)),"")} | J16: {=iferror(index('Internal Staffing Calculator'!$R$9:$BL$115, match($A16,'Internal Staffing Calculator'!$B$9:$B169,0),match(J$5,'Internal Staffing Calculator'!$R$7:$BL$7,0)),"")} | K16: {=iferror(index('Internal Staffing Calculator'!$R$9:$BL$115, match($A16,'Internal Staffing Calculator'!$B$9:$B169,0),match(K$5,'Internal Staffing Calculator'!$R$7:$BL$7,0)),"")} | L16: {=iferror(index('Internal Staffing Calculator'!$R$9:$BL$115, match($A16,'Internal Staffing Calculator'!$B$9:$B169,0),match(L$5,'Internal Staffing Calculator'!$R$7:$BL$7,0)),"")} | M16: {=iferror(index('Internal Staffing Calculator'!$R$9:$BL$115, match($A16,'Internal Staffing Calculator'!$B$9:$B169,0),match(M$5,'Internal Staffing Calculator'!$R$7:$BL$7,0)),"")} | N16: {=iferror(index('Internal Staffing Calculator'!$R$9:$BL$115, match($A16,'Internal Staffing Calculator'!$B$9:$B169,0),match(N$5,'Internal Staffing Calculator'!$R$7:$BL$7,0)),"")} | ... BA16: {=iferror(index('Internal Staffing Calculator'!$R$9:$BL$115, match($A16,'Internal Staffing Calculator'!$B$9:$B169,0),match(BA$5,'Internal Staffing Calculator'!$R$7:$BL$7,0)),"")}
B17: {=iferror(index('Internal Staffing Calculator'!P:P,match(A17,'Internal Staffing Calculator'!B:B,0)),"")} | C17: {=iferror(index('Internal Staffing Calculator'!BM:BM,match(A17,'Internal Staffing Calculator'!B:B,0)),"")} | D17: {=iferror(index('Internal Staffing Calculator'!F:F,match(A17,'Internal Staffing Calculator'!B:B,0)),"")} | E17: =SUM(G17:BA17) -> 0 | G17: {=iferror(index('Internal Staffing Calculator'!$R$9:$BL$115, match($A17,'Internal Staffing Calculator'!$B$9:$B169,0),match(G$5,'Internal Staffing Calculator'!$R$7:$BL$7,0)),"")} | H17: {=iferror(index('Internal Staffing Calculator'!$R$9:$BL$115, match($A17,'Internal Staffing Calculator'!$B$9:$B169,0),match(H$5,'Internal Staffing Calculator'!$R$7:$BL$7,0)),"")} | I17: {=iferror(index('Internal Staffing Calculator'!$R$9:$BL$115, match($A17,'Internal Staffing Calculator'!$B$9:$B169,0),match(I$5,'Internal Staffing Calculator'!$R$7:$BL$7,0)),"")} | J17: {=iferror(index('Internal Staffing Calculator'!$R$9:$BL$115, match($A17,'Internal Staffing Calculator'!$B$9:$B169,0),match(J$5,'Internal Staffing Calculator'!$R$7:$BL$7,0)),"")} | K17: {=iferror(index('Internal Staffing Calculator'!$R$9:$BL$115, match($A17,'Internal Staffing Calculator'!$B$9:$B169,0),match(K$5,'Internal Staffing Calculator'!$R$7:$BL$7,0)),"")} | L17: {=iferror(index('Internal Staffing Calculator'!$R$9:$BL$115, match($A17,'Internal Staffing Calculator'!$B$9:$B169,0),match(L$5,'Internal Staffing Calculator'!$R$7:$BL$7,0)),"")} | M17: {=iferror(index('Internal Staffing Calculator'!$R$9:$BL$115, match($A17,'Internal Staffing Calculator'!$B$9:$B169,0),match(M$5,'Internal Staffing Calculator'!$R$7:$BL$7,0)),"")} | N17: {=iferror(index('Internal Staffing Calculator'!$R$9:$BL$115, match($A17,'Internal Staffing Calculator'!$B$9:$B169,0),match(N$5,'Internal Staffing Calculator'!$R$7:$BL$7,0)),"")} | ... BA17: {=iferror(index('Internal Staffing Calculator'!$R$9:$BL$115, match($A17,'Internal Staffing Calculator'!$B$9:$B169,0),match(BA$5,'Internal Staffing Calculator'!$R$7:$BL$7,0)),"")}
B18: {=iferror(index('Internal Staffing Calculator'!P:P,match(A18,'Internal Staffing Calculator'!B:B,0)),"")} | C18: {=iferror(index('Internal Staffing Calculator'!BM:BM,match(A18,'Internal Staffing Calculator'!B:B,0)),"")} | D18: {=iferror(index('Internal Staffing Calculator'!F:F,match(A18,'Internal Staffing Calculator'!B:B,0)),"")} | E18: =SUM(G18:BA18) -> 0 | G18: {=iferror(index('Internal Staffing Calculator'!$R$9:$BL$115, match($A18,'Internal Staffing Calculator'!$B$9:$B169,0),match(G$5,'Internal Staffing Calculator'!$R$7:$BL$7,0)),"")} | H18: {=iferror(index('Internal Staffing Calculator'!$R$9:$BL$115, match($A18,'Internal Staffing Calculator'!$B$9:$B169,0),match(H$5,'Internal Staffing Calculator'!$R$7:$BL$7,0)),"")} | I18: {=iferror(index('Internal Staffing Calculator'!$R$9:$BL$115, match($A18,'Internal Staffing Calculator'!$B$9:$B169,0),match(I$5,'Internal Staffing Calculator'!$R$7:$BL$7,0)),"")} | J18: {=iferror(index('Internal Staffing Calculator'!$R$9:$BL$115, match($A18,'Internal Staffing Calculator'!$B$9:$B169,0),match(J$5,'Internal Staffing Calculator'!$R$7:$BL$7,0)),"")} | K18: {=iferror(index('Internal Staffing Calculator'!$R$9:$BL$115, match($A18,'Internal Staffing Calculator'!$B$9:$B169,0),match(K$5,'Internal Staffing Calculator'!$R$7:$BL$7,0)),"")} | L18: {=iferror(index('Internal Staffing Calculator'!$R$9:$BL$115, match($A18,'Internal Staffing Calculator'!$B$9:$B169,0),match(L$5,'Internal Staffing Calculator'!$R$7:$BL$7,0)),"")} | M18: {=iferror(index('Internal Staffing Calculator'!$R$9:$BL$115, match($A18,'Internal Staffing Calculator'!$B$9:$B169,0),match(M$5,'Internal Staffing Calculator'!$R$7:$BL$7,0)),"")} | N18: {=iferror(index('Internal Staffing Calculator'!$R$9:$BL$115, match($A18,'Internal Staffing Calculator'!$B$9:$B169,0),match(N$5,'Internal Staffing Calculator'!$R$7:$BL$7,0)),"")} | ... BA18: {=iferror(index('Internal Staffing Calculator'!$R$9:$BL$115, match($A18,'Internal Staffing Calculator'!$B$9:$B169,0),match(BA$5,'Internal Staffing Calculator'!$R$7:$BL$7,0)),"")}
B19: {=iferror(index('Internal Staffing Calculator'!P:P,match(A19,'Internal Staffing Calculator'!B:B,0)),"")} | C19: {=iferror(index('Internal Staffing Calculator'!BM:BM,match(A19,'Internal Staffing Calculator'!B:B,0)),"")} | D19: {=iferror(index('Internal Staffing Calculator'!F:F,match(A19,'Internal Staffing Calculator'!B:B,0)),"")} | E19: =SUM(G19:BA19) -> 0 | G19: {=iferror(index('Internal Staffing Calculator'!$R$9:$BL$115, match($A19,'Internal Staffing Calculator'!$B$9:$B169,0),match(G$5,'Internal Staffing Calculator'!$R$7:$BL$7,0)),"")} | H19: {=iferror(index('Internal Staffing Calculator'!$R$9:$BL$115, match($A19,'Internal Staffing Calculator'!$B$9:$B169,0),match(H$5,'Internal Staffing Calculator'!$R$7:$BL$7,0)),"")} | I19: {=iferror(index('Internal Staffing Calculator'!$R$9:$BL$115, match($A19,'Internal Staffing Calculator'!$B$9:$B169,0),match(I$5,'Internal Staffing Calculator'!$R$7:$BL$7,0)),"")} | J19: {=iferror(index('Internal Staffing Calculator'!$R$9:$BL$115, match($A19,'Internal Staffing Calculator'!$B$9:$B169,0),match(J$5,'Internal Staffing Calculator'!$R$7:$BL$7,0)),"")} | K19: {=iferror(index('Internal Staffing Calculator'!$R$9:$BL$115, match($A19,'Internal Staffing Calculator'!$B$9:$B169,0),match(K$5,'Internal Staffing Calculator'!$R$7:$BL$7,0)),"")} | L19: {=iferror(index('Internal Staffing Calculator'!$R$9:$BL$115, match($A19,'Internal Staffing Calculator'!$B$9:$B169,0),match(L$5,'Internal Staffing Calculator'!$R$7:$BL$7,0)),"")} | M19: {=iferror(index('Internal Staffing Calculator'!$R$9:$BL$115, match($A19,'Internal Staffing Calculator'!$B$9:$B169,0),match(M$5,'Internal Staffing Calculator'!$R$7:$BL$7,0)),"")} | N19: {=iferror(index('Internal Staffing Calculator'!$R$9:$BL$115, match($A19,'Internal Staffing Calculator'!$B$9:$B169,0),match(N$5,'Internal Staffing Calculator'!$R$7:$BL$7,0)),"")} | ... BA19: {=iferror(index('Internal Staffing Calculator'!$R$9:$BL$115, match($A19,'Internal Staffing Calculator'!$B$9:$B169,0),match(BA$5,'Internal Staffing Calculator'!$R$7:$BL$7,0)),"")}
B20: {=iferror(index('Internal Staffing Calculator'!P:P,match(A20,'Internal Staffing Calculator'!B:B,0)),"")} | C20: {=iferror(index('Internal Staffing Calculator'!BM:BM,match(A20,'Internal Staffing Calculator'!B:B,0)),"")} | D20: {=iferror(index('Internal Staffing Calculator'!F:F,match(A20,'Internal Staffing Calculator'!B:B,0)),"")} | E20: =SUM(G20:BA20) -> 0 | G20: {=iferror(index('Internal Staffing Calculator'!$R$9:$BL$115, match($A20,'Internal Staffing Calculator'!$B$9:$B169,0),match(G$5,'Internal Staffing Calculator'!$R$7:$BL$7,0)),"")} | H20: {=iferror(index('Internal Staffing Calculator'!$R$9:$BL$115, match($A20,'Internal Staffing Calculator'!$B$9:$B169,0),match(H$5,'Internal Staffing Calculator'!$R$7:$BL$7,0)),"")} | I20: {=iferror(index('Internal Staffing Calculator'!$R$9:$BL$115, match($A20,'Internal Staffing Calculator'!$B$9:$B169,0),match(I$5,'Internal Staffing Calculator'!$R$7:$BL$7,0)),"")} | J20: {=iferror(index('Internal Staffing Calculator'!$R$9:$BL$115, match($A20,'Internal Staffing Calculator'!$B$9:$B169,0),match(J$5,'Internal Staffing Calculator'!$R$7:$BL$7,0)),"")} | K20: {=iferror(index('Internal Staffing Calculator'!$R$9:$BL$115, match($A20,'Internal Staffing Calculator'!$B$9:$B169,0),match(K$5,'Internal Staffing Calculator'!$R$7:$BL$7,0)),"")} | L20: {=iferror(index('Internal Staffing Calculator'!$R$9:$BL$115, match($A20,'Internal Staffing Calculator'!$B$9:$B169,0),match(L$5,'Internal Staffing Calculator'!$R$7:$BL$7,0)),"")} | M20: {=iferror(index('Internal Staffing Calculator'!$R$9:$BL$115, match($A20,'Internal Staffing Calculator'!$B$9:$B169,0),match(M$5,'Internal Staffing Calculator'!$R$7:$BL$7,0)),"")} | N20: {=iferror(index('Internal Staffing Calculator'!$R$9:$BL$115, match($A20,'Internal Staffing Calculator'!$B$9:$B169,0),match(N$5,'Internal Staffing Calculator'!$R$7:$BL$7,0)),"")} | ... BA20: {=iferror(index('Internal Staffing Calculator'!$R$9:$BL$115, match($A20,'Internal Staffing Calculator'!$B$9:$B169,0),match(BA$5,'Internal Staffing Calculator'!$R$7:$BL$7,0)),"")}
